Workbook

Sheet Cell Referencing (2)
A2: S no | B2: Names | C2: Hindi | D2: English | E2: Maths | F2: Science | G2: Total
A3: 1 | B3: Aarav Sharma | C3: 41 | D3: 39 | E3: 75 | F3: 34
A4: 2 | B4: Riya Verma | C4: 67 | D4: 57 | E4: 73 | F4: 47
A5: 3 | B5: Vivaan Mehta | C5: 22 | D5: 77 | E5: 29 | F5: 93
A6: 4 | B6: Ananya Iyer | C6: 58 | D6: 80 | E6: 28 | F6: 92
A7: 5 | B7: Karan Patel | C7: 89 | D7: 69 | E7: 92 | F7: 25
A8: 6 | B8: Sanya Malhotra | C8: 43 | D8: 20 | E8: 66 | F8: 50
A9: 7 | B9: Rahul Nair | C9: 21 | D9: 27 | E9: 70 | F9: 53
A10: 8 | B10: Pooja Deshmukh | C10: 21 | D10: 35 | E10: 36 | F10: 41
A11: 9 | B11: Aditya Reddy | C11: 61 | D11: 19 | E11: 25 | F11: 73
A12: 10 | B12: Meera Kapoor | C12: 69 | D12: 32 | E12: 59 | F12: 41
A13: 11 | B13: Rohan Bansal | C13: 27 | D13: 75 | E13: 68 | F13: 79
A14: 12 | B14: Ishita Choudhary | C14: 76 | D14: 54 | E14: 40 | F14: 30
... A17: 15 | B17: Kabir Saxena | C17: 15 | D17: 95 | E17: 29 | F17: 64
A30: Total Marks | F30: 400
A31: S no | B31: Names | C31: Hindi | D31: English | E31: Maths | F31: Science | G31: Total | H31: % | I31: %
A32: 1 | B32: Aarav Sharma | C32: 41 | D32: 39 | E32: 75 | F32: 34 | G32: =SUM(C32:F32) -> 189
A33: 2 | B33: Riya Verma | C33: 67 | D33: 57 | E33: 73 | F33: 47 | G33: =SUM(C33:F33) -> 244
A34: 3 | B34: Vivaan Mehta | C34: 22 | D34: 77 | E34: 29 | F34: 93 | G34: =SUM(C34:F34) -> 221
A35: 4 | B35: Ananya Iyer | C35: 58 | D35: 80 | E35: 28 | F35: 92 | G35: =SUM(C35:F35) -> 258
A36: 5 | B36: Karan Patel | C36: 89 | D36: 69 | E36: 92 | F36: 25 | G36: =SUM(C36:F36) -> 275
A37: 6 | B37: Sanya Malhotra | C37: 43 | D37: 20 | E37: 66 | F37: 50 | G37: =SUM(C37:F37) -> 179
A38: 7 | B38: Rahul Nair | C38: 21 | D38: 27 | E38: 70 | F38: 53 | G38: =SUM(C38:F38) -> 171
A39: 8 | B39: Pooja Deshmukh | C39: 21 | D39: 35 | E39: 36 | F39: 41 | G39: =SUM(C39:F39) -> 133
A40: 9 | B40: Aditya Reddy | C40: 61 | D40: 19 | E40: 25 | F40: 73 | G40: =SUM(C40:F40) -> 178
A41: 10 | B41: Meera Kapoor | C41: 69 | D41: 32 | E41: 59 | F41: 41 | G41: =SUM(C41:F41) -> 201
A42: 11 | B42: Rohan Bansal | C42: 27 | D42: 75 | E42: 68 | F42: 79 | G42: =SUM(C42:F42) -> 249
A43: 12 | B43: Ishita Choudhary | C43: 76 | D43: 54 | E43: 40 | F43: 30 | G43: =SUM(C43:F43) -> 200
... A46: 15 | B46: Kabir Saxena | C46: 15 | D46: 95 | E46: 29 | F46: 64 | G46: =SUM(C46:F46) -> 203
A61: Total Marks | F61: 400
A62: S no | B62: Names | C62: Hindi | D62: English | E62: Maths | F62: Science | G62: Total | H62: % | I62: Hindi % | J62: English % | K62: Maths % | L62: Science %
A63: 1 | B63: Aarav Sharma | C63: 41 | D63: 39 | E63: 75 | F63: 34 | G63: =SUM(C63:F63) -> 189 | H63: =G63/$F$61 -> 0.4725
A64: 2 | B64: Riya Verma | C64: 67 | D64: 57 | E64: 73 | F64: 47 | G64: =SUM(C64:F64) -> 244 | H64: =G64/$F$61 -> 0.61
A65: 3 | B65: Vivaan Mehta | C65: 22 | D65: 77 | E65: 29 | F65: 93 | G65: =SUM(C65:F65) -> 221 | H65: =G65/$F$61 -> 0.5525
A66: 4 | B66: Ananya Iyer | C66: 58 | D66: 80 | E66: 28 | F66: 92 | G66: =SUM(C66:F66) -> 258 | H66: =G66/$F$61 -> 0.645
A67: 5 | B67: Karan Patel | C67: 89 | D67: 69 | E67: 92 | F67: 25 | G67: =SUM(C67:F67) -> 275 | H67: =G67/$F$61 -> 0.6875
A68: 6 | B68: Sanya Malhotra | C68: 43 | D68: 20 | E68: 66 | F68: 50 | G68: =SUM(C68:F68) -> 179 | H68: =G68/$F$61 -> 0.4475
A69: 7 | B69: Rahul Nair | C69: 21 | D69: 27 | E69: 70 | F69: 53 | G69: =SUM(C69:F69) -> 171 | H69: =G69/$F$61 -> 0.4275
A70: 8 | B70: Pooja Deshmukh | C70: 21 | D70: 35 | E70: 36 | F70: 41 | G70: =SUM(C70:F70) -> 133 | H70: =G70/$F$61 -> 0.3325
A71: 9 | B71: Aditya Reddy | C71: 61 | D71: 19 | E71: 25 | F71: 73 | G71: =SUM(C71:F71) -> 178 | H71: =G71/$F$61 -> 0.445
A72: 10 | B72: Meera Kapoor | C72: 69 | D72: 32 | E72: 59 | F72: 41 | G72: =SUM(C72:F72) -> 201 | H72: =G72/$F$61 -> 0.5025
A73: 11 | B73: Rohan Bansal | C73: 27 | D73: 75 | E73: 68 | F73: 79 | G73: =SUM(C73:F73) -> 249 | H73: =G73/$F$61 -> 0.6225
A74: 12 | B74: Ishita Choudhary | C74: 76 | D74: 54 | E74: 40 | F74: 30 | G74: =SUM(C74:F74) -> 200 | H74: =G74/$F$61 -> 0.5
A75: 13 | B75: Arjun Bhardwaj | C75: 29 | D75: 15 | E75: 81 | F75: 56 | G75: =SUM(C75:F75) -> 181 | H75: =G75/$F$61 -> 0.4525
B93: Total Marks | G93: 400
B94: S no | C94: Names | D94: Hindi | E94: English | F94: Maths | G94: Science | H94: Total | I94: % | J94: Rank
B95: 1 | C95: Aarav Sharma | D95: 41 | E95: 39 | F95: 75 | G95: 34 | H95: =SUM(D95:G95) -> 189 | I95: =H95/400 -> 0.4725 | J95: =RANK(I95,$I$95:$I$109,0) -> 10
B96: 2 | C96: Riya Verma | D96: 67 | E96: 57 | F96: 73 | G96: 47 | H96: =SUM(D96:G96) -> 244 | I96: =H96/400 -> 0.61 | J96: =RANK(I96,$I$95:$I$109,0) -> 4
B97: 3 | C97: Vivaan Mehta | D97: 22 | E97: 77 | F97: 29 | G97: 93 | H97: =SUM(D97:G97) -> 221 | I97: =H97/400 -> 0.5525 | J97: =RANK(I97,$I$95:$I$109,0) -> 6
B98: 4 | C98: Ananya Iyer | D98: 58 | E98: 80 | F98: 28 | G98: 92 | H98: =SUM(D98:G98) -> 258 | I98: =H98/400 -> 0.645 | J98: =RANK(I98,$I$95:$I$109,0) -> 2
B99: 5 | C99: Karan Patel | D99: 89 | E99: 69 | F99: 92 | G99: 25 | H99: =SUM(D99:G99) -> 275 | I99: =H99/400 -> 0.6875 | J99: =RANK(I99,$I$95:$I$109,0) -> 1
B100: 6 | C100: Sanya Malhotra | D100: 43 | E100: 20 | F100: 66 | G100: 50 | H100: =SUM(D100:G100) -> 179 | I100: =H100/400 -> 0.4475 | J100: =RANK(I100,$I$95:$I$109,0) -> 12
B101: 7 | C101: Rahul Nair | D101: 21 | E101: 27 | F101: 70 | G101: 53 | H101: =SUM(D101:G101) -> 171 | I101: =H101/400 -> 0.4275 | J101: =RANK(I101,$I$95:$I$109,0) -> 14
B102: 8 | C102: Pooja Deshmukh | D102: 21 | E102: 35 | F102: 36 | G102: 41 | H102: =SUM(D102:G102) -> 133 | I102: =H102/400 -> 0.3325 | J102: =RANK(I102,$I$95:$I$109,0) -> 15
B103: 9 | C103: Aditya Reddy | D103: 61 | E103: 19 | F103: 25 | G103: 73 | H103: =SUM(D103:G103) -> 178 | I103: =H103/400 -> 0.445 | J103: =RANK(I103,$I$95:$I$109,0) -> 13
B104: 10 | C104: Meera Kapoor | D104: 69 | E104: 32 | F104: 59 | G104: 41 | H104: =SUM(D104:G104) -> 201 | I104: =H104/400 -> 0.5025 | J104: =RANK(I104,$I$95:$I$109,0) -> 8
B105: 11 | C105: Rohan Bansal | D105: 27 | E105: 75 | F105: 68 | G105: 79 | H105: =SUM(D105:G105) -> 249 | I105: =H105/400 -> 0.6225 | J105: =RANK(I105,$I$95:$I$109,0) -> 3
B106: 12 | C106: Ishita Choudhary | D106: 76 | E106: 54 | F106: 40 | G106: 30 | H106: =SUM(D106:G106) -> 200 | I106: =H106/400 -> 0.5 | J106: =RANK(I106,$I$95:$I$109,0) -> 9
... B109: 15 | C109: Kabir Saxena | D109: 15 | E109: 95 | F109: 29 | G109: 64 | H109: =SUM(D109:G109) -> 203 | I109: =H109/400 -> 0.5075 | J109: =RANK(I109,$I$95:$I$109,0) -> 7

Sheet Cell Referencing
A2: S no | B2: Names | C2: Hindi | D2: English | E2: Maths | F2: Science | G2: Total
A3: 1 | B3: Aarav Sharma | C3: 41 | D3: 39 | E3: 75 | F3: 34 | G3: =SUM(C3:F3) -> 189 | H3: =41+39+75+34 -> 189 | I3: =SUM(C3:F3) -> 189
A4: 2 | B4: Riya Verma | C4: 67 | D4: 57 | E4: 73 | F4: 47 | G4: =SUM(C4:F4) -> 244 | H4: =41+39+75+34 -> 189 | I4: =SUM(C4:F4) -> 244
A5: 3 | B5: Vivaan Mehta | C5: 22 | D5: 77 | E5: 29 | F5: 93 | G5: =SUM(C5:F5) -> 221 | H5: =41+39+75+34 -> 189 | I5: =SUM(C5:F5) -> 221
A6: 4 | B6: Ananya Iyer | C6: 58 | D6: 80 | E6: 28 | F6: 92 | G6: =SUM(C6:F6) -> 258 | H6: =41+39+75+34 -> 189 | I6: =SUM(C6:F6) -> 258
A7: 5 | B7: Karan Patel | C7: 89 | D7: 69 | E7: 92 | F7: 25 | G7: =SUM(C7:F7) -> 275 | H7: =41+39+75+34 -> 189 | I7: =SUM(C7:F7) -> 275
A8: 6 | B8: Sanya Malhotra | C8: 43 | D8: 20 | E8: 66 | F8: 50 | G8: =SUM(C8:F8) -> 179 | H8: =41+39+75+34 -> 189 | I8: =SUM(C8:F8) -> 179
A9: 7 | B9: Rahul Nair | C9: 21 | D9: 27 | E9: 70 | F9: 53 | G9: =SUM(C9:F9) -> 171 | H9: =41+39+75+34 -> 189 | I9: =SUM(C9:F9) -> 171
A10: 8 | B10: Pooja Deshmukh | C10: 21 | D10: 35 | E10: 36 | F10: 41 | G10: =SUM(C10:F10) -> 133 | H10: =41+39+75+34 -> 189 | I10: =SUM(C10:F10) -> 133
A11: 9 | B11: Aditya Reddy | C11: 61 | D11: 19 | E11: 25 | F11: 73 | G11: =SUM(C11:F11) -> 178 | H11: =41+39+75+34 -> 189 | I11: =SUM(C11:F11) -> 178
A12: 10 | B12: Meera Kapoor | C12: 69 | D12: 32 | E12: 59 | F12: 41 | G12: =SUM(C12:F12) -> 201 | H12: =41+39+75+34 -> 189 | I12: =SUM(C12:F12) -> 201
A13: 11 | B13: Rohan Bansal | C13: 27 | D13: 75 | E13: 68 | F13: 79 | G13: =SUM(C13:F13) -> 249 | H13: =41+39+75+34 -> 189 | I13: =SUM(C13:F13) -> 249
A14: 12 | B14: Ishita Choudhary | C14: 76 | D14: 54 | E14: 40 | F14: 30 | G14: =SUM(C14:F14) -> 200 | H14: =41+39+75+34 -> 189 | I14: =SUM(C14:F14) -> 200
... A17: 15 | B17: Kabir Saxena | C17: 15 | D17: 95 | E17: 29 | F17: 64 | G17: =SUM(C17:F17) -> 203 | H17: =41+39+75+34 -> 189 | I17: =SUM(C17:F17) -> 203
A30: Total Marks | F30: 400
A31: S no | B31: Names | C31: Hindi | D31: English | E31: Maths | F31: Science | G31: Total | H31: % | I31: %
A32: 1 | B32: Aarav Sharma | C32: 41 | D32: 39 | E32: 75 | F32: 34 | G32: =SUM(C32:F32) -> 189 | H32: =G32/400 -> 0.4725 | I32: =G32/$F$30 -> 0.4725
A33: 2 | B33: Riya Verma | C33: 67 | D33: 57 | E33: 73 | F33: 47 | G33: =SUM(C33:F33) -> 244 | H33: =G33/400 -> 0.61 | I33: =G33/$F$30 -> 0.61
A34: 3 | B34: Vivaan Mehta | C34: 22 | D34: 77 | E34: 29 | F34: 93 | G34: =SUM(C34:F34) -> 221 | H34: =G34/400 -> 0.5525 | I34: =G34/$F$30 -> 0.5525
A35: 4 | B35: Ananya Iyer | C35: 58 | D35: 80 | E35: 28 | F35: 92 | G35: =SUM(C35:F35) -> 258 | H35: =G35/400 -> 0.645 | I35: =G35/$F$30 -> 0.645
A36: 5 | B36: Karan Patel | C36: 89 | D36: 69 | E36: 92 | F36: 25 | G36: =SUM(C36:F36) -> 275 | H36: =G36/400 -> 0.6875 | I36: =G36/$F$30 -> 0.6875
A37: 6 | B37: Sanya Malhotra | C37: 43 | D37: 20 | E37: 66 | F37: 50 | G37: =SUM(C37:F37) -> 179 | H37: =G37/400 -> 0.4475 | I37: =G37/$F$30 -> 0.4475
A38: 7 | B38: Rahul Nair | C38: 21 | D38: 27 | E38: 70 | F38: 53 | G38: =SUM(C38:F38) -> 171 | H38: =G38/400 -> 0.4275 | I38: =G38/$F$30 -> 0.4275
A39: 8 | B39: Pooja Deshmukh | C39: 21 | D39: 35 | E39: 36 | F39: 41 | G39: =SUM(C39:F39) -> 133 | H39: =G39/400 -> 0.3325 | I39: =G39/$F$30 -> 0.3325
A40: 9 | B40: Aditya Reddy | C40: 61 | D40: 19 | E40: 25 | F40: 73 | G40: =SUM(C40:F40) -> 178 | H40: =G40/400 -> 0.445 | I40: =G40/$F$30 -> 0.445
A41: 10 | B41: Meera Kapoor | C41: 69 | D41: 32 | E41: 59 | F41: 41 | G41: =SUM(C41:F41) -> 201 | H41: =G41/400 -> 0.5025 | I41: =G41/$F$30 -> 0.5025
A42: 11 | B42: Rohan Bansal | C42: 27 | D42: 75 | E42: 68 | F42: 79 | G42: =SUM(C42:F42) -> 249 | H42: =G42/400 -> 0.6225 | I42: =G42/$F$30 -> 0.6225
A43: 12 | B43: Ishita Choudhary | C43: 76 | D43: 54 | E43: 40 | F43: 30 | G43: =SUM(C43:F43) -> 200 | H43: =G43/400 -> 0.5 | I43: =G43/$F$30 -> 0.5
... A46: 15 | B46: Kabir Saxena | C46: 15 | D46: 95 | E46: 29 | F46: 64 | G46: =SUM(C46:F46) -> 203 | H46: =G46/400 -> 0.5075 | I46: =G46/$F$30 -> 0.5075
A61: Total Marks | F61: 400
A62: S no | B62: Names | C62: Hindi | D62: English | E62: Maths | F62: Science | G62: Total | H62: % | I62: Hindi % | J62: English % | K62: Maths % | L62: Science %
A63: 1 | B63: Aarav Sharma | C63: 41 | D63: 39 | E63: 75 | F63: 34 | G63: =SUM(C63:F63) -> 189 | H63: =G63/$F$61 -> 0.4725 | I63: =C63/$G63 -> 0.21693122 | J63: =D63/$G63 -> 0.20634921 | K63: =E63/$G63 -> 0.3968254 | L63: =F63/$G63 -> 0.17989418
A64: 2 | B64: Riya Verma | C64: 67 | D64: 57 | E64: 73 | F64: 47 | G64: =SUM(C64:F64) -> 244 | H64: =G64/$F$61 -> 0.61 | I64: =C64/$G64 -> 0.27459016 | J64: =D64/$G64 -> 0.23360656 | K64: =E64/$G64 -> 0.29918033 | L64: =F64/$G64 -> 0.19262295
A65: 3 | B65: Vivaan Mehta | C65: 22 | D65: 77 | E65: 29 | F65: 93 | G65: =SUM(C65:F65) -> 221 | H65: =G65/$F$61 -> 0.5525 | I65: =C65/$G65 -> 0.099547511 | J65: =D65/$G65 -> 0.34841629 | K65: =E65/$G65 -> 0.13122172 | L65: =F65/$G65 -> 0.42081448
A66: 4 | B66: Ananya Iyer | C66: 58 | D66: 80 | E66: 28 | F66: 92 | G66: =SUM(C66:F66) -> 258 | H66: =G66/$F$61 -> 0.645 | I66: =C66/$G66 -> 0.2248062 | J66: =D66/$G66 -> 0.31007752 | K66: =E66/$G66 -> 0.10852713 | L66: =F66/$G66 -> 0.35658915
A67: 5 | B67: Karan Patel | C67: 89 | D67: 69 | E67: 92 | F67: 25 | G67: =SUM(C67:F67) -> 275 | H67: =G67/$F$61 -> 0.6875 | I67: =C67/$G67 -> 0.32363636 | J67: =D67/$G67 -> 0.25090909 | K67: =E67/$G67 -> 0.33454545 | L67: =F67/$G67 -> 0.090909091
A68: 6 | B68: Sanya Malhotra | C68: 43 | D68: 20 | E68: 66 | F68: 50 | G68: =SUM(C68:F68) -> 179 | H68: =G68/$F$61 -> 0.4475 | I68: =C68/$G68 -> 0.24022346 | J68: =D68/$G68 -> 0.11173184 | K68: =E68/$G68 -> 0.36871508 | L68: =F68/$G68 -> 0.27932961
A69: 7 | B69: Rahul Nair | C69: 21 | D69: 27 | E69: 70 | F69: 53 | G69: =SUM(C69:F69) -> 171 | H69: =G69/$F$61 -> 0.4275 | I69: =C69/$G69 -> 0.12280702 | J69: =D69/$G69 -> 0.15789474 | K69: =E69/$G69 -> 0.40935673 | L69: =F69/$G69 -> 0.30994152
A70: 8 | B70: Pooja Deshmukh | C70: 21 | D70: 35 | E70: 36 | F70: 41 | G70: =SUM(C70:F70) -> 133 | H70: =G70/$F$61 -> 0.3325 | I70: =C70/$G70 -> 0.15789474 | J70: =D70/$G70 -> 0.26315789 | K70: =E70/$G70 -> 0.27067669 | L70: =F70/$G70 -> 0.30827068
A71: 9 | B71: Aditya Reddy | C71: 61 | D71: 19 | E71: 25 | F71: 73 | G71: =SUM(C71:F71) -> 178 | H71: =G71/$F$61 -> 0.445 | I71: =C71/$G71 -> 0.34269663 | J71: =D71/$G71 -> 0.10674157 | K71: =E71/$G71 -> 0.14044944 | L71: =F71/$G71 -> 0.41011236
A72: 10 | B72: Meera Kapoor | C72: 69 | D72: 32 | E72: 59 | F72: 41 | G72: =SUM(C72:F72) -> 201 | H72: =G72/$F$61 -> 0.5025 | I72: =C72/$G72 -> 0.34328358 | J72: =D72/$G72 -> 0.15920398 | K72: =E72/$G72 -> 0.29353234 | L72: =F72/$G72 -> 0.2039801
A73: 11 | B73: Rohan Bansal | C73: 27 | D73: 75 | E73: 68 | F73: 79 | G73: =SUM(C73:F73) -> 249 | H73: =G73/$F$61 -> 0.6225 | I73: =C73/$G73 -> 0.10843373 | J73: =D73/$G73 -> 0.30120482 | K73: =E73/$G73 -> 0.27309237 | L73: =F73/$G73 -> 0.31726908
A74: 12 | B74: Ishita Choudhary | C74: 76 | D74: 54 | E74: 40 | F74: 30 | G74: =SUM(C74:F74) -> 200 | H74: =G74/$F$61 -> 0.5 | I74: =C74/$G74 -> 0.38 | J74: =D74/$G74 -> 0.27 | K74: =E74/$G74 -> 0.2 | L74: =F74/$G74 -> 0.15
A75: 13 | B75: Arjun Bhardwaj | C75: 29 | D75: 15 | E75: 81 | F75: 56 | G75: =SUM(C75:F75) -> 181 | H75: =G75/$F$61 -> 0.4525 | I75: =C75/$G75 -> 0.16022099 | J75: =D75/$G75 -> 0.082872928 | K75: =E75/$G75 -> 0.44751381 | L75: =F75/$G75 -> 0.30939227
B93: Total Marks | G93: 400
B94: S no | C94: Names | D94: Hindi | E94: English | F94: Maths | G94: Science | H94: Total | I94: % | J94: Rank
B95: 1 | C95: Aarav Sharma | D95: 41 | E95: 39 | F95: 75 | G95: 34 | H95: =SUM(D95:G95) -> 189 | I95: =H95/400 -> 0.4725 | J95: =RANK(I95,$I$95:$I$109,0) -> 10
B96: 2 | C96: Riya Verma | D96: 67 | E96: 57 | F96: 73 | G96: 47 | H96: =SUM(D96:G96) -> 244 | I96: =H96/400 -> 0.61 | J96: =RANK(I96,$I$95:$I$109,0) -> 4
B97: 3 | C97: Vivaan Mehta | D97: 22 | E97: 77 | F97: 29 | G97: 93 | H97: =SUM(D97:G97) -> 221 | I97: =H97/400 -> 0.5525 | J97: =RANK(I97,$I$95:$I$109,0) -> 6
B98: 4 | C98: Ananya Iyer | D98: 58 | E98: 80 | F98: 28 | G98: 92 | H98: =SUM(D98:G98) -> 258 | I98: =H98/400 -> 0.645 | J98: =RANK(I98,$I$95:$I$109,0) -> 2
B99: 5 | C99: Karan Patel | D99: 89 | E99: 69 | F99: 92 | G99: 25 | H99: =SUM(D99:G99) -> 275 | I99: =H99/400 -> 0.6875 | J99: =RANK(I99,$I$95:$I$109,0) -> 1
B100: 6 | C100: Sanya Malhotra | D100: 43 | E100: 20 | F100: 66 | G100: 50 | H100: =SUM(D100:G100) -> 179 | I100: =H100/400 -> 0.4475 | J100: =RANK(I100,$I$95:$I$109,0) -> 12
B101: 7 | C101: Rahul Nair | D101: 21 | E101: 27 | F101: 70 | G101: 53 | H101: =SUM(D101:G101) -> 171 | I101: =H101/400 -> 0.4275 | J101: =RANK(I101,$I$95:$I$109,0) -> 14
B102: 8 | C102: Pooja Deshmukh | D102: 21 | E102: 35 | F102: 36 | G102: 41 | H102: =SUM(D102:G102) -> 133 | I102: =H102/400 -> 0.3325 | J102: =RANK(I102,$I$95:$I$109,0) -> 15
B103: 9 | C103: Aditya Reddy | D103: 61 | E103: 19 | F103: 25 | G103: 73 | H103: =SUM(D103:G103) -> 178 | I103: =H103/400 -> 0.445 | J103: =RANK(I103,$I$95:$I$109,0) -> 13
B104: 10 | C104: Meera Kapoor | D104: 69 | E104: 32 | F104: 59 | G104: 41 | H104: =SUM(D104:G104) -> 201 | I104: =H104/400 -> 0.5025 | J104: =RANK(I104,$I$95:$I$109,0) -> 8
B105: 11 | C105: Rohan Bansal | D105: 27 | E105: 75 | F105: 68 | G105: 79 | H105: =SUM(D105:G105) -> 249 | I105: =H105/400 -> 0.6225 | J105: =RANK(I105,$I$95:$I$109,0) -> 3
B106: 12 | C106: Ishita Choudhary | D106: 76 | E106: 54 | F106: 40 | G106: 30 | H106: =SUM(D106:G106) -> 200 | I106: =H106/400 -> 0.5 | J106: =RANK(I106,$I$95:$I$109,0) -> 9
... B109: 15 | C109: Kabir Saxena | D109: 15 | E109: 95 | F109: 29 | G109: 64 | H109: =SUM(D109:G109) -> 203 | I109: =H109/400 -> 0.5075 | J109: =RANK(I109,$I$95:$I$109,0) -> 7

Sheet Text Formulas (2)
B1: Left | E1: Right | H1: Mid
B2: Names | C2: Prefix | E2: ID | F2: Suffix | H2: ID | I2: Suffix
B3: Mr. Aarav Sharma | E3: AXP-5678-MNO | H3: AXP-5678-MNO | I3: =MID(H3,5,4) -> 5678
B4: Mr. Rohan Iyer | E4: BTR-8492-KLM | H4: BTR-8492-KLM | I4: =MID(H4,5,4) -> 8492
B5: Mr. Aditya Mehta | E5: CQS-2345-XYZ | H5: CQS-2345-XYZ | I5: =MID(H5,5,4) -> 2345
B6: Mr. Vikram Malhotra | E6: DYN-6789-PQR | H6: DYN-6789-PQR | I6: =MID(H6,5,4) -> 6789
B7: Mr. Rajat Bansal | E7: EJM-4532-ABC | H7: EJM-4532-ABC | I7: =MID(H7,5,4) -> 4532
B8: Mr. Suresh Reddy | E8: FVK-9102-DEF | H8: FVK-9102-DEF | I8: =MID(H8,5,4) -> 9102
B9: Mr. Arjun Thakur | E9: GWL-3217-GHI | H9: GWL-3217-GHI | I9: =MID(H9,5,4) -> 3217
B10: Mr. Kunal Saxena | E10: HZS-7654-JKL | H10: HZS-7654-JKL | I10: =MID(H10,5,4) -> 7654
B11: Mr. Siddharth Rao | E11: JQP-1876-STU | H11: JQP-1876-STU | I11: =MID(H11,5,4) -> 1876
B12: Ms. Manisha Tripathi | E12: KRM-5923-VWX | H12: KRM-5923-VWX | I12: =MID(H12,5,4) -> 5923
B18: Length
B19: ID
B20: AXP-5678-MNO
B21: BTR-8492-KLM
B22: CQS-235-XYZ
B23: DYN-679- PQR
B24: EJM-4532-ABC
B25: FVK-9102-DEF
B26: GWL-3217-GHI
B27: HZS-7654-JKL
B28: JQP-1876-STU
B29: KRM-5923-VWX
... B60: Text
B61: Birth dates | C61: Days
B62: 14-06-1996
B63: 23-09-1998
B64: 37084
B65: 18-04-1995
B66: 30-07-2003
B67: 36841
B68: 25-05-1999
B69: 35491
B70: 19-08-2004
B71: 37478
B80: Lower | E80: Upper
B81: Names | C81: Small Letters | E81: Names | F81: Capital Letters | H81: Proper
B82: Mr. Aarav Sharma | E82: Mr. Aarav Sharma | H82: Names | I82: Sentence Case
B83: Mr. Rohan Iyer | E83: Mr. Rohan Iyer | H83: MR. AARAV SHARMA
B84: Mr. Aditya Mehta | E84: Mr. Aditya Mehta | H84: MR. ROHAN IYER
B85: Mr. Vikram Malhotra | E85: Mr. Vikram Malhotra | H85: MR. ADITYA MEHTA
B86: Mr. Rajat Bansal | E86: Mr. Rajat Bansal | H86: MR. VIKRAM MALHOTRA
B87: Mr. Suresh Reddy | E87: Mr. Suresh Reddy | H87: MR. RAJAT BANSAL
B88: Mr. Arjun Thakur | E88: Mr. Arjun Thakur | H88: MR. SURESH REDDY
B89: Mr. Kunal Saxena | E89: Mr. Kunal Saxena | H89: MR. ARJUN THAKUR
B90: Mr. Siddharth Rao | E90: Mr. Siddharth Rao | H90: MR. KUNAL SAXENA
B91: Mr. Manish Tripathi | E91: Mr. Manish Tripathi | H91: MR. SIDDHARTH RAO
H92: MR. MANISH TRIPATHI
B100: Text Join | F100: FlashFill (Ctrl E) | J100: & | N100: Concatenate | R100: Concat
B101: First Name | C101: Last Name | D101: Full Name | F101: First Name | G101: Last Name | H101: Full Name | J101: Full Name | K101: First Name | L101: Last Name | N101: First Name | O101: Last Name | P101: Full Name | R101: First Name | S101: Last Name | T101: Full Name
B102: Aarav | C102: Sharma | F102: Aarav | G102: Sharma | J102: Aarav Sharma | N102: Aarav | O102: Sharma | R102: Aarav | S102: Sharma
B103: Rohan | C103: Iyer | F103: Rohan | G103: Iyer | J103: Rohan Iyer | N103: Rohan | O103: Iyer | R103: Rohan | S103: Iyer
B104: Aditya | C104: Mehta | F104: Aditya | G104: Mehta | J104: Aditya Mehta | N104: Aditya | O104: Mehta | R104: Aditya | S104: Mehta
B105: Vikram | C105: Malhotra | F105: Vikram | G105: Malhotra | J105: Vikram Malhotra | N105: Vikram | O105: Malhotra | R105: Vikram | S105: Malhotra
B106: Rajat | C106: Bansal | F106: Rajat | G106: Bansal | J106: Rajat Bansal | N106: Rajat | O106: Bansal | R106: Rajat | S106: Bansal
B107: Suresh | C107: Reddy | F107: Suresh | G107: Reddy | J107: Suresh Reddy | N107: Suresh | O107: Reddy | R107: Suresh | S107: Reddy
B108: Arjun | C108: Thakur | F108: Arjun | G108: Thakur | J108: Arjun Thakur | N108: Arjun | O108: Thakur | R108: Arjun | S108: Thakur
B109: Kunal | C109: Saxena | F109: Kunal | G109: Saxena | J109: Kunal Saxena | N109: Kunal | O109: Saxena | R109: Kunal | S109: Saxena
B110: Siddharth | C110: Rao | F110: Siddharth | G110: Rao | J110: Siddharth Rao | N110: Siddharth | O110: Rao | R110: Siddharth | S110: Rao
B111: Manish | C111: Tripathi | F111: Manish | G111: Tripathi | J111: Manish Tripathi | N111: Manish | O111: Tripathi | R111: Manish | S111: Tripathi
B125: Substitute | E125: Find | H125: Replace | K125: Search
B126: ID | C126: Change | E126: ID | F126: Change | H126: ID | I126: Change | K126: ID | L126: Change
B127: AXP-5678-MNO | E127: AXP-5678-MNO | H127: AXP-5678-MNO | K127: AXP-5678-MNO
B128: BTR-8492-KLM | E128: BTR-8492-KLM | H128: BTR-8492-KLM | K128: BTR-8492-KLM
B129: CQS-2345-XYZ | E129: CQS-2345-XYZ | H129: CQS-2345-XYZ | K129: CQS-2345-XYZ
B130: DYN-6789-PQR | E130: DYN-6789-PQR | H130: DYN-6789-PQR | K130: DYN-6789-PQR
B131: EJM-4532-ABC | E131: EJM-4532-ABC | H131: EJM-4532-ABC | K131: EJM-4532-ABC
B132: FVK-9102-DEF | E132: FVK-9102-DEF | H132: FVK-9102-DEF | K132: FVK-9102-DEF
B133: GWL-3217-GHI | E133: GWL-3217-GHI | H133: GWL-3217-GHI | K133: GWL-3217-GHI
B134: HZS-7654-JKL | E134: HZS-7654-JKL | H134: HZS-7654-JKL | K134: HZS-7654-JKL
B135: JQP-1876-STU | E135: JQP-1876-STU | H135: JQP-1876-STU | K135: JQP-1876-STU
B136: KRM-5923-VWX | E136: KRM-5923-VWX | H136: KRM-5923-VWX | K136: KRM-5923-VWX

Sheet Text Formulas
B1: Left | E1: Right | H1: Mid
B2: Names | C2: Prefix | E2: ID | F2: Suffix | H2: ID | I2: Suffix
B3: Mr. Aarav Sharma | C3: =LEFT(B3,3) -> Mr. | E3: AXP-5678-MNO | F3: =RIGHT(E3,3) -> MNO | H3: AXP-5678-MNO | I3: =MID(H3,5,4) -> 5678
B4: Mr. Rohan Iyer | C4: =LEFT(B4,3) -> Mr. | E4: BTR-8492-KLM | F4: =RIGHT(E4,3) -> KLM | H4: BTR-8492-KLM | I4: =MID(H4,5,4) -> 8492
B5: Mr. Aditya Mehta | C5: =LEFT(B5,3) -> Mr. | E5: CQS-2345-XYZ | F5: =RIGHT(E5,3) -> XYZ | H5: CQS-2345-XYZ | I5: =MID(H5,5,4) -> 2345
B6: Mr. Vikram Malhotra | C6: =LEFT(B6,3) -> Mr. | E6: DYN-6789-PQR | F6: =RIGHT(E6,3) -> PQR | H6: DYN-6789-PQR | I6: =MID(H6,5,4) -> 6789
B7: Mr. Rajat Bansal | C7: =LEFT(B7,3) -> Mr. | E7: EJM-4532-ABC | F7: =RIGHT(E7,3) -> ABC | H7: EJM-4532-ABC | I7: =MID(H7,5,4) -> 4532
B8: Mr. Suresh Reddy | C8: =LEFT(B8,3) -> Mr. | E8: FVK-9102-DEF | F8: =RIGHT(E8,3) -> DEF | H8: FVK-9102-DEF | I8: =MID(H8,5,4) -> 9102
B9: Mr. Arjun Thakur | C9: =LEFT(B9,3) -> Mr. | E9: GWL-3217-GHI | F9: =RIGHT(E9,3) -> GHI | H9: GWL-3217-GHI | I9: =MID(H9,5,4) -> 3217
B10: Mr. Kunal Saxena | C10: =LEFT(B10,3) -> Mr. | E10: HZS-7654-JKL | F10: =RIGHT(E10,3) -> JKL | H10: HZS-7654-JKL | I10: =MID(H10,5,4) -> 7654
B11: Mr. Siddharth Rao | C11: =LEFT(B11,3) -> Mr. | E11: JQP-1876-STU | F11: =RIGHT(E11,3) -> STU | H11: JQP-1876-STU | I11: =MID(H11,5,4) -> 1876
B12: Ms. Manisha Tripathi | C12: =LEFT(B12,3) -> Ms. | E12: KRM-5923-VWX | F12: =RIGHT(E12,3) -> VWX | H12: KRM-5923-VWX | I12: =MID(H12,5,4) -> 5923
B18: Len | D18: Length
B19: ID | D19: IDgth
B20: AXP-5678-MNO | C20: =LEN(B20) -> 12
B21: BTR-8492-KLM | C21: =LEN(B21) -> 12
B22: CQS-235-XYZ | C22: =LEN(B22) -> 11
B23: DYN-679- PQR | C23: =LEN(B23) -> 14
B24: EJM-4532-ABC | C24: =LEN(B24) -> 12
B25: FVK-9102-DEF | C25: =LEN(B25) -> 12
B26: GWL-3217-GHI | C26: =LEN(B26) -> 12
B27: HZS-7654-JKL | C27: =LEN(B27) -> 12
B28: JQP-1876-STU | C28: =LEN(B28) -> 12
B29: KRM-5923-VWX | C29: =LEN(B29) -> 12
B39: Trim | D39: unwanted spaces
B40: ID
B41: Mr. Aarav Sharma | C41: =TRIM(B41) -> Mr. Aarav Sharma
B42: Mr. Rohan Iyer | C42: =TRIM(B42) -> Mr. Rohan Iyer
B43: Mr. Aditya Mehta | C43: =TRIM(B43) -> Mr. Aditya Mehta
B44: Mr. Vikram Malhotra | C44: =TRIM(B44) -> Mr. Vikram Malhotra
B45: Mr. Rajat Bansal | C45: =TRIM(B45) -> Mr. Rajat Bansal
B46: Mr. Suresh Reddy | C46: =TRIM(B46) -> Mr. Suresh Reddy
B47: Mr. Arjun Thakur | C47: =TRIM(B47) -> Mr. Arjun Thakur
B48: Mr. Kunal Saxena | C48: =TRIM(B48) -> Mr. Kunal Saxena
B49: Mr. Siddharth Rao | C49: =TRIM(B49) -> Mr. Siddharth Rao
B50: Mr. Manish Tripathi | C50: =TRIM(B50) -> Mr. Manish Tripathi
B60: Text
B61: Birth dates | C61: Days
B62: 14-06-1996 | C62: =TEXT(B62,"dddd") -> Friday | D62: =TEXT(B62,"mmmm") -> June
B63: 23-09-1998 | C63: =TEXT(B63,"dddd") -> Wednesday | D63: =TEXT(B63,"mmmm") -> September
B64: 37084 | C64: =TEXT(B64,"dddd") -> Thursday | D64: =TEXT(B64,"mmmm") -> July
B65: 18-04-1995 | C65: =TEXT(B65,"dddd") -> Tuesday | D65: =TEXT(B65,"mmmm") -> April
B66: 30-07-2003 | C66: =TEXT(B66,"dddd") -> Wednesday | D66: =TEXT(B66,"mmmm") -> July
B67: 36841 | C67: =TEXT(B67,"dddd") -> Saturday | D67: =TEXT(B67,"mmmm") -> November
B68: 25-05-1999 | C68: =TEXT(B68,"dddd") -> Tuesday | D68: =TEXT(B68,"mmmm") -> May
B69: 35491 | C69: =TEXT(B69,"dddd") -> Sunday | D69: =TEXT(B69,"mmmm") -> March
B70: 19-08-2004 | C70: =TEXT(B70,"dddd") -> Thursday | D70: =TEXT(B70,"mmmm") -> August
B71: 37478 | C71: =TEXT(B71,"dddd") -> Saturday | D71: =TEXT(B71,"mmmm") -> August
B80: Lower | E80: Upper | H80: Proper
B81: Names | C81: Small Letters | E81: Names | F81: Capital Letters | H81: Names | I81: Sentence Case
B82: Mr. Aarav Sharma | C82: =LOWER(B82) -> mr. aarav sharma | E82: Mr. Aarav Sharma | F82: =UPPER(E82) -> MR. AARAV SHARMA | H82: MR. AARAV SHARMA | I82: =PROPER(H82) -> Mr. Aarav Sharma
B83: Mr. Rohan Iyer | C83: =LOWER(B83) -> mr. rohan iyer | E83: Mr. Rohan Iyer | F83: =UPPER(E83) -> MR. ROHAN IYER | H83: MR. ROHAN IYER | I83: =PROPER(H83) -> Mr. Rohan Iyer
B84: Mr. Aditya Mehta | C84: =LOWER(B84) -> mr. aditya mehta | E84: Mr. Aditya Mehta | F84: =UPPER(E84) -> MR. ADITYA MEHTA | H84: MR. ADITYA MEHTA | I84: =PROPER(H84) -> Mr. Aditya Mehta
B85: Mr. Vikram Malhotra | C85: =LOWER(B85) -> mr. vikram malhotra | E85: Mr. Vikram Malhotra | F85: =UPPER(E85) -> MR. VIKRAM MALHOTRA | H85: MR. VIKRAM MALHOTRA | I85: =PROPER(H85) -> Mr. Vikram Malhotra
B86: Mr. Rajat Bansal | C86: =LOWER(B86) -> mr. rajat bansal | E86: Mr. Rajat Bansal | F86: =UPPER(E86) -> MR. RAJAT BANSAL | H86: MR. RAJAT BANSAL | I86: =PROPER(H86) -> Mr. Rajat Bansal
B87: Mr. Suresh Reddy | C87: =LOWER(B87) -> mr. suresh reddy | E87: Mr. Suresh Reddy | F87: =UPPER(E87) -> MR. SURESH REDDY | H87: MR. SURESH REDDY | I87: =PROPER(H87) -> Mr. Suresh Reddy
B88: Mr. Arjun Thakur | C88: =LOWER(B88) -> mr. arjun thakur | E88: Mr. Arjun Thakur | F88: =UPPER(E88) -> MR. ARJUN THAKUR | H88: MR. ARJUN THAKUR | I88: =PROPER(H88) -> Mr. Arjun Thakur
B89: Mr. Kunal Saxena | C89: =LOWER(B89) -> mr. kunal saxena | E89: Mr. Kunal Saxena | F89: =UPPER(E89) -> MR. KUNAL SAXENA | H89: MR. KUNAL SAXENA | I89: =PROPER(H89) -> Mr. Kunal Saxena
B90: Mr. Siddharth Rao | C90: =LOWER(B90) -> mr. siddharth rao | E90: Mr. Siddharth Rao | F90: =UPPER(E90) -> MR. SIDDHARTH RAO | H90: MR. SIDDHARTH RAO | I90: =PROPER(H90) -> Mr. Siddharth Rao
B91: Mr. Manish Tripathi | C91: =LOWER(B91) -> mr. manish tripathi | E91: Mr. Manish Tripathi | F91: =UPPER(E91) -> MR. MANISH TRIPATHI | H91: MR. MANISH TRIPATHI | I91: =PROPER(H91) -> Mr. Manish Tripathi
B100: Text Join | F100: FlashFill (Ctrl E) | J100: Text Split | N100: Concatenate | R100: Concat | W100: Text Split
B101: First Name | C101: Last Name | D101: Full Name | F101: First Name | G101: Last Name | H101: Full Name | J101: Full Name | K101: First Name | L101: Last Name | N101: First Name | O101: Last Name | P101: Full Name | R101: First Name | S101: Last Name | T101: Full Name | U101: & | W101: Full Name | X101: Before | Y101: After
B102: Aarav | C102: Sharma | D102: =_xlfn.TEXTJOIN(",",TRUE,B102,C102) -> Aarav,Sharma | F102: Aarav | G102: Sharma | H102: A S | J102: Aarav Sharma | K102: {=_xlfn.TEXTSPLIT(J102," ")} -> Aarav | L102: Sharma | N102: Aarav | O102: Sharma | P102: =CONCATENATE(N102," ",O102) -> Aarav Sharma | R102: Aarav | S102: Sharma | T102: =_xlfn.CONCAT(R102,"-",S102) -> Aarav-Sharma | U102: =R102&" "&S102 -> Aarav Sharma | W102: Aarav Sharma | X102: =_xlfn.TEXTBEFORE(W102," ") -> Aarav | Y102: =_xlfn.TEXTAFTER(W102," ") -> Sharma
B103: Rohan | C103: Iyer | D103: =_xlfn.TEXTJOIN(",",TRUE,B103,C103) -> Rohan,Iyer | F103: Rohan | G103: Iyer | H103: R I | J103: Rohan Iyer | K103: {=_xlfn.TEXTSPLIT(J103," ")} -> Rohan | L103: Iyer | N103: Rohan | O103: Iyer | P103: =CONCATENATE(N103," ",O103) -> Rohan Iyer | R103: Rohan | S103: Iyer | T103: =_xlfn.CONCAT(R103,"-",S103) -> Rohan-Iyer | U103: =R103&" "&S103 -> Rohan Iyer | W103: Rohan Iyer | X103: =_xlfn.TEXTBEFORE(W103," ") -> Rohan | Y103: =_xlfn.TEXTAFTER(W103," ") -> Iyer
B104: Aditya | C104: Mehta | D104: =_xlfn.TEXTJOIN(",",TRUE,B104,C104) -> Aditya,Mehta | F104: Aditya | G104: Mehta | H104: A M | J104: Aditya Mehta | K104: {=_xlfn.TEXTSPLIT(J104," ")} -> Aditya | L104: Mehta | N104: Aditya | O104: Mehta | P104: =CONCATENATE(N104," ",O104) -> Aditya Mehta | R104: Aditya | S104: Mehta | T104: =_xlfn.CONCAT(R104,"-",S104) -> Aditya-Mehta | U104: =R104&" "&S104 -> Aditya Mehta | W104: Aditya Mehta | X104: =_xlfn.TEXTBEFORE(W104," ") -> Aditya | Y104: =_xlfn.TEXTAFTER(W104," ") -> Mehta
B105: Vikram | C105: Malhotra | D105: =_xlfn.TEXTJOIN(",",TRUE,B105,C105) -> Vikram,Malhotra | F105: Vikram | G105: Malhotra | H105: V M | J105: Vikram Malhotra | K105: {=_xlfn.TEXTSPLIT(J105," ")} -> Vikram | L105: Malhotra | N105: Vikram | O105: Malhotra | P105: =CONCATENATE(N105," ",O105) -> Vikram Malhotra | R105: Vikram | S105: Malhotra | T105: =_xlfn.CONCAT(R105,"-",S105) -> Vikram-Malhotra | U105: =R105&" "&S105 -> Vikram Malhotra | W105: Vikram Malhotra | X105: =_xlfn.TEXTBEFORE(W105," ") -> Vikram | Y105: =_xlfn.TEXTAFTER(W105," ") -> Malhotra
B106: Rajat | C106: Bansal | D106: =_xlfn.TEXTJOIN(",",TRUE,B106,C106) -> Rajat,Bansal | F106: Rajat | G106: Bansal | H106: R B | J106: Rajat Bansal | K106: {=_xlfn.TEXTSPLIT(J106," ")} -> Rajat | L106: Bansal | N106: Rajat | O106: Bansal | P106: =CONCATENATE(N106," ",O106) -> Rajat Bansal | R106: Rajat | S106: Bansal | T106: =_xlfn.CONCAT(R106,"-",S106) -> Rajat-Bansal | U106: =R106&" "&S106 -> Rajat Bansal | W106: Rajat Bansal | X106: =_xlfn.TEXTBEFORE(W106," ") -> Rajat | Y106: =_xlfn.TEXTAFTER(W106," ") -> Bansal
B107: Suresh | C107: Reddy | D107: =_xlfn.TEXTJOIN(",",TRUE,B107,C107) -> Suresh,Reddy | F107: Suresh | G107: Reddy | H107: S R | J107: Suresh Reddy | K107: {=_xlfn.TEXTSPLIT(J107," ")} -> Suresh | L107: Reddy | N107: Suresh | O107: Reddy | P107: =CONCATENATE(N107," ",O107) -> Suresh Reddy | R107: Suresh | S107: Reddy | T107: =_xlfn.CONCAT(R107,"-",S107) -> Suresh-Reddy | U107: =R107&" "&S107 -> Suresh Reddy | W107: Suresh Reddy | X107: =_xlfn.TEXTBEFORE(W107," ") -> Suresh | Y107: =_xlfn.TEXTAFTER(W107," ") -> Reddy
B108: Arjun | C108: Thakur | D108: =_xlfn.TEXTJOIN(",",TRUE,B108,C108) -> Arjun,Thakur | F108: Arjun | G108: Thakur | H108: A T | J108: Arjun Thakur | K108: {=_xlfn.TEXTSPLIT(J108," ")} -> Arjun | L108: Thakur | N108: Arjun | O108: Thakur | P108: =CONCATENATE(N108," ",O108) -> Arjun Thakur | R108: Arjun | S108: Thakur | T108: =_xlfn.CONCAT(R108,"-",S108) -> Arjun-Thakur | U108: =R108&" "&S108 -> Arjun Thakur | W108: Arjun Thakur | X108: =_xlfn.TEXTBEFORE(W108," ") -> Arjun | Y108: =_xlfn.TEXTAFTER(W108," ") -> Thakur
B109: Kunal | C109: Saxena | D109: =_xlfn.TEXTJOIN(",",TRUE,B109,C109) -> Kunal,Saxena | F109: Kunal | G109: Saxena | H109: K S | J109: Kunal Saxena | K109: {=_xlfn.TEXTSPLIT(J109," ")} -> Kunal | L109: Saxena | N109: Kunal | O109: Saxena | P109: =CONCATENATE(N109," ",O109) -> Kunal Saxena | R109: Kunal | S109: Saxena | T109: =_xlfn.CONCAT(R109,"-",S109) -> Kunal-Saxena | U109: =R109&" "&S109 -> Kunal Saxena | W109: Kunal Saxena | X109: =_xlfn.TEXTBEFORE(W109," ") -> Kunal | Y109: =_xlfn.TEXTAFTER(W109," ") -> Saxena
B110: Siddharth | C110: Rao | D110: =_xlfn.TEXTJOIN(",",TRUE,B110,C110) -> Siddharth,Rao | F110: Siddharth | G110: Rao | H110: S R | J110: Siddharth Rao | K110: {=_xlfn.TEXTSPLIT(J110," ")} -> Siddharth | L110: Rao | N110: Siddharth | O110: Rao | P110: =CONCATENATE(N110," ",O110) -> Siddharth Rao | R110: Siddharth | S110: Rao | T110: =_xlfn.CONCAT(R110,"-",S110) -> Siddharth-Rao | U110: =R110&" "&S110 -> Siddharth Rao | W110: Siddharth Rao | X110: =_xlfn.TEXTBEFORE(W110," ") -> Siddharth | Y110: =_xlfn.TEXTAFTER(W110," ") -> Rao
B111: Manish | C111: Tripathi | D111: =_xlfn.TEXTJOIN(",",TRUE,B111,C111) -> Manish,Tripathi | F111: Manish | G111: Tripathi | H111: M T | J111: Manish Tripathi | K111: {=_xlfn.TEXTSPLIT(J111," ")} -> Manish | L111: Tripathi | N111: Manish | O111: Tripathi | P111: =CONCATENATE(N111," ",O111) -> Manish Tripathi | R111: Manish | S111: Tripathi | T111: =_xlfn.CONCAT(R111,"-",S111) -> Manish-Tripathi | U111: =R111&" "&S111 -> Manish Tripathi | W111: Manish Tripathi | X111: =_xlfn.TEXTBEFORE(W111," ") -> Manish | Y111: =_xlfn.TEXTAFTER(W111," ") -> Tripathi
B125: Substitute | E125: Find (Case Sensitive) | H125: Replace | K125: Search(Not Case Sensitive)
B126: ID | C126: Change | E126: ID | F126: Change | H126: ID | I126: Change | K126: ID | L126: Change
B127: AXP-5678-MNO | C127: =SUBSTITUTE(B127,"-","@") -> AXP@5678@MNO | E127: AXp-5678-MNO | F127: =FIND("p",E127) -> 3 | G127: =SEARCH("P",E127) -> 3 | H127: AXP-5678-MNO | I127: =REPLACE(H127,5,4,2026) -> AXP-2026-MNO | K127: AXP-5678-MNO | L127: =SEARCH("o",K127) -> 12
B128: AXP-5678-M-O | C128: =SUBSTITUTE(B128,"-","@") -> AXP@5678@M@O | E128: BTR-8492-KLp | F128: =FIND("p",E128) -> 12 | G128: =SEARCH("P",E128) -> 12 | H128: BTR-8492-KLM | I128: =REPLACE(H128,5,4,2026) -> BTR-2026-KLM | K128: BTR-8492-KLM | L128: =SEARCH("o",K128) -> #VALUE!
B129: CQS-2345-XYZ | C129: =SUBSTITUTE(B129,"-","@") -> CQS@2345@XYZ | E129: CQS-p345-XYZ | F129: =FIND("p",E129) -> 5 | G129: =SEARCH("P",E129) -> 5 | H129: CQS-2345-XYZ | I129: =REPLACE(H129,5,4,2026) -> CQS-2026-XYZ | K129: CQS-2345-XYZO | L129: =SEARCH("o",K129) -> 13
B130: DYN-6789-PQR | C130: =SUBSTITUTE(B130,"-","@") -> DYN@6789@PQR | E130: DYN-6789-PQR | F130: =FIND("p",E130) -> #VALUE! | G130: =SEARCH("P",E130) -> 10 | H130: DYN-6789-PQR | I130: =REPLACE(H130,5,4,2026) -> DYN-2026-PQR | K130: DYN-6789-PQR | L130: =SEARCH("o",K130) -> #VALUE!
B131: EJM-4532-ABC | C131: =SUBSTITUTE(B131,"-","@") -> EJM@4532@ABC | E131: EJM-4532-ABC | F131: =FIND("p",E131) -> #VALUE! | G131: =SEARCH("P",E131) -> #VALUE! | H131: EJM-4532-ABC | I131: =REPLACE(H131,5,4,2026) -> EJM-2026-ABC | K131: EJM-4532-ABC | L131: =SEARCH("o",K131) -> #VALUE!
B132: FVK-9102-DEF | C132: =SUBSTITUTE(B132,"-","@") -> FVK@9102@DEF | E132: FVK-p102-DEF | F132: =FIND("p",E132) -> 5 | G132: =SEARCH("P",E132) -> 5 | H132: FVK-9102-DEF | I132: =REPLACE(H132,5,4,2026) -> FVK-2026-DEF | K132: FVK-9102-OEF | L132: =SEARCH("o",K132) -> 10
B133: GWL-3217-GHI | C133: =SUBSTITUTE(B133,"-","@") -> GWL@3217@GHI | E133: GWL-3217-GHI | F133: =FIND("p",E133) -> #VALUE! | G133: =SEARCH("P",E133) -> #VALUE! | H133: GWL-3217-GHI | I133: =REPLACE(H133,5,4,2026) -> GWL-2026-GHI | K133: GWL-3217-GHI | L133: =SEARCH("o",K133) -> #VALUE!
B134: HZS-7654-JKL | C134: =SUBSTITUTE(B134,"-","@") -> HZS@7654@JKL | E134: HZS-7654-JKL | F134: =FIND("p",E134) -> #VALUE! | G134: =SEARCH("P",E134) -> #VALUE! | H134: HZS-7654-JKL | I134: =REPLACE(H134,5,4,2026) -> HZS-2026-JKL | K134: HZS-7654-JKL | L134: =SEARCH("o",K134) -> #VALUE!
B135: JQP-1876-STU | C135: =SUBSTITUTE(B135,"-","@") -> JQP@1876@STU | E135: JQP-1876-SPU | F135: =FIND("p",E135) -> #VALUE! | G135: =SEARCH("P",E135) -> 3 | H135: JQP-1876-STU | I135: =REPLACE(H135,5,4,2026) -> JQP-2026-STU | K135: JQP-1876-STU | L135: =SEARCH("o",K135) -> #VALUE!
B136: KRM-5923-VWX | C136: =SUBSTITUTE(B136,"-","@") -> KRM@5923@VWX | E136: KRM-5923-VWX | F136: =FIND("p",E136) -> #VALUE! | G136: =SEARCH("P",E136) -> #VALUE! | H136: KRM-5923-VWX | I136: =REPLACE(H136,5,4,2026) -> KRM-2026-VWX | K136: KRM-5923-VWX | L136: =SEARCH("o",K136) -> #VALUE!
B145: 1234563 | C145: =VALUE(B145) -> 1234563
B150: Tannu Singhal | C150: =CLEAN(B150) -> TannuSinghal

Sheet Notes
A1: Text Formulae (25) | H1: 25
A2: S No | B2: Formula | C2: Syntax | D2: Meaning (Hinglish) | E2: Usage | F2: Example | H2: 29
A3: 1 | B3: LEFT | C3: LEFT(TEXT, num_chars) | D3: Left side se characters nikaalta hai | E3: Starting letters extract karne ke liye | F3: =LEFT("Tannu",3) → Tan | H3: 28
A4: 2 | B4: RIGHT | C4: RIGHT(TEXT, num_chars) | D4: Right side se characters nikaalta hai | E4: Ending extract karne ke liye | F4: =RIGHT("Tannu",2) → nu | H4: 20
A5: 3 | B5: MID | C5: MID(TEXT, num_chars) | D5: Beech ka text nikaalta hai | E5: Specific position ka text | F5: =MID("Excel",2,3) → xce | H5: 20
A6: 4 | B6: LEN | C6: LEN(TEXT, num_chars) | D6: Total characters count karta hai | E6: Length check karne ke liye | F6: =LEN("Hello") → 5 | H6: 10
A7: 5 | B7: TRIM | C7: TRIM(TEXT, num_chars) | D7: Extra spaces hata deta hai | E7: Clean data ke liye | F7: =TRIM(" Hello ") → Hello | H7: 10
A8: 6 | B8: UPPER | C8: UPPER(TEXT, num_chars) | D8: Sabko capital bana deta hai | E8: Standard format | F8: =UPPER("excel") → EXCEL
A9: 7 | B9: LOWER | C9: LOWER(TEXT, num_chars) | D9: Sabko small letters me convert karta hai | E9: Email cleaning | F9: =LOWER("EXCEL") → excel
A10: 8 | B10: PROPER | C10: PROPER(TEXT, num_chars) | D10: Har word ka first letter capital | E10: Name formatting | F10: =PROPER("tannu singhal") → Tannu Singhal
A11: 9 | B11: CONCAT | C11: CONCAT(TEXT, num_chars) | D11: Multiple text join karta hai | E11: Data combine | F11: =CONCAT("A","B") → AB
A12: 10 | B12: CONCATENATE | C12: CONCATENATE(TEXT, num_chars) | D12: Same as CONCAT (old version) | E12: Combine text | F12: =CONCATENATE("Hi"," ","All") -> Hi All
A13: 11 | B13: TEXTJOIN | C13: TEXTJOIN(TEXT, num_chars) | D13: Join karta hai with separator | E13: Advanced joining | F13: =_xlfn.TEXTJOIN(",",TRUE,A2:A4) -> S No,1,2
A14: 12 | B14: FIND | C14: FIND(TEXT, num_chars) | D14: Case-sensitive search karta hai | E14: Position find karna | F14: =FIND("a","Tannu") → 2
A15: 13 | B15: SEARCH | C15: SEARCH(TEXT, num_chars) | D15: Case-insensitive search | E15: Flexible search | F15: =SEARCH("A","tannu") → 2
A16: 14 | B16: REPLACE | C16: REPLACE(TEXT, num_chars) | D16: Text replace karta hai position se | E16: Data correction | F16: =REPLACE("12345",2,2,"AA") -> 1AA45
A17: 15 | B17: SUBSTITUTE | C17: SUBSTITUTE(TEXT, num_chars) | D17: Specific text replace karta hai | E17: Word replace | F17: =SUBSTITUTE("Hi all","all","team") -> Hi team
A18: 16 | B18: VALUE | C18: VALUE(TEXT, num_chars) | D18: Text ko number me convert karta hai | E18: Numeric conversion | F18: =VALUE("123") → 123
A19: 17 | B19: TEXT | C19: TEXT(TEXT, num_chars) | D19: Number ko text format me convert | E19: Formatting | F19: =TEXT(100,"₹0") → ₹100
A20: 18 | B20: CLEAN | C20: CLEAN(TEXT, num_chars) | D20: Non-printable characters remove karta hai | E20: Imported data cleaning | F20: =CLEAN(A2) -> S No
A21: 19 | B21: CHAR | C21: CHAR(TEXT, num_chars) | D21: ASCII code se character return | E21: Special characters | F21: =CHAR(65) → A
A22: 20 | B22: REPT | C22: REPT(TEXT, num_chars) | D22: Text repeat karta hai | E22: Pattern banana | F22: =REPT("*",5) → *****
A23: Text Split , Ampersend , flashfill , Textbeforedelimeter , textafterdelimeter
A33: Statistical Formulae (30)
A34: S No | B34: Formula | C34: Syntax | D34: Meaning (Hinglish) | E34: Usage | F34: Example
A35: 1 | B35: AVERAGE | C35: AVERAGE(range) | D35: Average nikaalta hai | E35: Mean calculation | F35: =AVERAGE(10,20,30) → 20
A36: 2 | B36: MAX | C36: MAX(range) | D36: Sabse badi value | E36: Highest find | F36: =MAX(10,50,30) → 50
A37: 3 | B37: MIN | C37: MIN(range) | D37: Sabse chhoti value | E37: Lowest find | F37: =MIN(10,50,30) → 10
A38: 4 | B38: COUNT | C38: COUNT(range) | D38: Numbers count karta hai | E38: Numeric count | F38: =COUNT(1,2,"A") → 2
A39: 5 | B39: COUNTA | C39: COUNTA(range) | D39: Non-empty count | E39: Filled cells | F39: =COUNTA(1,"A") → 2
A40: 6 | B40: COUNTIF | C40: COUNTIF(range,criteria) | D40: Condition pe count | E40: Filtered count | F40: =COUNTIF(A2:A6,">10") -> 0
A41: 7 | B41: COUNTIFS | C41: COUNTIFS(range1,criteria1,...) | D41: Multi condition count | E41: Advanced filtering | F41: =COUNTIFS(A2:A6,">10",B2:B6,"A") -> 0
A42: 8 | B42: AVERAGEIF | C42: AVERAGEIF(range,criteria) | D42: Condition pe average | E42: Filtered avg | F42: =AVERAGEIF(A2:A6,">10") -> #DIV/0!
A43: 9 | B43: AVERAGEIFS | C43: AVERAGEIFS(avg_range,criteria_range1,criteria1,...) | D43: Multi condition avg | E43: Advanced avg | F43: =AVERAGEIFS(A2:A6,B2:B6,"A") -> #DIV/0!
A44: 10 | B44: SUM | C44: SUM(range) | D44: Total sum | E44: Total calc | F44: =SUM(10,20,30) → 60
A45: 11 | B45: SUMIF | C45: SUMIF(range,criteria,sum_range) | D45: Condition pe sum | E45: Filtered sum | F45: =SUMIF(A2:A6,">10",B2:B6) -> 0
A46: 12 | B46: SUMIFS | C46: SUMIFS(sum_range,criteria_range1,criteria1,...) | D46: Multi condition sum | E46: Complex analysis | F46: =SUMIFS(B2:B6,A2:A6,">10") -> 0
A47: 13 | B47: LARGE | C47: LARGE(range,k) | D47: kth largest | E47: Top values | F47: =LARGE(A2:A6,2) -> 3
A48: 14 | B48: SMALL | C48: SMALL(range,k) | D48: kth smallest | E48: Bottom values | F48: =SMALL(A2:A6,2) -> 2
A49: 15 | B49: RANK | C49: RANK(number,range) | D49: Rank deta hai | E49: Position | F49: =RANK(50,A2:A6) -> #N/A
A50: 16 | B50: ROUND | C50: ROUND(number,num_digits) | D50: Normal rounding | E50: Approx value | F50: =ROUND(12.345,2) → 12.35
A51: 17 | B51: ROUNDUP | C51: ROUNDUP(number,num_digits) | D51: Hamesha upar round | E51: Profit side | F51: =ROUNDUP(12.341,2) → 12.35
A52: 18 | B52: ROUNDDOWN | C52: ROUNDDOWN(number,num_digits) | D52: Hamesha neeche | E52: Safe side | F52: =ROUNDDOWN(12.349,2) → 12.34
A53: 19 | B53: INT | C53: INT(number) | D53: Integer deta hai | E53: Decimal hatao | F53: =INT(12.9) → 12
A54: 20 | B54: TRUNC | C54: TRUNC(number,[digits]) | D54: Decimal cut karta hai | E54: Exact truncate | F54: =TRUNC(12.987,2) → 12.98
A55: 21 | B55: FLOOR | C55: FLOOR(number,significance) | D55: Lower multiple | E55: Discount | F55: =FLOOR(23,5) → 20
A56: 22 | B56: MROUND | C56: MROUND(number,multiple) | D56: Nearest multiple | E56: Smart rounding | F56: =MROUND(23,5) → 25
A57: 23 | B57: RAND | C57: RAND() | D57: 0–1 random number | E57: Random data | F57: =RAND() -> 0.27730609
A58: 24 | B58: RANDBETWEEN | C58: RANDBETWEEN(bottom,top) | D58: Range me random | E58: Testing data | F58: =RANDBETWEEN(1,100) -> 52
A59: 25 | B59: RANDARRAY | C59: RANDARRAY(rows,cols,min,max,integer) | D59: Random table | E59: Bulk data | F59: {=_xlfn.RANDARRAY(3,2,1,10,TRUE)} -> #VALUE!
A60: 26 | B60: ABS | C60: ABS(number) | D60: Positive bana deta hai | E60: Distance | F60: =ABS(-10) → 10
A61: 27 | B61: MOD | C61: MOD(number,divisor) | D61: Remainder deta hai | E61: Even/odd | F61: =MOD(10,3) → 1
A62: 28 | B62: POWER | C62: POWER(number,power) | D62: Power nikalta hai | E62: Exponential | F62: =POWER(2,3) → 8
A63: 29 | B63: SQRT | C63: SQRT(number) | D63: Square root | E63: Math calc | F63: =SQRT(16) → 4
A64: 30 | B64: Ceiling | C64: Upper Multiple
A68: Date & Time Formulae (28)
A69: S No | B69: Formula | C69: Syntax | D69: Meaning (Hinglish) | E69: Usage | F69: Example
A70: 1 | B70: TODAY | C70: TODAY() | D70: Aaj ki date deta hai | E70: Current date | F70: TODAY()
A71: 2 | B71: NOW | C71: NOW() | D71: Current date + time | E71: Live timestamp | F71: NOW()
A72: 3 | B72: DATE | C72: DATE(year,month,day) | D72: Custom date banata hai | E72: Date creation | F72: DATE(2026,4,9)
A73: 4 | B73: TIME | C73: TIME(hour,minute,second) | D73: Time create karta hai | E73: Custom time | F73: TIME(10,30,0)
A74: 5 | B74: DAY | C74: DAY(date) | D74: Day nikaalta hai | E74: Extract day | F74: DAY(A1)
A75: 6 | B75: MONTH | C75: MONTH(date) | D75: Month nikaalta hai | E75: Extract month | F75: MONTH(A1)
A76: 7 | B76: YEAR | C76: YEAR(date) | D76: Year nikaalta hai | E76: Extract year | F76: YEAR(A1)
A77: 8 | B77: HOUR | C77: HOUR(time) | D77: Hour nikaalta hai | E77: Time breakdown | F77: HOUR(A1)
A78: 9 | B78: MINUTE | C78: MINUTE(time) | D78: Minute nikaalta hai | E78: Time breakdown | F78: MINUTE(A1)
A79: 10 | B79: SECOND | C79: SECOND(time) | D79: Seconds nikaalta hai | E79: Time breakdown | F79: SECOND(A1)
A80: 11 | B80: WEEKDAY | C80: WEEKDAY(date,[type]) | D80: Week day number deta hai | E80: Day identify | F80: WEEKDAY(A1,2)
A81: 12 | B81: WEEKNUM | C81: WEEKNUM(date,[type]) | D81: Week number deta hai | E81: Weekly tracking | F81: WEEKNUM(A1)
... A97: 28 | B97: NOW()+n | C97: NOW()+n | D97: Future time/date | E97: Scheduling | F97: NOW()+1
A102: Logical Formulae (20)
A103: S No | B103: Formula | C103: Syntax | D103: Meaning (Hinglish) | E103: Usage | F103: Example
A104: 1 | B104: IF | C104: IF(condition,value_if_true,value_if_false) | D104: Condition check karta hai | E104: Decision making | F104: =IF(A1>50,"Pass","Fail") -> Pass
A105: 2 | B105: IFS | C105: IFS(condition1,value1,condition2,value2,...) | D105: Multiple conditions check karta hai | E105: Multiple logic | F105: {=_xlfn.IFS(A1>90,"A",A1>50,"B")} -> A
A106: 3 | B106: AND | C106: AND(condition1,condition2,...) | D106: Sab conditions true honi chahiye | E106: Multi-condition check | F106: =AND(A1>50,B1>50) -> FALSE
A107: 4 | B107: OR | C107: OR(condition1,condition2,...) | D107: Koi ek condition true ho | E107: Flexible check | F107: =OR(A1>50,B1>50) -> TRUE
A108: 5 | B108: NOT | C108: NOT(condition) | D108: Result ko ulta kar deta hai | E108: Reverse logic | F108: =NOT(A1>50) -> FALSE
A109: 6 | B109: IFERROR | C109: IFERROR(value,value_if_error) | D109: Error aaye toh alternate value deta hai | E109: Error handling | F109: =IFERROR(A1/B1,"Error") -> Error
A110: 7 | B110: IFNA | C110: IFNA(value,value_if_na) | D110: Sirf #N/A error handle karta hai | E110: Lookup errors | F110: =IFNA(VLOOKUP(...),"Not Found")
A111: 8 | B111: SWITCH | C111: SWITCH(expression,value1,result1,...) | D111: Multiple matching conditions | E111: Cleaner IF alternative | F111: {=_xlfn.SWITCH(A1,1,"One",2,"Two")} -> #N/A
A112: 9 | B112: TRUE | C112: TRUE() | D112: TRUE return karta hai | E112: Logical testing | F112: =TRUE() -> TRUE
A113: 10 | B113: FALSE | C113: FALSE() | D113: FALSE return karta hai | E113: Logical testing | F113: =FALSE() -> FALSE
A114: 11 | B114: ISBLANK | C114: ISBLANK(value) | D114: Blank check karta hai | E114: Missing data | F114: =ISBLANK(A1) -> FALSE
A115: 12 | B115: ISNUMBER | C115: ISNUMBER(value) | D115: Number check karta hai | E115: Data validation | F115: =ISNUMBER(A1) -> FALSE
A116: 13 | B116: ISTEXT | C116: ISTEXT(value) | D116: Text check karta hai | E116: Data type check | F116: =ISTEXT(A1) -> TRUE
A117: 14 | B117: ISERROR | C117: ISERROR(value) | D117: Koi bhi error check karta hai | E117: Error detection | F117: =ISERROR(A1) -> FALSE
A118: 15 | B118: ISNA | C118: ISNA(value) | D118: #N/A error check karta hai | E118: Lookup validation | F118: =ISNA(A1) -> FALSE
A119: 16 | B119: ISLOGICAL | C119: ISLOGICAL(value) | D119: TRUE/FALSE check karta hai | E119: Logical validation | F119: =ISLOGICAL(A1) -> FALSE
A120: 17 | B120: ISFORMULA | C120: ISFORMULA(reference) | D120: Cell me formula hai ya nahi | E120: Audit purpose | F120: =_xlfn.ISFORMULA(A1) -> FALSE
A121: 18 | B121: EXACT | C121: EXACT(text1,text2) | D121: Case-sensitive match | E121: Exact comparison | F121: =EXACT("Excel","excel") -> FALSE
A122: 19 | B122: XOR | C122: XOR(condition1,condition2,...) | D122: Odd number of TRUE ho toh TRUE | E122: Advanced logic | F122: =_xlfn.XOR(A1>50,B1>50) -> TRUE
A123: 20 | B123: N | C123: N(value) | D123: TRUE=1, FALSE=0 convert karta hai | E123: Logical to number | F123: =N(TRUE) → 1
A130: Lookup & Refrence Formulae (20)
A131: S No | B131: Formula | C131: Syntax | D131: Meaning (Hinglish) | E131: Usage | F131: Example
A132: 1 | B132: VLOOKUP | C132: VLOOKUP(value,table,col_index,[range]) | D132: Vertical lookup karta hai | E132: Table se data fetch | F132: VLOOKUP(A1,B1:D10,2,FALSE)
A133: 2 | B133: HLOOKUP | C133: HLOOKUP(value,table,row_index,[range]) | D133: Horizontal lookup karta hai | E133: Row-wise search | F133: HLOOKUP(A1,B1:D5,2,FALSE)
A134: 3 | B134: XLOOKUP | C134: XLOOKUP(lookup,lookup_array,return_array) | D134: Advanced lookup (VLOOKUP ka upgrade) | E134: Flexible search | F134: XLOOKUP(A1,A2:A10,B2:B10)
A135: 4 | B135: LOOKUP | C135: LOOKUP(value,vector,result_vector) | D135: Basic lookup function | E135: Approx search | F135: LOOKUP(A1,A2:A10,B2:B10)
A136: 5 | B136: INDEX | C136: INDEX(array,row_num,[col_num]) | D136: Position se value return karta hai | E136: Exact data fetch | F136: INDEX(A1:C10,2,3)
A137: 6 | B137: MATCH | C137: MATCH(value,array,[match_type]) | D137: Position find karta hai | E137: Lookup support | F137: MATCH(A1,A1:A10,0)
...

Sheet Logical Formulas
A1: S no | B1: Students Name | C1: Hindi | D1: English | E1: Math | F1: Science | G1: Total | H1: % | I1: Status
A2: 1 | B2: Aarav Mehta | C2: 40 | D2: 38 | E2: 34 | F2: 77 | G2: =SUM(C2:F2) -> 189 | H2: =G2/400 -> 0.4725 | I2: =IF(H2>=50%,"Pass","Fail") -> Fail | J2: =IF(H2<50%,"Fail","Pass") -> Fail
A3: 2 | B3: Priya Sharma | C3: 35 | D3: 72 | E3: 76 | F3: 68 | G3: =SUM(C3:F3) -> 251 | H3: =G3/400 -> 0.6275 | I3: =IF(H3>=50%,"Pass","Fail") -> Pass | J3: =IF(H3<50%,"Fail","Pass") -> Pass
A4: 3 | B4: Ishaan Verma | C4: 85 | D4: 87 | E4: 58 | F4: 62 | G4: =SUM(C4:F4) -> 292 | H4: =G4/400 -> 0.73 | I4: =IF(H4>=50%,"Pass","Fail") -> Pass | J4: =IF(H4<50%,"Fail","Pass") -> Pass
A5: 4 | B5: Sneha Iyer | C5: 61 | D5: 52 | E5: 77 | F5: 67 | G5: =SUM(C5:F5) -> 257 | H5: =G5/400 -> 0.6425 | I5: =IF(H5>=50%,"Pass","Fail") -> Pass | J5: =IF(H5<50%,"Fail","Pass") -> Pass
A6: 5 | B6: Rohan Das | C6: 26 | D6: 91 | E6: 75 | F6: 38 | G6: =SUM(C6:F6) -> 230 | H6: =G6/400 -> 0.575 | I6: =IF(H6>=50%,"Pass","Fail") -> Pass | J6: =IF(H6<50%,"Fail","Pass") -> Pass
A7: 6 | B7: Kritika Nair | C7: 49 | D7: 55 | E7: 63 | F7: 73 | G7: =SUM(C7:F7) -> 240 | H7: =G7/400 -> 0.6 | I7: =IF(H7>=50%,"Pass","Fail") -> Pass | J7: =IF(H7<50%,"Fail","Pass") -> Pass
A8: 7 | B8: Yash Patel | C8: 44 | D8: 56 | E8: 92 | F8: 77 | G8: =SUM(C8:F8) -> 269 | H8: =G8/400 -> 0.6725 | I8: =IF(H8>=50%,"Pass","Fail") -> Pass | J8: =IF(H8<50%,"Fail","Pass") -> Pass
A9: 8 | B9: Ananya Reddy | C9: 95 | D9: 80 | E9: 62 | F9: 85 | G9: =SUM(C9:F9) -> 322 | H9: =G9/400 -> 0.805 | I9: =IF(H9>=50%,"Pass","Fail") -> Pass | J9: =IF(H9<50%,"Fail","Pass") -> Pass
A10: 9 | B10: Aditya Choudhary | C10: 64 | D10: 59 | E10: 85 | F10: 58 | G10: =SUM(C10:F10) -> 266 | H10: =G10/400 -> 0.665 | I10: =IF(H10>=50%,"Pass","Fail") -> Pass | J10: =IF(H10<50%,"Fail","Pass") -> Pass
A11: 10 | B11: Tanvi Joshi | C11: 32 | D11: 42 | E11: 30 | F11: 63 | G11: =SUM(C11:F11) -> 167 | H11: =G11/400 -> 0.4175 | I11: =IF(H11>=50%,"Pass","Fail") -> Fail | J11: =IF(H11<50%,"Fail","Pass") -> Fail
A12: 11 | B12: Nikhil Bansal | C12: 32 | D12: 68 | E12: 48 | F12: 95 | G12: =SUM(C12:F12) -> 243 | H12: =G12/400 -> 0.6075 | I12: =IF(H12>=50%,"Pass","Fail") -> Pass | J12: =IF(H12<50%,"Fail","Pass") -> Pass
A13: 12 | B13: Pooja Sinha | C13: 98 | D13: 53 | E13: 52 | F13: 57 | G13: =SUM(C13:F13) -> 260 | H13: =G13/400 -> 0.65 | I13: =IF(H13>=50%,"Pass","Fail") -> Pass | J13: =IF(H13<50%,"Fail","Pass") -> Pass
... A21: 20 | B21: Neha Jaiswal | C21: 26 | D21: 38 | E21: 33 | F21: 42 | G21: =SUM(C21:F21) -> 139 | H21: =G21/400 -> 0.3475 | I21: =IF(H21>=50%,"Pass","Fail") -> Fail | J21: =IF(H21<50%,"Fail","Pass") -> Fail
A31: S no | B31: Salesman | C31: Sales | D31: Rating | E31: IF And | F31: And | G31: Or | H31: IF or
A32: 1 | B32: Aarav Mehta | C32: 82269 | D32: 2 | E32: =IF(AND(C32>=50000,D32>=3),"Bonus Eligibile","No Bonus") -> No Bonus | F32: =AND(C32>=50000,D32>=3) -> FALSE | G32: =OR(C32>=50000,D32>=3) -> TRUE | H32: =IF(OR(C32>=50000,D32>=3),"Bonus Eligible", " No Bonus") -> Bonus Eligible
A33: 2 | B33: Priya Sharma | C33: 85056 | D33: 2 | E33: =IF(AND(C33>=50000,D33>=3),"Bonus Eligibile","No Bonus") -> No Bonus | F33: =AND(C33>=50000,D33>=3) -> FALSE | G33: =OR(C33>=50000,D33>=3) -> TRUE | H33: =IF(OR(C33>=50000,D33>=3),"Bonus Eligible", " No Bonus") -> Bonus Eligible
A34: 3 | B34: Ishaan Verma | C34: 65900 | D34: 3 | E34: =IF(AND(C34>=50000,D34>=3),"Bonus Eligibile","No Bonus") -> Bonus Eligibile | F34: =AND(C34>=50000,D34>=3) -> TRUE | G34: =OR(C34>=50000,D34>=3) -> TRUE | H34: =IF(OR(C34>=50000,D34>=3),"Bonus Eligible", " No Bonus") -> Bonus Eligible
A35: 4 | B35: Sneha Iyer | C35: 49825 | D35: 1 | E35: =IF(AND(C35>=50000,D35>=3),"Bonus Eligibile","No Bonus") -> No Bonus | F35: =AND(C35>=50000,D35>=3) -> FALSE | G35: =OR(C35>=50000,D35>=3) -> FALSE | H35: =IF(OR(C35>=50000,D35>=3),"Bonus Eligible", " No Bonus") -> No Bonus
A36: 5 | B36: Rohan Das | C36: 77583 | D36: 1 | E36: =IF(AND(C36>=50000,D36>=3),"Bonus Eligibile","No Bonus") -> No Bonus | F36: =AND(C36>=50000,D36>=3) -> FALSE | G36: =OR(C36>=50000,D36>=3) -> TRUE | H36: =IF(OR(C36>=50000,D36>=3),"Bonus Eligible", " No Bonus") -> Bonus Eligible
A37: 6 | B37: Kritika Nair | C37: 62039 | D37: 3 | E37: =IF(AND(C37>=50000,D37>=3),"Bonus Eligibile","No Bonus") -> Bonus Eligibile | F37: =AND(C37>=50000,D37>=3) -> TRUE | G37: =OR(C37>=50000,D37>=3) -> TRUE | H37: =IF(OR(C37>=50000,D37>=3),"Bonus Eligible", " No Bonus") -> Bonus Eligible
A38: 7 | B38: Yash Patel | C38: 49241 | D38: 4 | E38: =IF(AND(C38>=50000,D38>=3),"Bonus Eligibile","No Bonus") -> No Bonus | F38: =AND(C38>=50000,D38>=3) -> FALSE | G38: =OR(C38>=50000,D38>=3) -> TRUE | H38: =IF(OR(C38>=50000,D38>=3),"Bonus Eligible", " No Bonus") -> Bonus Eligible
A39: 8 | B39: Ananya Reddy | C39: 48046 | D39: 2 | E39: =IF(AND(C39>=50000,D39>=3),"Bonus Eligibile","No Bonus") -> No Bonus | F39: =AND(C39>=50000,D39>=3) -> FALSE | G39: =OR(C39>=50000,D39>=3) -> FALSE | H39: =IF(OR(C39>=50000,D39>=3),"Bonus Eligible", " No Bonus") -> No Bonus
A40: 9 | B40: Aditya Choudhary | C40: 13201 | D40: 4 | E40: =IF(AND(C40>=50000,D40>=3),"Bonus Eligibile","No Bonus") -> No Bonus | F40: =AND(C40>=50000,D40>=3) -> FALSE | G40: =OR(C40>=50000,D40>=3) -> TRUE | H40: =IF(OR(C40>=50000,D40>=3),"Bonus Eligible", " No Bonus") -> Bonus Eligible
A41: 10 | B41: Tanvi Joshi | C41: 63474 | D41: 5 | E41: =IF(AND(C41>=50000,D41>=3),"Bonus Eligibile","No Bonus") -> Bonus Eligibile | F41: =AND(C41>=50000,D41>=3) -> TRUE | G41: =OR(C41>=50000,D41>=3) -> TRUE | H41: =IF(OR(C41>=50000,D41>=3),"Bonus Eligible", " No Bonus") -> Bonus Eligible
A42: 11 | B42: Nikhil Bansal | C42: 67520 | D42: 1 | E42: =IF(AND(C42>=50000,D42>=3),"Bonus Eligibile","No Bonus") -> No Bonus | F42: =AND(C42>=50000,D42>=3) -> FALSE | G42: =OR(C42>=50000,D42>=3) -> TRUE | H42: =IF(OR(C42>=50000,D42>=3),"Bonus Eligible", " No Bonus") -> Bonus Eligible
A43: 12 | B43: Pooja Sinha | C43: 38646 | D43: 5 | E43: =IF(AND(C43>=50000,D43>=3),"Bonus Eligibile","No Bonus") -> No Bonus | F43: =AND(C43>=50000,D43>=3) -> FALSE | G43: =OR(C43>=50000,D43>=3) -> TRUE | H43: =IF(OR(C43>=50000,D43>=3),"Bonus Eligible", " No Bonus") -> Bonus Eligible
... A51: 20 | B51: Neha Jaiswal | C51: 81922 | D51: 5 | E51: =IF(AND(C51>=50000,D51>=3),"Bonus Eligibile","No Bonus") -> Bonus Eligibile | F51: =AND(C51>=50000,D51>=3) -> TRUE | G51: =OR(C51>=50000,D51>=3) -> TRUE | H51: =IF(OR(C51>=50000,D51>=3),"Bonus Eligible", " No Bonus") -> Bonus Eligible
A58: S no | B58: Students Name | C58: Hindi | D58: English | E58: Math | F58: Science | G58: Total | H58: % | I58: Grade | J58: Switch
A59: 1 | B59: Aarav Mehta | C59: 100 | D59: 100 | E59: 90 | F59: 90 | G59: =SUM(C59:F59) -> 380 | H59: =G59/400 -> 0.95 | I59: {=_xlfn.IFS(H59<30%,"D",H59<50%,"C",H59<75%,"B",H59<90%,"A",H59>90%,"A+")} -> A+ | J59: {=_xlfn.SWITCH(I59,"A+",10000,"A",5000,"B",2000,1000)} -> 10000 | L59: 0-30% | M59: D | N59: 1000
A60: 2 | B60: Priya Sharma | C60: 95 | D60: 85 | E60: 96 | F60: 95 | G60: =SUM(C60:F60) -> 371 | H60: =G60/400 -> 0.9275 | I60: {=_xlfn.IFS(H60<30%,"D",H60<50%,"C",H60<75%,"B",H60<90%,"A",H60>90%,"A+")} -> A+ | J60: {=_xlfn.SWITCH(I60,"A+",10000,"A",5000,"B",2000,1000)} -> 10000 | L60: 30%-50% | M60: C | N60: 1000
A61: 3 | B61: Ishaan Verma | C61: 85 | D61: 87 | E61: 58 | F61: 62 | G61: =SUM(C61:F61) -> 292 | H61: =G61/400 -> 0.73 | I61: {=_xlfn.IFS(H61<30%,"D",H61<50%,"C",H61<75%,"B",H61<90%,"A",H61>90%,"A+")} -> B | J61: {=_xlfn.SWITCH(I61,"A+",10000,"A",5000,"B",2000,1000)} -> 2000 | L61: 50%-75% | M61: B | N61: 2000
A62: 4 | B62: Sneha Iyer | C62: 61 | D62: 52 | E62: 77 | F62: 67 | G62: =SUM(C62:F62) -> 257 | H62: =G62/400 -> 0.6425 | I62: {=_xlfn.IFS(H62<30%,"D",H62<50%,"C",H62<75%,"B",H62<90%,"A",H62>90%,"A+")} -> B | J62: {=_xlfn.SWITCH(I62,"A+",10000,"A",5000,"B",2000,1000)} -> 2000 | L62: 75%-90% | M62: A | N62: 5000
A63: 5 | B63: Rohan Das | C63: 26 | D63: 91 | E63: 75 | F63: 38 | G63: =SUM(C63:F63) -> 230 | H63: =G63/400 -> 0.575 | I63: {=_xlfn.IFS(H63<30%,"D",H63<50%,"C",H63<75%,"B",H63<90%,"A",H63>90%,"A+")} -> B | J63: {=_xlfn.SWITCH(I63,"A+",10000,"A",5000,"B",2000,1000)} -> 2000 | L63: 90%-100% | M63: A+ | N63: 10000
A64: 6 | B64: Kritika Nair | C64: 49 | D64: 55 | E64: 63 | F64: 73 | G64: =SUM(C64:F64) -> 240 | H64: =G64/400 -> 0.6 | I64: {=_xlfn.IFS(H64<30%,"D",H64<50%,"C",H64<75%,"B",H64<90%,"A",H64>90%,"A+")} -> B | J64: {=_xlfn.SWITCH(I64,"A+",10000,"A",5000,"B",2000,1000)} -> 2000
A65: 7 | B65: Yash Patel | C65: 44 | D65: 56 | E65: 92 | F65: 77 | G65: =SUM(C65:F65) -> 269 | H65: =G65/400 -> 0.6725 | I65: {=_xlfn.IFS(H65<30%,"D",H65<50%,"C",H65<75%,"B",H65<90%,"A",H65>90%,"A+")} -> B | J65: {=_xlfn.SWITCH(I65,"A+",10000,"A",5000,"B",2000,1000)} -> 2000
A66: 8 | B66: Ananya Reddy | C66: 95 | D66: 80 | E66: 62 | F66: 85 | G66: =SUM(C66:F66) -> 322 | H66: =G66/400 -> 0.805 | I66: {=_xlfn.IFS(H66<30%,"D",H66<50%,"C",H66<75%,"B",H66<90%,"A",H66>90%,"A+")} -> A | J66: {=_xlfn.SWITCH(I66,"A+",10000,"A",5000,"B",2000,1000)} -> 5000
A67: 9 | B67: Aditya Choudhary | C67: 64 | D67: 59 | E67: 85 | F67: 58 | G67: =SUM(C67:F67) -> 266 | H67: =G67/400 -> 0.665 | I67: {=_xlfn.IFS(H67<30%,"D",H67<50%,"C",H67<75%,"B",H67<90%,"A",H67>90%,"A+")} -> B | J67: {=_xlfn.SWITCH(I67,"A+",10000,"A",5000,"B",2000,1000)} -> 2000
A68: 10 | B68: Tanvi Joshi | C68: 32 | D68: 42 | E68: 30 | F68: 63 | G68: =SUM(C68:F68) -> 167 | H68: =G68/400 -> 0.4175 | I68: {=_xlfn.IFS(H68<30%,"D",H68<50%,"C",H68<75%,"B",H68<90%,"A",H68>90%,"A+")} -> C | J68: {=_xlfn.SWITCH(I68,"A+",10000,"A",5000,"B",2000,1000)} -> 1000
A69: 11 | B69: Nikhil Bansal | C69: 32 | D69: 68 | E69: 48 | F69: 95 | G69: =SUM(C69:F69) -> 243 | H69: =G69/400 -> 0.6075 | I69: {=_xlfn.IFS(H69<30%,"D",H69<50%,"C",H69<75%,"B",H69<90%,"A",H69>90%,"A+")} -> B | J69: {=_xlfn.SWITCH(I69,"A+",10000,"A",5000,"B",2000,1000)} -> 2000
A70: 12 | B70: Pooja Sinha | C70: 98 | D70: 98 | E70: 100 | F70: 100 | G70: =SUM(C70:F70) -> 396 | H70: =G70/400 -> 0.99 | I70: {=_xlfn.IFS(H70<30%,"D",H70<50%,"C",H70<75%,"B",H70<90%,"A",H70>90%,"A+")} -> A+ | J70: {=_xlfn.SWITCH(I70,"A+",10000,"A",5000,"B",2000,1000)} -> 10000
A71: 13 | B71: Harshvardhan Gupta | C71: 61 | D71: 83 | E71: 39 | F71: 80 | G71: =SUM(C71:F71) -> 263 | H71: =G71/400 -> 0.6575 | I71: {=_xlfn.IFS(H71<30%,"D",H71<50%,"C",H71<75%,"B",H71<90%,"A",H71>90%,"A+")} -> B | J71: {=_xlfn.SWITCH(I71,"A+",10000,"A",5000,"B",2000,1000)} -> 2000
A72: 14 | B72: Meera Menon | C72: 58 | D72: 87 | E72: 72 | F72: 46 | G72: =SUM(C72:F72) -> 263 | H72: =G72/400 -> 0.6575 | I72: {=_xlfn.IFS(H72<30%,"D",H72<50%,"C",H72<75%,"B",H72<90%,"A",H72>90%,"A+")} -> B | J72: {=_xlfn.SWITCH(I72,"A+",10000,"A",5000,"B",2000,1000)} -> 2000
A73: 15 | B73: Siddharth Rao | C73: 71 | D73: 64 | E73: 25 | F73: 66 | G73: =SUM(C73:F73) -> 226 | H73: =G73/400 -> 0.565 | I73: {=_xlfn.IFS(H73<30%,"D",H73<50%,"C",H73<75%,"B",H73<90%,"A",H73>90%,"A+")} -> B | J73: {=_xlfn.SWITCH(I73,"A+",10000,"A",5000,"B",2000,1000)} -> 2000
A74: 16 | B74: Ritika Sengupta | C74: 80 | D74: 31 | E74: 96 | F74: 94 | G74: =SUM(C74:F74) -> 301 | H74: =G74/400 -> 0.7525 | I74: {=_xlfn.IFS(H74<30%,"D",H74<50%,"C",H74<75%,"B",H74<90%,"A",H74>90%,"A+")} -> A | J74: {=_xlfn.SWITCH(I74,"A+",10000,"A",5000,"B",2000,1000)} -> 5000
A75: 17 | B75: Kunal Thakur | C75: 72 | D75: 10 | E75: 10 | F75: 10 | G75: =SUM(C75:F75) -> 102 | H75: =G75/400 -> 0.255 | I75: {=_xlfn.IFS(H75<30%,"D",H75<50%,"C",H75<75%,"B",H75<90%,"A",H75>90%,"A+")} -> D | J75: {=_xlfn.SWITCH(I75,"A+",10000,"A",5000,"B",2000,1000)} -> 1000
... A78: 20 | B78: Neha Jaiswal | C78: 26 | D78: 38 | E78: 33 | F78: 42 | G78: =SUM(C78:F78) -> 139 | H78: =G78/400 -> 0.3475 | I78: {=_xlfn.IFS(H78<30%,"D",H78<50%,"C",H78<75%,"B",H78<90%,"A",H78>90%,"A+")} -> C | J78: {=_xlfn.SWITCH(I78,"A+",10000,"A",5000,"B",2000,1000)} -> 1000
E90: 50 | F90: 0 | G90: =IFERROR(E90/F90,"Value is Wrong") -> Value is Wrong
E96: 6846 | F96: =ISEVEN(E96) -> TRUE | G96: =ISTEXT(E96) -> FALSE

Sheet Date n Time Formulas (2)
B2: Current Date | F2: 45728 | G2: Current Time | K2: 0.49097222
B5: Date | C5: Text | D5: Day | E5: Month | F5: Year | G5: Date
B6: 41043
B7: 36126
B8: 45147
B9: 38383
B10: 42938
B11: 34247
B12: 40255
B13: 44536
B14: 36645
B15: 42258
A24: Holidays | B24: Start Date | C24: End Date | D24: Days | E24: Days360 | F24: Networkdays | G24: Networkdays (holidays) | H24: Networkdays.intl | I24: Networkdays.intl (HOLIDAY)
A25: 45385 | B25: 45604 | C25: 45646
A26: 45428 | B26: 45342 | C26: 45562
A27: 45509 | B27: 45680 | C27: 45723
A28: 45529 | B28: 45292 | C28: 45433
A29: 45535 | B29: 45441 | C29: 45595
A30: 45553 | B30: 45632 | C30: 45701
A31: 45590 | B31: 45526 | C31: 45724
A32: 45652 | B32: 45668 | C32: 45705
A33: 45693 | B33: 45509 | C33: 45763
A34: 45693 | B34: 45602 | C34: 45662
B45: Start Date | C45: Months | D45: Days | E45: Edate | F45: Eomonth
B46: 45604 | C46: 2 | D46: 60
B47: 45342 | C47: 3 | D47: 90
B48: 45680 | C48: 3 | D48: 65
B49: 45292 | C49: 4 | D49: 52
B50: 45441 | C50: 6 | D50: 62
B51: 45632 | C51: 5 | D51: 32
B52: 45526 | C52: 2 | D52: 60
B53: 45668 | C53: 3 | D53: 90
B54: 45509 | C54: 1 | D54: 30
B55: 45602 | C55: 2 | D55: 62
B63: Start Date | C63: Holidays | D63: Days | E63: Workday | F63: Workday (holiday) | G63: Workday.intl | H63: Workday.intl (holiday)
B64: 45604 | C64: 45385 | D64: 50
B65: 45342 | C65: 45428 | D65: 60
B66: 45680 | C66: 45509 | D66: 20
B67: 45292 | C67: 45529 | D67: 35
B68: 45441 | C68: 45535 | D68: 45
B69: 45632 | C69: 45553 | D69: 52
B70: 45526 | C70: 45590 | D70: 42
B71: 45668 | C71: 45652 | D71: 50
B72: 45509 | C72: 45693 | D72: 52
B73: 45602 | C73: 45693 | D73: 42
B84: Time | C84: Hour | D84: Minute | E84: Second
B85: 0.38255787
B86: 0.92321759
B87: 0.066527778
B88: 0.96116898
B89: 0.056643519
B90: 0.58608796
B91: 0.25799769
B92: 0.71309028
B93: 0.55476852
B94: 0.25489583

Sheet Date n Time Formulas
B2: Current Date | C2: =TODAY() -> 46130 | F2: 46122 | G2: Current Time | H2: =NOW() -> 46130.705 | K2: 0.61875
B5: Date | C5: Text | D5: Day | E5: Month | F5: Year | G5: Date
B6: 41043 | C6: =TEXT(B6,"ddd") -> Mon | D6: =DAY(B6) -> 14 | E6: =MONTH(B6) -> 5 | F6: =YEAR(B6) -> 2012 | G6: =DATE(F6,E6,D6) -> 41043
B7: 36126 | C7: =TEXT(B7,"ddd") -> Fri | D7: =DAY(B7) -> 27 | E7: =MONTH(B7) -> 11 | F7: =YEAR(B7) -> 1998 | G7: =DATE(F7,E7,D7) -> 36126
B8: 45147 | C8: =TEXT(B8,"ddd") -> Wed | D8: =DAY(B8) -> 9 | E8: =MONTH(B8) -> 8 | F8: =YEAR(B8) -> 2023 | G8: =DATE(F8,E8,D8) -> 45147
B9: 38383 | C9: =TEXT(B9,"ddd") -> Mon | D9: =DAY(B9) -> 31 | E9: =MONTH(B9) -> 1 | F9: =YEAR(B9) -> 2005 | G9: =DATE(F9,E9,D9) -> 38383
B10: 42938 | C10: =TEXT(B10,"ddd") -> Sat | D10: =DAY(B10) -> 22 | E10: =MONTH(B10) -> 7 | F10: =YEAR(B10) -> 2017 | G10: =DATE(F10,E10,D10) -> 42938
B11: 34247 | C11: =TEXT(B11,"ddd") -> Tue | D11: =DAY(B11) -> 5 | E11: =MONTH(B11) -> 10 | F11: =YEAR(B11) -> 1993 | G11: =DATE(F11,E11,D11) -> 34247
B12: 40255 | C12: =TEXT(B12,"ddd") -> Thu | D12: =DAY(B12) -> 18 | E12: =MONTH(B12) -> 3 | F12: =YEAR(B12) -> 2010 | G12: =DATE(F12,E12,D12) -> 40255
B13: 44536 | C13: =TEXT(B13,"ddd") -> Mon | D13: =DAY(B13) -> 6 | E13: =MONTH(B13) -> 12 | F13: =YEAR(B13) -> 2021 | G13: =DATE(F13,E13,D13) -> 44536
B14: 36645 | C14: =TEXT(B14,"ddd") -> Sat | D14: =DAY(B14) -> 29 | E14: =MONTH(B14) -> 4 | F14: =YEAR(B14) -> 2000 | G14: =DATE(F14,E14,D14) -> 36645
B15: 42258 | C15: =TEXT(B15,"ddd") -> Fri | D15: =DAY(B15) -> 11 | E15: =MONTH(B15) -> 9 | F15: =YEAR(B15) -> 2015 | G15: =DATE(F15,E15,D15) -> 42258
A24: Holidays | B24: Start Date | C24: End Date | D24: Days | E24: Days360 | F24: Networkdays | G24: Networkdays (holidays) | H24: Networkdays.intl | I24: Networkdays.intl (HOLIDAY)
A25: 46117 | B25: 46106 | C25: 46117 | D25: =_xlfn.DAYS(C25,B25) -> 11 | E25: =DAYS360(B25,C25) -> 10 | F25: =NETWORKDAYS(B25,C25) -> 8 | G25: =NETWORKDAYS(B25,C25,A25) -> 8 | H25: =NETWORKDAYS.INTL(B25,C25,11) -> 10 | I25: =NETWORKDAYS.INTL(B25,C25,11,A25) -> 10
A26: 46085 | B26: 46078 | C26: 46086 | D26: =_xlfn.DAYS(C26,B26) -> 8 | E26: =DAYS360(B26,C26) -> 10 | F26: =NETWORKDAYS(B26,C26) -> 7 | G26: =NETWORKDAYS(B26,C26,A26) -> 6 | H26: =NETWORKDAYS.INTL(B26,C26,11) -> 8 | I26: =NETWORKDAYS.INTL(B26,C26,11,A26) -> 7
A27: 45509 | B27: 45680 | C27: 45723 | D27: =_xlfn.DAYS(C27,B27) -> 43 | E27: =DAYS360(B27,C27) -> 44 | F27: =NETWORKDAYS(B27,C27) -> 32 | G27: =NETWORKDAYS(B27,C27,A27) -> 32 | H27: =NETWORKDAYS.INTL(B27,C27,11) -> 38 | I27: =NETWORKDAYS.INTL(B27,C27,11,A27) -> 38
A28: 45529 | B28: 45292 | C28: 45433 | D28: =_xlfn.DAYS(C28,B28) -> 141 | E28: =DAYS360(B28,C28) -> 140 | F28: =NETWORKDAYS(B28,C28) -> 102 | G28: =NETWORKDAYS(B28,C28,A28) -> 102 | H28: =NETWORKDAYS.INTL(B28,C28,11) -> 122 | I28: =NETWORKDAYS.INTL(B28,C28,11,A28) -> 122
A29: 45535 | B29: 45441 | C29: 45595 | D29: =_xlfn.DAYS(C29,B29) -> 154 | E29: =DAYS360(B29,C29) -> 151 | F29: =NETWORKDAYS(B29,C29) -> 111 | G29: =NETWORKDAYS(B29,C29,A29) -> 111 | H29: =NETWORKDAYS.INTL(B29,C29,11) -> 133 | I29: =NETWORKDAYS.INTL(B29,C29,11,A29) -> 132
A30: 45553 | B30: 45632 | C30: 45701 | D30: =_xlfn.DAYS(C30,B30) -> 69 | E30: =DAYS360(B30,C30) -> 67 | F30: =NETWORKDAYS(B30,C30) -> 50 | G30: =NETWORKDAYS(B30,C30,A30) -> 50 | H30: =NETWORKDAYS.INTL(B30,C30,11) -> 60 | I30: =NETWORKDAYS.INTL(B30,C30,11,A30) -> 60
A31: 45590 | B31: 45526 | C31: 45724 | D31: =_xlfn.DAYS(C31,B31) -> 198 | E31: =DAYS360(B31,C31) -> 196 | F31: =NETWORKDAYS(B31,C31) -> 142 | G31: =NETWORKDAYS(B31,C31,A31) -> 141 | H31: =NETWORKDAYS.INTL(B31,C31,11) -> 171 | I31: =NETWORKDAYS.INTL(B31,C31,11,A31) -> 170
A32: 45652 | B32: 45668 | C32: 45705 | D32: =_xlfn.DAYS(C32,B32) -> 37 | E32: =DAYS360(B32,C32) -> 36 | F32: =NETWORKDAYS(B32,C32) -> 26 | G32: =NETWORKDAYS(B32,C32,A32) -> 26 | H32: =NETWORKDAYS.INTL(B32,C32,11) -> 32 | I32: =NETWORKDAYS.INTL(B32,C32,11,A32) -> 32
A33: 45693 | B33: 45509 | C33: 45763 | D33: =_xlfn.DAYS(C33,B33) -> 254 | E33: =DAYS360(B33,C33) -> 251 | F33: =NETWORKDAYS(B33,C33) -> 183 | G33: =NETWORKDAYS(B33,C33,A33) -> 182 | H33: =NETWORKDAYS.INTL(B33,C33,11) -> 219 | I33: =NETWORKDAYS.INTL(B33,C33,11,A33) -> 218
A34: 45693 | B34: 45602 | C34: 45662 | D34: =_xlfn.DAYS(C34,B34) -> 60 | E34: =DAYS360(B34,C34) -> 59 | F34: =NETWORKDAYS(B34,C34) -> 43 | G34: =NETWORKDAYS(B34,C34,A34) -> 43 | H34: =NETWORKDAYS.INTL(B34,C34,11) -> 52 | I34: =NETWORKDAYS.INTL(B34,C34,11,A34) -> 52
B45: Start Date | C45: Months | D45: Days | E45: Edate | F45: Eomonth | H45: 46143 | I45: =EOMONTH(H45,0) -> 46173
B46: 45604 | C46: 2 | D46: 60 | E46: =EDATE(B46,C46) -> 45665 | F46: =EOMONTH(B46,C46) -> 45688
B47: 45342 | C47: 3 | D47: 90 | E47: =EDATE(B47,C47) -> 45432 | F47: =EOMONTH(B47,C47) -> 45443
B48: 45680 | C48: 3 | D48: 65 | E48: =EDATE(B48,C48) -> 45770 | F48: =EOMONTH(B48,C48) -> 45777
B49: 45292 | C49: 4 | D49: 52 | E49: =EDATE(B49,C49) -> 45413 | F49: =EOMONTH(B49,C49) -> 45443
B50: 45441 | C50: 6 | D50: 62 | E50: =EDATE(B50,C50) -> 45625 | F50: =EOMONTH(B50,C50) -> 45626
B51: 45632 | C51: 5 | D51: 32 | E51: =EDATE(B51,C51) -> 45783 | F51: =EOMONTH(B51,C51) -> 45808
B52: 45526 | C52: 2 | D52: 60 | E52: =EDATE(B52,C52) -> 45587 | F52: =EOMONTH(B52,C52) -> 45596
B53: 45668 | C53: 3 | D53: 90 | E53: =EDATE(B53,C53) -> 45758 | F53: =EOMONTH(B53,C53) -> 45777
B54: 45509 | C54: 1 | D54: 30 | E54: =EDATE(B54,C54) -> 45540 | F54: =EOMONTH(B54,C54) -> 45565
B55: 45602 | C55: 2 | D55: 62 | E55: =EDATE(B55,C55) -> 45663 | F55: =EOMONTH(B55,C55) -> 45688
B63: Start Date | C63: Holidays | D63: Days | E63: Workday | F63: Workday (holiday) | G63: Workday.intl | H63: Workday.intl (holiday)
B64: 46110 | C64: 46115 | D64: 10 | E64: =WORKDAY(B64,D64) -> 46122 | F64: =WORKDAY(B64,D64,C64) -> 46125 | G64: =WORKDAY.INTL(B64,D64,11) -> 46121 | H64: =WORKDAY.INTL(B64,D64,11,C64) -> 46122
B65: 45342 | C65: 45428 | D65: 60 | E65: =WORKDAY(B65,D65) -> 45426 | F65: =WORKDAY(B65,D65,C65) -> 45426 | G65: =WORKDAY.INTL(B65,D65,11) -> 45412 | H65: =WORKDAY.INTL(B65,D65,11,C65) -> 45412
B66: 45680 | C66: 45509 | D66: 20 | E66: =WORKDAY(B66,D66) -> 45708 | F66: =WORKDAY(B66,D66,C66) -> 45708 | G66: =WORKDAY.INTL(B66,D66,11) -> 45703 | H66: =WORKDAY.INTL(B66,D66,11,C66) -> 45703
B67: 45292 | C67: 45529 | D67: 35 | E67: =WORKDAY(B67,D67) -> 45341 | F67: =WORKDAY(B67,D67,C67) -> 45341 | G67: =WORKDAY.INTL(B67,D67,11) -> 45332 | H67: =WORKDAY.INTL(B67,D67,11,C67) -> 45332
B68: 45441 | C68: 45535 | D68: 45 | E68: =WORKDAY(B68,D68) -> 45504 | F68: =WORKDAY(B68,D68,C68) -> 45504 | G68: =WORKDAY.INTL(B68,D68,11) -> 45493 | H68: =WORKDAY.INTL(B68,D68,11,C68) -> 45493
B69: 45632 | C69: 45553 | D69: 52 | E69: =WORKDAY(B69,D69) -> 45706 | F69: =WORKDAY(B69,D69,C69) -> 45706 | G69: =WORKDAY.INTL(B69,D69,11) -> 45693 | H69: =WORKDAY.INTL(B69,D69,11,C69) -> 45693
B70: 45526 | C70: 45590 | D70: 42 | E70: =WORKDAY(B70,D70) -> 45586 | F70: =WORKDAY(B70,D70,C70) -> 45586 | G70: =WORKDAY.INTL(B70,D70,11) -> 45575 | H70: =WORKDAY.INTL(B70,D70,11,C70) -> 45575
B71: 45668 | C71: 45652 | D71: 50 | E71: =WORKDAY(B71,D71) -> 45737 | F71: =WORKDAY(B71,D71,C71) -> 45737 | G71: =WORKDAY.INTL(B71,D71,11) -> 45727 | H71: =WORKDAY.INTL(B71,D71,11,C71) -> 45727
B72: 45509 | C72: 45693 | D72: 52 | E72: =WORKDAY(B72,D72) -> 45581 | F72: =WORKDAY(B72,D72,C72) -> 45581 | G72: =WORKDAY.INTL(B72,D72,11) -> 45569 | H72: =WORKDAY.INTL(B72,D72,11,C72) -> 45569
B73: 45602 | C73: 45693 | D73: 42 | E73: =WORKDAY(B73,D73) -> 45660 | F73: =WORKDAY(B73,D73,C73) -> 45660 | G73: =WORKDAY.INTL(B73,D73,11) -> 45651 | H73: =WORKDAY.INTL(B73,D73,11,C73) -> 45651
B84: Time | C84: Hour | D84: Minute | E84: Second | F84: Time
B85: 0.38255787 | C85: =HOUR(B85) -> 9 | D85: =MINUTE(B85) -> 10 | E85: =SECOND(B85) -> 53 | F85: =TIME(C85,D85,E85) -> 0.38255787
B86: 0.92321759 | C86: =HOUR(B86) -> 22 | D86: =MINUTE(B86) -> 9 | E86: =SECOND(B86) -> 26 | F86: =TIME(C86,D86,E86) -> 0.92321759
B87: 0.066527778 | C87: =HOUR(B87) -> 1 | D87: =MINUTE(B87) -> 35 | E87: =SECOND(B87) -> 48 | F87: =TIME(C87,D87,E87) -> 0.066527778
B88: 0.96116898 | C88: =HOUR(B88) -> 23 | D88: =MINUTE(B88) -> 4 | E88: =SECOND(B88) -> 5 | F88: =TIME(C88,D88,E88) -> 0.96116898
B89: 0.056643519 | C89: =HOUR(B89) -> 1 | D89: =MINUTE(B89) -> 21 | E89: =SECOND(B89) -> 34 | F89: =TIME(C89,D89,E89) -> 0.056643519
B90: 0.58608796 | C90: =HOUR(B90) -> 14 | D90: =MINUTE(B90) -> 3 | E90: =SECOND(B90) -> 58 | F90: =TIME(C90,D90,E90) -> 0.58608796
B91: 0.25799769 | C91: =HOUR(B91) -> 6 | D91: =MINUTE(B91) -> 11 | E91: =SECOND(B91) -> 31 | F91: =TIME(C91,D91,E91) -> 0.25799769
B92: 0.71309028 | C92: =HOUR(B92) -> 17 | D92: =MINUTE(B92) -> 6 | E92: =SECOND(B92) -> 51 | F92: =TIME(C92,D92,E92) -> 0.71309028
B93: 0.55476852 | C93: =HOUR(B93) -> 13 | D93: =MINUTE(B93) -> 18 | E93: =SECOND(B93) -> 52 | F93: =TIME(C93,D93,E93) -> 0.55476852
B94: 0.25489583 | C94: =HOUR(B94) -> 6 | D94: =MINUTE(B94) -> 7 | E94: =SECOND(B94) -> 3 | F94: =TIME(C94,D94,E94) -> 0.25489583
C116: DOB | D116: Today | E116: Datedif | F116: Yearfrac
C117: 36940 | D117: 46122 | E117: =DATEDIF(C117,D117,"Y") -> 25 | F117: =YEARFRAC(C117,D117) -> 25.144444
E119: =WEEKDAY(D117) -> 6
E120: =WEEKNUM(D117) -> 15
C122: =TODAY()+7 -> 46137

Sheet Number Formulas
A1: Rand (0 to 1)
A2: =RAND() -> 0.0021902235 | B2: =RAND() -> 0.19636937 | C2: =RAND() -> 0.16405
A3: =RAND() -> 0.34639094 | B3: =RAND() -> 0.13355238 | C3: =RAND() -> 0.54592086
A4: =RAND() -> 0.099037107 | B4: =RAND() -> 0.82019816 | C4: =RAND() -> 0.52791368
A5: =RAND() -> 0.11721299 | B5: =RAND() -> 0.86531061 | C5: =RAND() -> 0.71289322
A6: =RAND() -> 0.59885354 | B6: =RAND() -> 0.29779912 | C6: =RAND() -> 0.13217502
A7: =RAND() -> 0.017868615 | B7: =RAND() -> 0.026714302 | C7: =RAND() -> 0.043508455
A10: Rand Between (Range)
A11: =RANDBETWEEN(0,100) -> 79 | B11: =RANDBETWEEN(0,100) -> 91 | C11: =RANDBETWEEN(0,100) -> 89
A12: =RANDBETWEEN(0,100) -> 10 | B12: =RANDBETWEEN(0,100) -> 70 | C12: =RANDBETWEEN(0,100) -> 65
A13: =RANDBETWEEN(0,100) -> 24 | B13: =RANDBETWEEN(0,100) -> 60 | C13: =RANDBETWEEN(0,100) -> 56
A14: =RANDBETWEEN(0,100) -> 94 | B14: =RANDBETWEEN(0,100) -> 83 | C14: =RANDBETWEEN(0,100) -> 100
A15: =RANDBETWEEN(0,100) -> 59 | B15: =RANDBETWEEN(0,100) -> 52 | C15: =RANDBETWEEN(0,100) -> 31
A16: =RANDBETWEEN(0,100) -> 82 | B16: =RANDBETWEEN(0,100) -> 95 | C16: =RANDBETWEEN(0,100) -> 43
A17: =RANDBETWEEN(0,100) -> 15 | B17: =RANDBETWEEN(0,100) -> 55 | C17: =RANDBETWEEN(0,100) -> 40
A18: =RANDBETWEEN(0,100) -> 60 | B18: =RANDBETWEEN(0,100) -> 24 | C18: =RANDBETWEEN(0,100) -> 42
A22: Rand Array
A23: {=_xlfn.RANDARRAY(5,4,0,100,TRUE)} -> 84 | B23: 45 | C23: 36 | D23: 22
A24: 56 | B24: 65 | C24: 77 | D24: 72
A25: 60 | B25: 35 | C25: 49 | D25: 69
A26: 14 | B26: 96 | C26: 20 | D26: 10
A27: 38 | B27: 64 | C27: 12 | D27: 30
A31: Rand Array
A32: 41 | B32: 49 | C32: 92 | D32: 33
A33: 23 | B33: 12 | C33: 43 | D33: 29
A34: 77 | B34: 32 | C34: 5 | D34: 97
A35: 56 | B35: 66 | C35: 91 | D35: 21
A36: 89 | B36: 19 | C36: 10 | D36: 57
A43: 30707 | C43: 1 | D43: =LARGE(A43:A50,C43) -> 94832 | E43: =SMALL(A43:A50,C43) -> 11148 | F43: =SMALL($A$43:$A$50,C43) -> 11148
A44: 29747 | C44: 2 | D44: =LARGE(A44:A51,C44) -> 88535 | E44: =SMALL(A44:A51,C44) -> 29747 | F44: =SMALL($A$43:$A$50,C44) -> 29747
A45: 45679 | C45: 3 | D45: =LARGE(A45:A52,C45) -> 64561 | E45: =SMALL(A45:A52,C45) -> 45679 | F45: =SMALL($A$43:$A$50,C45) -> 30707
A46: 94832
A47: 64561
A48: 88535
A49: 37974
A50: 11148
A55: Round | D55: Round up | G55: Round Down | I55: Integer | J55: Trunc
A56: 1318.0083 | B56: =ROUND(A56,2) -> 1318.01 | D56: 1318.0083 | E56: =ROUNDUP(D56,2) -> 1318.01 | G56: 1318.0083 | H56: =ROUNDDOWN(G56,2) -> 1318 | I56: =INT(G56) -> 1318 | J56: =TRUNC(G56,1) -> 1318
A57: 4504.4012 | B57: =ROUND(A57,2) -> 4504.4 | D57: 4504.4012 | E57: =ROUNDUP(D57,2) -> 4504.41 | G57: 4504.4012 | H57: =ROUNDDOWN(G57,2) -> 4504.4 | I57: =INT(G57) -> 4504 | J57: =TRUNC(G57,1) -> 4504.4
A58: 1469.1423 | B58: =ROUND(A58,2) -> 1469.14 | D58: 1469.1423 | E58: =ROUNDUP(D58,2) -> 1469.15 | G58: 1469.1423 | H58: =ROUNDDOWN(G58,2) -> 1469.14 | I58: =INT(G58) -> 1469 | J58: =TRUNC(G58,1) -> 1469.1
A59: 7551.7682 | B59: =ROUND(A59,2) -> 7551.77 | D59: 7551.7682 | E59: =ROUNDUP(D59,2) -> 7551.77 | G59: 7551.7682 | H59: =ROUNDDOWN(G59,2) -> 7551.76 | I59: =INT(G59) -> 7551 | J59: =TRUNC(G59,1) -> 7551.7
A60: 5878.8671 | B60: =ROUND(A60,2) -> 5878.87 | D60: 5878.8671 | E60: =ROUNDUP(D60,2) -> 5878.87 | G60: 5878.8671 | H60: =ROUNDDOWN(G60,2) -> 5878.86 | I60: =INT(G60) -> 5878 | J60: =TRUNC(G60,1) -> 5878.8
A61: 1797.2407 | B61: =ROUND(A61,2) -> 1797.24 | D61: 1797.2407 | E61: =ROUNDUP(D61,2) -> 1797.25 | G61: 1797.2407 | H61: =ROUNDDOWN(G61,2) -> 1797.24 | I61: =INT(G61) -> 1797 | J61: =TRUNC(G61,1) -> 1797.2
A62: 9736.2945 | B62: =ROUND(A62,2) -> 9736.29 | D62: 9736.2945 | E62: =ROUNDUP(D62,2) -> 9736.3 | G62: 9736.2945 | H62: =ROUNDDOWN(G62,2) -> 9736.29 | I62: =INT(G62) -> 9736 | J62: =TRUNC(G62,1) -> 9736.2
C71: Floor | D71: Ceiling | E71: Mround
B72: 50 | C72: =FLOOR(B72,3) -> 48 | D72: =CEILING(B72,3) -> 51 | E72: =MROUND(B72,3) -> 51

Sheet Sumif etc (2)
A3: Party Names | B3: Sales | D3: Party Names | E3: Total Sales | F3: Average Sale | G3: Count Of Sale
A4: SwiftNova Enterprises | B4: 24750 | D4: SwiftNova Enterprises
A5: BluePeak Solutions | B5: 43891 | D5: BluePeak Solutions
A6: EliteCrest Innovations | B6: 36623 | D6: EliteCrest Innovations
A7: QuantumByte Technologies | B7: 33686 | D7: QuantumByte Technologies
A8: GoldenLeaf Ventures | B8: 37488 | D8: GoldenLeaf Ventures
A9: UrbanNest Interiors | B9: 21012 | D9: UrbanNest Interiors
A10: Vertex Synergy | B10: 34133 | D10: Vertex Synergy
A11: EverGlow Essentials | B11: 25015 | D11: EverGlow Essentials
A12: TruHarvest Organics | B12: 24185 | D12: TruHarvest Organics
A13: StellarEdge Consulting | B13: 27419 | D13: StellarEdge Consulting
A14: SwiftNova Enterprises | B14: 20989 | D14: Total Sale
A15: BluePeak Solutions | B15: 37327
A16: EliteCrest Innovations | B16: 14753
A17: QuantumByte Technologies | B17: 16689
A18: GoldenLeaf Ventures | B18: 38507
A19: EliteCrest Innovations | B19: 14720
A20: QuantumByte Technologies | B20: 38768
A21: GoldenLeaf Ventures | B21: 45280
A22: UrbanNest Interiors | B22: 49176
A23: Vertex Synergy | B23: 39695
A24: EverGlow Essentials | B24: 19380
A25: TruHarvest Organics | B25: 32705
A26: StellarEdge Consulting | B26: 37700
... A341: EverGlow Essentials | B341: 17811
B342: =SUM(B4:B341) -> 10175331

Sheet Sumif etc
A1: Party Names | B1: Sales | D1: Party Names | E1: Total Sales | F1: Average Sale | G1: Count Of Sale
A2: SwiftNova Enterprises | B2: 24750 | D2: SwiftNova Enterprises | E2: =SUMIF($A$2:$A$339,$D2,$B$2:$B$339) -> 805869 | F2: =AVERAGEIF($A$2:$A$339,D2,$B$2:$B$339) -> 28781.036 | G2: =COUNTIF($A$2:$A$339,D2) -> 28 | K2: Attendance Tracker 365
A3: BluePeak Solutions | B3: 43891 | D3: BluePeak Solutions | E3: =SUMIF($A$2:$A$339,$D3,$B$2:$B$339) -> 847774 | F3: =AVERAGEIF($A$2:$A$339,D3,$B$2:$B$339) -> 30277.643 | G3: =COUNTIF($A$2:$A$339,D3) -> 28 | K3: S no | L3: Students Name | M3: Mon | N3: Tue | O3: Wed | P3: Thu | Q3: Fri | R3: Present | S3: Absent
A4: EliteCrest Innovations | B4: 36623 | D4: EliteCrest Innovations | E4: =SUMIF($A$2:$A$339,$D4,$B$2:$B$339) -> 896206 | F4: =AVERAGEIF($A$2:$A$339,D4,$B$2:$B$339) -> 27157.758 | G4: =COUNTIF($A$2:$A$339,D4) -> 33 | K4: 1 | L4: Aarav Sharma | M4: TRUE | N4: FALSE | O4: FALSE | P4: FALSE | Q4: FALSE | R4: =COUNTIF(M4:Q4,"True") -> 1 | S4: =COUNTIF(M4:Q4,"False") -> 4
A5: QuantumByte Technologies | B5: 33686 | D5: QuantumByte Technologies | E5: =SUMIF($A$2:$A$339,$D5,$B$2:$B$339) -> 913593 | F5: =AVERAGEIF($A$2:$A$339,D5,$B$2:$B$339) -> 27684.636 | G5: =COUNTIF($A$2:$A$339,D5) -> 33 | K5: 2 | L5: Kavya Iyer | M5: FALSE | N5: TRUE | O5: TRUE | P5: TRUE | Q5: TRUE | R5: =COUNTIF(M5:Q5,"True") -> 4 | S5: =COUNTIF(M5:Q5,"False") -> 1
A6: GoldenLeaf Ventures | B6: 37488 | D6: GoldenLeaf Ventures | E6: =SUMIF($A$2:$A$339,$D6,$B$2:$B$339) -> 1361323 | F6: =AVERAGEIF($A$2:$A$339,D6,$B$2:$B$339) -> 32412.452 | G6: =COUNTIF($A$2:$A$339,D6) -> 42 | K6: 3 | L6: Rohan Mehta | M6: FALSE | N6: TRUE | O6: TRUE | P6: TRUE | Q6: TRUE | R6: =COUNTIF(M6:Q6,"True") -> 4 | S6: =COUNTIF(M6:Q6,"False") -> 1
A7: UrbanNest Interiors | B7: 21012 | D7: UrbanNest Interiors | E7: =SUMIF($A$2:$A$339,$D7,$B$2:$B$339) -> 590284 | F7: =AVERAGEIF($A$2:$A$339,D7,$B$2:$B$339) -> 31067.579 | G7: =COUNTIF($A$2:$A$339,D7) -> 19 | K7: 4 | L7: Sneha Reddy | M7: TRUE | N7: TRUE | O7: TRUE | P7: TRUE | Q7: TRUE | R7: =COUNTIF(M7:Q7,"True") -> 5 | S7: =COUNTIF(M7:Q7,"False") -> 0
A8: Vertex Synergy | B8: 34133 | D8: Vertex Synergy | E8: =SUMIF($A$2:$A$339,$D8,$B$2:$B$339) -> 1012579 | F8: =AVERAGEIF($A$2:$A$339,D8,$B$2:$B$339) -> 29781.735 | G8: =COUNTIF($A$2:$A$339,D8) -> 34 | K8: 5 | L8: Aditya Verma | M8: TRUE | N8: TRUE | O8: TRUE | P8: TRUE | Q8: TRUE | R8: =COUNTIF(M8:Q8,"True") -> 5 | S8: =COUNTIF(M8:Q8,"False") -> 0
A9: EverGlow Essentials | B9: 25015 | D9: EverGlow Essentials | E9: =SUMIF($A$2:$A$339,$D9,$B$2:$B$339) -> 1176087 | F9: =AVERAGEIF($A$2:$A$339,D9,$B$2:$B$339) -> 29402.175 | G9: =COUNTIF($A$2:$A$339,D9) -> 40 | K9: 6 | L9: Priya Nair | M9: FALSE | N9: TRUE | O9: TRUE | P9: TRUE | Q9: TRUE | R9: =COUNTIF(M9:Q9,"True") -> 4 | S9: =COUNTIF(M9:Q9,"False") -> 1
A10: TruHarvest Organics | B10: 24185 | D10: TruHarvest Organics | E10: =SUMIF($A$2:$A$339,$D10,$B$2:$B$339) -> 1408626 | F10: =AVERAGEIF($A$2:$A$339,D10,$B$2:$B$339) -> 30622.304 | G10: =COUNTIF($A$2:$A$339,D10) -> 46 | K10: 7 | L10: Arjun Singh | M10: TRUE | N10: TRUE | O10: TRUE | P10: TRUE | Q10: TRUE | R10: =COUNTIF(M10:Q10,"True") -> 5 | S10: =COUNTIF(M10:Q10,"False") -> 0
A11: StellarEdge Consulting | B11: 27419 | D11: StellarEdge Consulting | E11: =SUMIF($A$2:$A$339,$D11,$B$2:$B$339) -> 1162990 | F11: =AVERAGEIF($A$2:$A$339,D11,$B$2:$B$339) -> 33228.286 | G11: =COUNTIF($A$2:$A$339,D11) -> 35
A12: SwiftNova Enterprises | B12: 20989 | D12: Total Sale | E12: =SUM(E2:E11) -> 10175331
A13: BluePeak Solutions | B13: 37327
A14: EliteCrest Innovations | B14: 14753 | K14: Attendance Tracker Normal
A15: QuantumByte Technologies | B15: 16689 | K15: S no | L15: Students Name | M15: Mon | N15: Tue | O15: Wed | P15: Thu | Q15: Fri | R15: Present | S15: Absent
A16: GoldenLeaf Ventures | B16: 38507 | K16: 1 | L16: Aarav Sharma | M16: P | N16: P | O16: P | P16: P | Q16: O | R16: =COUNTIF(M16:Q16,"P") -> 4 | S16: =COUNTIF(M16:Q16,"O") -> 1
A17: EliteCrest Innovations | B17: 14720 | K17: 2 | L17: Kavya Iyer | M17: O | N17: P | O17: O | P17: O | Q17: P | R17: =COUNTIF(M17:Q17,"P") -> 2 | S17: =COUNTIF(M17:Q17,"O") -> 3
A18: QuantumByte Technologies | B18: 38768 | K18: 3 | L18: Rohan Mehta | M18: P | N18: P | O18: O | P18: P | Q18: O | R18: =COUNTIF(M18:Q18,"P") -> 3 | S18: =COUNTIF(M18:Q18,"O") -> 2
A19: GoldenLeaf Ventures | B19: 45280 | K19: 4 | L19: Sneha Reddy | M19: O | N19: O | O19: P | P19: O | Q19: P | R19: =COUNTIF(M19:Q19,"P") -> 2 | S19: =COUNTIF(M19:Q19,"O") -> 3
A20: UrbanNest Interiors | B20: 49176 | K20: 5 | L20: Aditya Verma | M20: P | N20: O | O20: P | P20: O | Q20: P | R20: =COUNTIF(M20:Q20,"P") -> 3 | S20: =COUNTIF(M20:Q20,"O") -> 2
A21: Vertex Synergy | B21: 39695 | K21: 6 | L21: Priya Nair | M21: O | N21: P | O21: P | P21: O | Q21: P | R21: =COUNTIF(M21:Q21,"P") -> 3 | S21: =COUNTIF(M21:Q21,"O") -> 2
A22: EverGlow Essentials | B22: 19380 | K22: 7 | L22: Arjun Singh | M22: P | N22: O | O22: P | P22: P | Q22: O | R22: =COUNTIF(M22:Q22,"P") -> 3 | S22: =COUNTIF(M22:Q22,"O") -> 2
A23: TruHarvest Organics | B23: 32705
A24: StellarEdge Consulting | B24: 37700
A25: Vertex Synergy | B25: 25793
A26: EverGlow Essentials | B26: 10459
A27: TruHarvest Organics | B27: 31197
A28: StellarEdge Consulting | B28: 28369
A29: SwiftNova Enterprises | B29: 25100
A30: BluePeak Solutions | B30: 10238
A31: EliteCrest Innovations | B31: 33922
A32: QuantumByte Technologies | B32: 22743
A33: GoldenLeaf Ventures | B33: 36685
A34: TruHarvest Organics | B34: 37198
... A339: EverGlow Essentials | B339: 17811
B340: =SUBTOTAL(9,B2:B339) -> 10175331

Sheet Master data
A1: S no | B1: Date | C1: Month | D1: Name | E1: Product Name | F1: Category | G1: Region | H1: City | I1: State | J1: Gender | K1: Quantity | L1: Rate | M1: Amount
A2: 1 | B2: 46061 | C2: =TEXT(B2,"mmm") -> Feb | D2: Bharat Innovations | E2: Speaker | F2: Electronic | G2: North | H2: Delhi | I2: Delhi | J2: Male | K2: 4292 | L2: 783 | M2: 3360636
A3: 2 | B3: 45800 | C3: =TEXT(B3,"mmm") -> May | D3: Green Leaf Enterprises | E3: Earbuds | F3: Electronic | G3: West | H3: Mumbai | I3: Maharashtra | J3: Male | K3: 8037 | L3: 578 | M3: 4645386
A4: =A3 -> 2 | B4: =B3 -> 45800 | C4: =TEXT(B4,"mmm") -> May | D4: =D3 -> Green Leaf Enterprises | E4: =E3 -> Earbuds | F4: =F3 -> Electronic | G4: =G3 -> West | H4: =H3 -> Mumbai | I4: =I3 -> Maharashtra | J4: =J3 -> Male | K4: =K3 -> 8037 | ... M4: =M3 -> 4645386
A5: 4 | B5: 46051 | C5: =TEXT(B5,"mmm") -> Jan | D5: Mystic India Exports | E5: Earbuds | F5: Electronic | G5: South | H5: Chennai | I5: Tamil Nadu | J5: Male | K5: 3941 | L5: 905 | M5: 3566605
A6: =A5 -> 4 | B6: =B5 -> 46051 | C6: =TEXT(B6,"mmm") -> Jan | D6: Green Leaf Enterprises | E6: =E5 -> Earbuds | F6: =F5 -> Electronic | G6: =G5 -> South | H6: =H5 -> Chennai | I6: =I5 -> Tamil Nadu | J6: =J5 -> Male | K6: =K5 -> 3941 | L6: =L5 -> 905 | M6: =M5 -> 3566605
A7: 6 | B7: 45802 | C7: =TEXT(B7,"mmm") -> May | D7: Green Leaf Enterprises | E7: Women dress | F7: Fashion | G7: South | H7: Hyderabad | I7: Telangana | J7: Male | K7: 4261 | L7: 954 | M7: 4064994
A8: =A7 -> 6 | B8: =B7 -> 45802 | C8: =TEXT(B8,"mmm") -> May | D8: Green Leaf Enterprises | E8: =E7 -> Women dress | F8: =F7 -> Fashion | G8: =G7 -> South | H8: =H7 -> Hyderabad | I8: =I7 -> Telangana | J8: =J7 -> Male | K8: =K7 -> 4261 | L8: =L7 -> 954 | M8: =M7 -> 4064994
A9: 8 | B9: 45907 | C9: =TEXT(B9,"mmm") -> Sep | D9: Zenith Construction Co. | E9: Speaker | F9: Electronic | G9: West | H9: Surat | I9: Gujarat | J9: Female | K9: 1631 | L9: 508 | M9: 828548
A10: =A9 -> 8 | B10: =B9 -> 45907 | C10: =TEXT(B10,"mmm") -> Sep | D10: =D9 -> Zenith Construction Co. | E10: =E9 -> Speaker | F10: =F9 -> Electronic | G10: =G9 -> West | H10: =H9 -> Surat | I10: =I9 -> Gujarat | J10: =J9 -> Female | K10: =K9 -> 1631 | ... M10: =M9 -> 828548
A11: 10 | B11: 46060 | C11: =TEXT(B11,"mmm") -> Feb | D11: Divine Creations | E11: Speaker | F11: Electronic | G11: North | H11: Kanpur | I11: Uttar Pradesh | J11: Female | K11: 4283 | L11: 804 | M11: 3443532
A12: 11 | B12: 45831 | C12: =TEXT(B12,"mmm") -> Jun | D12: Metro Tech Solutions | E12: Speaker | F12: Electronic | G12: West | H12: Nagpur | I12: Maharashtra | J12: Female | K12: 4249 | L12: 842 | M12: 3577658
A13: 12 | B13: 45941 | C13: =TEXT(B13,"mmm") -> Oct | D13: True Path Logistics | E13: Speaker | F13: Electronic | G13: Central | H13: Indore | I13: Madhya Pradesh | J13: Female | K13: 1902 | L13: 671 | M13: 1276242
A14: 13 | B14: 45976 | C14: =TEXT(B14,"mmm") -> Nov | D14: Green Leaf Enterprises | E14: Male dress | F14: Fashion | G14: West | H14: Thane | I14: Maharashtra | J14: Female | K14: 6166 | L14: 894 | M14: 5512404
A15: 14 | B15: 46049 | C15: =TEXT(B15,"mmm") -> Jan | D15: Green Leaf Enterprises | E15: Male dress | F15: Fashion | G15: North (Union Territory) | H15: Chandigarh | I15: Chandigarh | J15: Female | K15: 3669 | L15: 541 | M15: 1984929
A16: 15 | B16: 46078 | C16: =TEXT(B16,"mmm") -> Feb | D16: Green Leaf Enterprises | E16: Male dress | F16: Fashion | G16: Central | H16: Bhopal | I16: Madhya Pradesh | J16: Female | K16: 4667 | L16: 646 | M16: 3014882
A17: 16 | B17: 46033 | C17: =TEXT(B17,"mmm") -> Jan | D17: Visionary Holdings | E17: Male dress | F17: Fashion | G17: South | H17: Visakhapatnam | I17: Andhra Pradesh | J17: Female | K17: 6722 | L17: 671 | M17: 4510462
A18: 17 | B18: 45865 | C18: =TEXT(B18,"mmm") -> Jul | D18: Stellar Design Studio | E18: Male dress | F18: Fashion | G18: East | H18: Patna | I18: Bihar | J18: Female | K18: 8821 | L18: 611 | M18: 5389631
A19: =A18 -> 17 | B19: =B18 -> 45865 | C19: =TEXT(B19,"mmm") -> Jul | D19: =D18 -> Stellar Design Studio | E19: =E18 -> Male dress | F19: =F18 -> Fashion | G19: =G18 -> East | H19: =H18 -> Patna | I19: =I18 -> Bihar | J19: =J18 -> Female | K19: =K18 -> 8821 | ... M19: =M18 -> 5389631
A20: 19 | B20: 46031 | C20: =TEXT(B20,"mmm") -> Jan | D20: Green Leaf Enterprises | E20: Male dress | F20: Fashion | G20: North | H20: Agra | I20: Uttar Pradesh | J20: Male | K20: 9513 | L20: 632 | M20: 6012216
A21: =A20 -> 19 | B21: =B20 -> 46031 | C21: =TEXT(B21,"mmm") -> Jan | D21: Green Leaf Enterprises | E21: =E20 -> Male dress | F21: =F20 -> Fashion | G21: =G20 -> North | H21: =H20 -> Agra | I21: =I20 -> Uttar Pradesh | J21: =J20 -> Male | K21: =K20 -> 9513 | L21: =L20 -> 632 | M21: =M20 -> 6012216
A22: 21 | B22: 45821 | C22: =TEXT(B22,"mmm") -> Jun | D22: Green Leaf Enterprises | E22: TV | F22: Electronic | G22: South | H22: Coimbatore | I22: Tamil Nadu | J22: Male | K22: 4332 | L22: 858 | M22: 3716856
A23: =A22 -> 21 | B23: =B22 -> 45821 | C23: =TEXT(B23,"mmm") -> Jun | D23: =D22 -> Green Leaf Enterprises | E23: =E22 -> TV | F23: =F22 -> Electronic | G23: =G22 -> South | H23: =H22 -> Coimbatore | I23: =I22 -> Tamil Nadu | J23: =J22 -> Male | K23: =K22 -> 4332 | ... M23: =M22 -> 3716856
A24: 23 | B24: 45982 | C24: =TEXT(B24,"mmm") -> Nov | D24: Crystal Clear Solutions | E24: TV | F24: Electronic | G24: North | H24: Jodhpur | I24: Rajasthan | J24: Female | K24: 3691 | L24: 940 | M24: 3469540
A25: =A24 -> 23 | B25: 46078 | C25: =TEXT(B25,"mmm") -> Feb | D25: Modern Trends Fashion | E25: TV | F25: Electronic | G25: North | H25: Varanasi | I25: Uttar Pradesh | J25: Female | K25: 2570 | L25: 704 | M25: 1809280
A26: 25 | B26: 46077 | C26: =TEXT(B26,"mmm") -> Feb | D26: Green Leaf Enterprises | E26: TV | F26: Electronic | G26: South | H26: Kochi | I26: Kerala | J26: Female | K26: 1992 | L26: 538 | M26: 1071696
A27: 26 | B27: 46077 | C27: =TEXT(B27,"mmm") -> Feb | D27: Green Leaf Enterprises | E27: TV | F27: Electronic | G27: West | H27: Aurangabad | I27: Maharashtra | J27: Female | K27: 2907 | L27: 750 | M27: 2180250
A28: 27 | B28: 46031 | C28: =TEXT(B28,"mmm") -> Jan | D28: Future Insights Analytics | E28: TV | F28: Electronic | G28: North | H28: Shimla | I28: Himachal Pradesh | J28: Female | K28: 2936 | L28: 558 | M28: 1638288
A29: =A28 -> 27 | B29: =B28 -> 46031 | C29: =TEXT(B29,"mmm") -> Jan | D29: Future Insights Analytics | E29: =E28 -> TV | F29: =F28 -> Electronic | G29: =G28 -> North | H29: =H28 -> Shimla | I29: =I28 -> Himachal Pradesh | J29: =J28 -> Female | K29: =K28 -> 2936 | L29: =L28 -> 558 | M29: =M28 -> 1638288
A30: 29 | B30: 45986 | C30: =TEXT(B30,"mmm") -> Nov | D30: Future Insights Analytics | E30: TV | F30: Electronic | G30: Central | H30: Raipur | I30: Chhattisgarh | J30: Male | K30: 7291 | L30: 837 | M30: 6102567
A31: 30 | B31: 46003 | C31: =TEXT(B31,"mmm") -> Dec | D31: Future Insights Analytics | E31: TV | F31: Electronic | G31: East | H31: Durgapur | I31: West Bengal | J31: Male | K31: 3141 | L31: 834 | M31: 2619594
A32: 31 | B32: 45898 | C32: =TEXT(B32,"mmm") -> Aug | D32: Golden Era Realty | E32: TV | F32: Electronic | G32: East | H32: Kolkata | I32: West Bengal | J32: Female | K32: 7170 | L32: 521 | M32: 3735570
A33: 32 | B33: 45959 | C33: =TEXT(B33,"mmm") -> Oct | D33: Green Leaf Enterprises | E33: Laptop | F33: Electronic | G33: East | H33: Jamshedpur | I33: Jharkhand | J33: Female | K33: 5398 | L33: 832 | M33: 4491136
A34: 33 | B34: 45977 | C34: =TEXT(B34,"mmm") -> Nov | D34: Future Insights Analytics | E34: Laptop | F34: Electronic | G34: East | H34: Siliguri | I34: West Bengal | J34: Female | K34: 9466 | L34: 933 | M34: 8831778
A35: 34 | B35: 46028 | C35: =TEXT(B35,"mmm") -> Jan | D35: Future Insights Analytics | E35: Laptop | F35: Electronic | G35: South | H35: Mangalore | I35: Karnataka | J35: Female | K35: 4168 | L35: 769 | M35: 3205192
A36: 35 | B36: 46001 | C36: =TEXT(B36,"mmm") -> Dec | D36: Urban Edge Consulting | E36: Laptop | F36: Electronic | G36: North | H36: Delhi | I36: Delhi | J36: Female | K36: 5773 | L36: 627 | M36: 3619671
A37: =A36 -> 35 | B37: =B36 -> 46001 | C37: =TEXT(B37,"mmm") -> Dec | D37: Green Leaf Enterprises | E37: =E36 -> Laptop | F37: =F36 -> Electronic | G37: =G36 -> North | H37: =H36 -> Delhi | I37: =I36 -> Delhi | J37: =J36 -> Female | K37: =K36 -> 5773 | L37: =L36 -> 627 | M37: =M36 -> 3619671
A38: 37 | B38: 45762 | C38: =TEXT(B38,"mmm") -> Apr | D38: Green Leaf Enterprises | E38: Laptop | F38: Electronic | G38: East | H38: Kolkata | I38: West Bengal | J38: Female | K38: 4691 | L38: 901 | M38: 4226591
A39: 38 | B39: 45773 | C39: =TEXT(B39,"mmm") -> Apr | D39: Green Leaf Enterprises | E39: Laptop | F39: Electronic | G39: South | H39: Chennai | I39: Tamil Nadu | J39: Female | K39: 5945 | L39: 887 | M39: 5273215
A40: 39 | B40: 46064 | C40: =TEXT(B40,"mmm") -> Feb | D40: Green Leaf Enterprises | E40: Laptop | F40: Electronic | G40: South | H40: Bengaluru | I40: Karnataka | J40: Female | K40: 6807 | L40: 607 | M40: 4131849
A41: 40 | B41: 46043 | C41: =TEXT(B41,"mmm") -> Jan | D41: Green Leaf Enterprises | E41: Laptop | F41: Electronic | G41: South | H41: Hyderabad | I41: Telangana | J41: Male | K41: 3546 | L41: 562 | M41: 1992852
A42: 41 | B42: 46016 | C42: =TEXT(B42,"mmm") -> Dec | D42: Green Leaf Enterprises | E42: Laptop | F42: Electronic | G42: West | H42: Ahmedabad | I42: Gujarat | J42: Male | K42: 9463 | L42: 615 | M42: 5819745
A43: 42 | B43: 46057 | C43: =TEXT(B43,"mmm") -> Feb | D43: Green Leaf Enterprises | E43: Laptop | F43: Electronic | G43: West | H43: Pune | I43: Maharashtra | J43: Male | K43: 9927 | L43: 631 | M43: 6263937
A44: 43 | B44: 46081 | C44: =TEXT(B44,"mmm") -> Feb | D44: Radiance Spa | E44: Saree | F44: Fashion | G44: North | H44: Jaipur | I44: Rajasthan | J44: Male | K44: 1666 | L44: 714 | M44: 1189524
A45: =A44 -> 43 | B45: =B44 -> 46081 | C45: =TEXT(B45,"mmm") -> Feb | D45: =D44 -> Radiance Spa | E45: =E44 -> Saree | F45: =F44 -> Fashion | G45: =G44 -> North | H45: =H44 -> Jaipur | I45: =I44 -> Rajasthan | J45: =J44 -> Male | K45: =K44 -> 1666 | ... M45: =M44 -> 1189524
A46: 45 | B46: 45852 | C46: =TEXT(B46,"mmm") -> Jul | D46: Verve Fitness Studio | E46: Saree | F46: Fashion | G46: North | H46: Lucknow | I46: Uttar Pradesh | J46: Female | K46: 7124 | L46: 693 | M46: 4936932
A47: 46 | B47: 46064 | C47: =TEXT(B47,"mmm") -> Feb | D47: Future Insights Analytics | E47: Saree | F47: Fashion | G47: North | H47: Kanpur | I47: Uttar Pradesh | J47: Female | K47: 9636 | L47: 873 | M47: 8412228
A48: 47 | B48: 45839 | C48: =TEXT(B48,"mmm") -> Jul | D48: Future Insights Analytics | E48: Saree | F48: Fashion | G48: Central | H48: Indore | I48: Madhya Pradesh | J48: Female | K48: 6338 | L48: 540 | M48: 3422520
A49: 48 | B49: 45800 | C49: =TEXT(B49,"mmm") -> May | D49: Dynamic Events Management | E49: Saree | F49: Fashion | G49: West | H49: Thane | I49: Maharashtra | J49: Female | K49: 8446 | L49: 812 | M49: 6858152
A50: =A49 -> 48 | B50: =B49 -> 45800 | C50: =TEXT(B50,"mmm") -> May | D50: =D49 -> Dynamic Events Management | E50: =E49 -> Saree | F50: =F49 -> Fashion | G50: =G49 -> West | H50: =H49 -> Thane | I50: =I49 -> Maharashtra | J50: =J49 -> Female | K50: =K49 -> 8446 | ... M50: =M49 -> 6858152
A51: 50 | B51: 45963 | C51: =TEXT(B51,"mmm") -> Nov | D51: Future Insights Analytics | E51: Saree | F51: Fashion | G51: Central | H51: Bhopal | I51: Madhya Pradesh | J51: Female | K51: 3887 | L51: 912 | M51: 3544944
A52: 51 | B52: 45828 | C52: =TEXT(B52,"mmm") -> Jun | D52: Future Insights Analytics | E52: Saree | F52: Fashion | G52: South | H52: Visakhapatnam | I52: Andhra Pradesh | J52: Male | K52: 9519 | L52: 970 | M52: 9233430
A53: 52 | B53: 45877 | C53: =TEXT(B53,"mmm") -> Aug | D53: Future Insights Analytics | E53: Saree | F53: Fashion | G53: East | H53: Patna | I53: Bihar | J53: Male | K53: 8983 | L53: 840 | M53: 7545720
A54: 53 | B54: 46027 | C54: =TEXT(B54,"mmm") -> Jan | D54: Classic Heritage Crafts | E54: Saree | F54: Fashion | G54: West | H54: Vadodara | I54: Gujarat | J54: Male | K54: 6892 | L54: 643 | M54: 4431556
A55: 54 | B55: 46075 | C55: =TEXT(B55,"mmm") -> Feb | D55: Noble Nutraceuticals | E55: Suit | F55: Fashion | G55: North | H55: Meerut | I55: Uttar Pradesh | J55: Female | K55: 8990 | L55: 666 | M55: 5987340
A56: 55 | B56: 45838 | C56: =TEXT(B56,"mmm") -> Jun | D56: Supreme Travel Agency | E56: Suit | F56: Fashion | G56: South | H56: Coimbatore | I56: Tamil Nadu | J56: Male | K56: 5594 | L56: 615 | M56: 3440310
A57: 56 | B57: 45877 | C57: =TEXT(B57,"mmm") -> Aug | D57: Future Vision Tech | E57: Suit | F57: Fashion | G57: South | H57: Madurai | I57: Tamil Nadu | J57: Male | K57: 5491 | L57: 601 | M57: 3300091
A58: =A57 -> 56 | B58: =B57 -> 45877 | C58: =TEXT(B58,"mmm") -> Aug | D58: =D57 -> Future Vision Tech | E58: =E57 -> Suit | F58: =F57 -> Fashion | G58: =G57 -> South | H58: =H57 -> Madurai | I58: =I57 -> Tamil Nadu | J58: =J57 -> Male | K58: =K57 -> 5491 | ... M58: =M57 -> 3300091
A59: 58 | B59: 45987 | C59: =TEXT(B59,"mmm") -> Nov | D59: Pinnacle Health Products | E59: Suit | F59: Fashion | G59: East | H59: Ranchi | I59: Jharkhand | J59: Female | K59: 2421 | L59: 765 | M59: 1852065
A60: 59 | B60: 45905 | C60: =TEXT(B60,"mmm") -> Sep | D60: Apex Auto Care | E60: Suit | F60: Fashion | G60: South | H60: Kochi | I60: Kerala | J60: Female | K60: 8893 | L60: 848 | M60: 7541264
A61: 60 | B61: 45900 | C61: =TEXT(B61,"mmm") -> Aug | D61: Royal Glow Cosmetics | E61: Suit | F61: Fashion | G61: West | H61: Aurangabad | I61: Maharashtra | J61: Female | K61: 4938 | L61: 726 | M61: 3584988
A62: 61 | B62: 45960 | C62: =TEXT(B62,"mmm") -> Oct | D62: Zenith Culinary Arts | E62: Suit | F62: Fashion | G62: North | H62: Shimla | I62: Himachal Pradesh | J62: Female | K62: 4836 | L62: 783 | M62: 3786588
A63: 62 | B63: 45777 | C63: =TEXT(B63,"mmm") -> Apr | D63: Visionary Tours | E63: Suit | F63: Fashion | G63: North | H63: Dehradun | I63: Uttarakhand | J63: Female | K63: 3490 | L63: 889 | M63: 3102610
A64: 63 | B64: 45855 | C64: =TEXT(B64,"mmm") -> Jul | D64: Horizon Wellness | E64: Car accessories | F64: Decor | G64: Northeast | H64: Guwahati | I64: Assam | J64: Female | K64: 1921 | L64: 568 | M64: 1091128
A65: 64 | B65: 45996 | C65: =TEXT(B65,"mmm") -> Dec | D65: True Value Electronics | E65: Car accessories | F65: Decor | G65: North | H65: Amritsar | I65: Punjab | J65: Female | K65: 5036 | L65: 745 | M65: 3751820
A66: =A65 -> 64 | B66: =B65 -> 45996 | C66: =TEXT(B66,"mmm") -> Dec | D66: =D65 -> True Value Electronics | E66: =E65 -> Car accessories | F66: =F65 -> Decor | G66: =G65 -> North | H66: =H65 -> Amritsar | I66: =I65 -> Punjab | J66: =J65 -> Female | K66: =K65 -> 5036 | ... M66: =M65 -> 3751820
A67: 66 | B67: 46040 | C67: =TEXT(B67,"mmm") -> Jan | D67: Stellar Advertising | E67: Car accessories | F67: Decor | G67: East | H67: Durgapur | I67: West Bengal | J67: Female | K67: 6233 | L67: 675 | M67: 4207275
A68: 67 | B68: 45801 | C68: =TEXT(B68,"mmm") -> May | D68: Radiant Enterprise Solutions | E68: Car accessories | F68: Decor | G68: East | H68: Kolkata | I68: West Bengal | J68: Female | K68: 9156 | L68: 778 | M68: 7123368
A69: 68 | B69: 45816 | C69: =TEXT(B69,"mmm") -> Jun | D69: Modern Trends Retail | E69: Car accessories | F69: Decor | G69: Central | H69: Gwalior | I69: Madhya Pradesh | J69: Male | K69: 3687 | L69: 867 | M69: 3196629
A70: 69 | B70: 45880 | C70: =TEXT(B70,"mmm") -> Aug | D70: Global Spectrum Consulting | E70: Car accessories | F70: Decor | G70: East | H70: Jamshedpur | I70: Jharkhand | J70: Male | K70: 3165 | L70: 903 | M70: 2857995
A71: 70 | B71: 45993 | C71: =TEXT(B71,"mmm") -> Dec | D71: Elite Essence Products | E71: Saree | F71: Fashion | G71: East | H71: Siliguri | I71: West Bengal | J71: Male | K71: 1580 | L71: 718 | M71: 1134440
A72: 71 | B72: 45862 | C72: =TEXT(B72,"mmm") -> Jul | D72: Infinite Solutions | E72: Saree | F72: Fashion | G72: West | H72: Mumbai | I72: Maharashtra | J72: Female | K72: 7609 | L72: 636 | M72: 4839324
A73: 72 | B73: 46060 | C73: =TEXT(B73,"mmm") -> Feb | D73: Apex Construction | E73: Saree | F73: Fashion | G73: East | H73: Kolkata | I73: West Bengal | J73: Female | K73: 2460 | L73: 571 | M73: 1404660
A74: 73 | B74: 46039 | C74: =TEXT(B74,"mmm") -> Jan | D74: Legacy Innovations | E74: Suit | F74: Fashion | G74: South | H74: Chennai | I74: Tamil Nadu | J74: Female | K74: 8048 | L74: 648 | M74: 5215104
A75: 74 | B75: 45944 | C75: =TEXT(B75,"mmm") -> Oct | D75: Pure Harmony Foods | E75: Suit | F75: Fashion | G75: South | H75: Bengaluru | I75: Karnataka | J75: Male | K75: 6821 | L75: 871 | M75: 5941091
A76: 75 | B76: 46042 | C76: =TEXT(B76,"mmm") -> Jan | D76: Zenith Security Systems | E76: Suit | F76: Fashion | G76: South | H76: Hyderabad | I76: Telangana | J76: Male | K76: 1898 | L76: 726 | M76: 1377948
A77: 76 | B77: 45944 | C77: =TEXT(B77,"mmm") -> Oct | D77: Crystal Clear Beverages | E77: Suit | F77: Fashion | G77: West | H77: Ahmedabad | I77: Gujarat | J77: Male | K77: 8320 | L77: 701 | M77: 5832320
A78: 77 | B78: 45962 | C78: =TEXT(B78,"mmm") -> Nov | D78: Metro Line Tech | E78: Suit | F78: Fashion | G78: West | H78: Pune | I78: Maharashtra | J78: Male | K78: 7085 | L78: 980 | M78: 6943300
A79: 78 | B79: 45871 | C79: =TEXT(B79,"mmm") -> Aug | D79: Urban Pulse Consulting | E79: Suit | F79: Fashion | G79: North | H79: Jaipur | I79: Rajasthan | J79: Male | K79: 7382 | L79: 866 | M79: 6392812
A80: =A79 -> 78 | B80: =B79 -> 45871 | C80: =TEXT(B80,"mmm") -> Aug | D80: =D79 -> Urban Pulse Consulting | E80: =E79 -> Suit | F80: =F79 -> Fashion | G80: =G79 -> North | H80: =H79 -> Jaipur | I80: =I79 -> Rajasthan | J80: =J79 -> Male | K80: =K79 -> 7382 | ... M80: =M79 -> 6392812
A81: 80 | B81: 46017 | C81: =TEXT(B81,"mmm") -> Dec | D81: Noble Travel Services | E81: Home décor | F81: Decor | G81: North | H81: Lucknow | I81: Uttar Pradesh | J81: Female | K81: 2540 | L81: 735 | M81: 1866900
A82: 81 | B82: 45784 | C82: =TEXT(B82,"mmm") -> May | D82: Bright Future Academy | E82: Home décor | F82: Decor | G82: North | H82: Kanpur | I82: Uttar Pradesh | J82: Female | K82: 6995 | L82: 959 | M82: 6708205
A83: =A82 -> 81 | B83: =B82 -> 45784 | C83: =TEXT(B83,"mmm") -> May | D83: =D82 -> Bright Future Academy | E83: =E82 -> Home décor | F83: =F82 -> Decor | G83: =G82 -> North | H83: =H82 -> Kanpur | I83: =I82 -> Uttar Pradesh | J83: =J82 -> Female | K83: =K82 -> 6995 | ... M83: =M82 -> 6708205
A84: 83 | B84: 45966 | C84: =TEXT(B84,"mmm") -> Nov | D84: Apex Retailers | E84: Home décor | F84: Decor | G84: West | H84: Thane | I84: Maharashtra | J84: Female | K84: 2645 | L84: 513 | M84: 1356885
A85: 84 | B85: 45795 | C85: =TEXT(B85,"mmm") -> May | D85: Prestige Property Developers | E85: Home décor | F85: Decor | G85: North (Union Territory) | H85: Chandigarh | I85: Chandigarh | J85: Female | K85: 4794 | L85: 703 | M85: 3370182
A86: 85 | B86: 45770 | C86: =TEXT(B86,"mmm") -> Apr | D86: Harmony Ventures | E86: Home décor | F86: Decor | G86: South | H86: Visakhapatnam | I86: Andhra Pradesh | J86: Male | K86: 9519 | L86: 949 | M86: 9033531
A87: =A86 -> 85 | B87: =B86 -> 45770 | C87: =TEXT(B87,"mmm") -> Apr | D87: =D86 -> Harmony Ventures | E87: =E86 -> Home décor | F87: =F86 -> Decor | G87: =G86 -> South | H87: =H86 -> Visakhapatnam | I87: =I86 -> Andhra Pradesh | J87: =J86 -> Male | K87: =K86 -> 9519 | ... M87: =M86 -> 9033531
A88: 87 | B88: 45918 | C88: =TEXT(B88,"mmm") -> Sep | D88: Future Path Technologies | E88: Home décor | F88: Decor | G88: West | H88: Vadodara | I88: Gujarat | J88: Male | K88: 1885 | L88: 811 | M88: 1528735
A89: 88 | B89: 45774 | C89: =TEXT(B89,"mmm") -> Apr | D89: Radiance Health and Wellness | E89: Laptop | F89: Electronic | G89: North | H89: Meerut | I89: Uttar Pradesh | J89: Male | K89: 6596 | L89: 501 | M89: 3304596
A90: 89 | B90: 46059 | C90: =TEXT(B90,"mmm") -> Feb | D90: Legacy Auto Works | E90: Laptop | F90: Electronic | G90: South | H90: Coimbatore | I90: Tamil Nadu | J90: Male | K90: 3074 | L90: 869 | M90: 2671306
A91: 90 | B91: 45761 | C91: =TEXT(B91,"mmm") -> Apr | D91: Prime Essence Creations | E91: Laptop | F91: Electronic | G91: South | H91: Madurai | I91: Tamil Nadu | J91: Male | K91: 6116 | L91: 699 | M91: 4275084
A92: 91 | B92: 45814 | C92: =TEXT(B92,"mmm") -> Jun | D92: Quantum Ventures | E92: Laptop | F92: Electronic | G92: North | H92: Jodhpur | I92: Rajasthan | J92: Male | K92: 5729 | L92: 753 | M92: 4313937
A93: 92 | B93: 46018 | C93: =TEXT(B93,"mmm") -> Dec | D93: Horizon Tech Solutions | E93: Laptop | F93: Electronic | G93: North | H93: Varanasi | I93: Uttar Pradesh | J93: Female | K93: 7181 | L93: 668 | M93: 4796908
A94: 93 | B94: 46010 | C94: =TEXT(B94,"mmm") -> Dec | D94: Urban Legends Apparel | E94: Laptop | F94: Electronic | G94: East | H94: Ranchi | I94: Jharkhand | J94: Female | K94: 9034 | L94: 730 | M94: 6594820
A95: 94 | B95: 46035 | C95: =TEXT(B95,"mmm") -> Jan | D95: Pure Bliss Beverages | E95: Laptop | F95: Electronic | G95: South | H95: Kochi | I95: Kerala | J95: Female | K95: 6005 | L95: 739 | M95: 4437695
A96: 95 | B96: 45963 | C96: =TEXT(B96,"mmm") -> Nov | D96: Pure Bliss Beverages | E96: Laptop | F96: Electronic | G96: West | H96: Aurangabad | I96: Maharashtra | J96: Female | K96: 5261 | L96: 626 | M96: 3293386
A97: 96 | B97: 45774 | C97: =TEXT(B97,"mmm") -> Apr | D97: Pure Bliss Beverages | E97: Laptop | F97: Electronic | G97: North | H97: Shimla | I97: Himachal Pradesh | J97: Female | K97: 5989 | L97: 889 | M97: 5324221
A98: 97 | B98: 45972 | C98: =TEXT(B98,"mmm") -> Nov | D98: Pure Bliss Beverages | E98: Laptop | F98: Electronic | G98: North | H98: Dehradun | I98: Uttarakhand | J98: Female | K98: 6350 | L98: 615 | M98: 3905250
A99: 98 | B99: 46047 | C99: =TEXT(B99,"mmm") -> Jan | D99: Apex Travel Ventures | E99: Laptop | F99: Electronic | G99: Northeast | H99: Guwahati | I99: Assam | J99: Female | K99: 9014 | L99: 687 | M99: 6192618
... A295: 294 | B295: 45818 | C295: =TEXT(B295,"mmm") -> Jun | D295: Legacy Health Co. | E295: Suit | F295: Fashion | G295: North | H295: Amritsar | I295: Punjab | J295: Male | K295: 5246 | L295: 653 | M295: 3425638
...

Sheet Sumifs
A1: Party Name | B1: Apr | C1: May | D1: Jun | E1: Jul | F1: Aug | G1: Sep | H1: Oct | I1: Nov | J1: Dec | K1: Jan | L1: Feb | M1: Mar | N1: Total
A2: Bharat Innovations | B2: {=SUMIFS('Master data'!$M$2:$M$295,'Master data'!$D$2:$D$295,A2:A148,'Master data'!$C$2:$C$295,B1:M1)} -> 0 | C2: 0 | D2: 0 | E2: 0 | F2: 0 | G2: 0 | H2: 0 | I2: 0 | J2: 0 | K2: 0 | L2: 3360636 | M2: 0 | N2: =SUM(B2:M2) -> 3360636
A3: Green Leaf Enterprises | B3: 9499806 | C3: 17420760 | D3: 7433712 | E3: 0 | F3: 0 | G3: 0 | H3: 4491136 | I3: 5512404 | J3: 9439416 | K3: 19568818 | L3: 16662614 | M3: 0 | N3: =SUM(B3:M3) -> 90028666
A4: Mystic India Exports | B4: 0 | C4: 0 | D4: 0 | E4: 0 | F4: 0 | G4: 0 | H4: 0 | I4: 0 | J4: 0 | K4: 3566605 | L4: 0 | M4: 0 | N4: =SUM(B4:M4) -> 3566605
A5: Zenith Construction Co. | B5: 0 | C5: 0 | D5: 0 | E5: 0 | F5: 0 | G5: 1657096 | H5: 0 | I5: 0 | J5: 0 | K5: 0 | L5: 0 | M5: 0 | N5: =SUM(B5:M5) -> 1657096
A6: Divine Creations | B6: 0 | C6: 0 | D6: 0 | E6: 0 | F6: 0 | G6: 0 | H6: 0 | I6: 0 | J6: 0 | K6: 0 | L6: 3443532 | M6: 0 | N6: =SUM(B6:M6) -> 3443532
A7: Metro Tech Solutions | B7: 0 | C7: 0 | D7: 3577658 | E7: 0 | F7: 0 | G7: 0 | H7: 0 | I7: 0 | J7: 0 | K7: 0 | L7: 0 | M7: 0 | N7: =SUM(B7:M7) -> 3577658
A8: True Path Logistics | B8: 0 | C8: 0 | D8: 0 | E8: 0 | F8: 0 | G8: 0 | H8: 1276242 | I8: 0 | J8: 0 | K8: 0 | L8: 0 | M8: 0 | N8: =SUM(B8:M8) -> 1276242
A9: Visionary Holdings | B9: 0 | C9: 0 | D9: 0 | E9: 0 | F9: 0 | G9: 0 | H9: 0 | I9: 0 | J9: 0 | K9: 4510462 | L9: 0 | M9: 0 | N9: =SUM(B9:M9) -> 4510462
A10: Stellar Design Studio | B10: 0 | C10: 0 | D10: 0 | E10: 10779262 | F10: 0 | G10: 0 | H10: 0 | I10: 0 | J10: 0 | K10: 0 | L10: 0 | M10: 0 | N10: =SUM(B10:M10) -> 10779262
A11: Crystal Clear Solutions | B11: 0 | C11: 0 | D11: 0 | E11: 0 | F11: 0 | G11: 0 | H11: 0 | I11: 3469540 | J11: 0 | K11: 0 | L11: 0 | M11: 0 | N11: =SUM(B11:M11) -> 3469540
A12: Modern Trends Fashion | B12: 0 | C12: 0 | D12: 0 | E12: 0 | F12: 0 | G12: 0 | H12: 0 | I12: 0 | J12: 0 | K12: 0 | L12: 1809280 | M12: 0 | N12: =SUM(B12:M12) -> 1809280
A13: Future Insights Analytics | B13: 24171699 | C13: 0 | D13: 17642676 | E13: 18771986 | F13: 18251892 | G13: 10762649 | H13: 4605916 | I13: 25097581 | J13: 10357596 | K13: 15032265 | L13: 11536096 | M13: 0 | N13: =SUM(B13:M13) -> 156230356
A14: Golden Era Realty | B14: 0 | C14: 0 | D14: 0 | E14: 0 | F14: 3735570 | G14: 0 | H14: 0 | I14: 0 | J14: 0 | K14: 0 | L14: 0 | M14: 0 | N14: =SUM(B14:M14) -> 3735570
... A148: Legacy Health Co. | B148: 0 | C148: 0 | D148: 3425638 | E148: 0 | F148: 0 | G148: 0 | H148: 0 | I148: 0 | J148: 0 | K148: 0 | L148: 0 | M148: 0 | N148: =SUM(B148:M148) -> 3425638
A156: Party Name | B156: Apr | C156: May | D156: Jun | E156: Jul | F156: Aug | G156: Sep | H156: Oct | I156: Nov | J156: Dec | K156: Jan | L156: Feb | M156: Mar | N156: Total
A157: Bharat Innovations | B157: - | C157: - | D157: - | E157: - | F157: - | G157: - | H157: - | I157: - | J157: - | K157: - | L157: 3360636 | M157: - | N157: =AVERAGE(B157:M157) -> 3360636
A158: Green Leaf Enterprises | B158: 4749903 | C158: 4355190 | D158: 3716856 | E158: - | F158: - | G158: - | H158: 4491136 | I158: 5512404 | J158: 4719708 | K158: 3913763.6 | L158: 3332522.8 | M158: - | N158: =AVERAGE(B158:M158) -> 4348935.4
A159: Mystic India Exports | B159: - | C159: - | D159: - | E159: - | F159: - | G159: - | H159: - | I159: - | J159: - | K159: 3566605 | L159: - | M159: - | N159: =AVERAGE(B159:M159) -> 3566605
A160: Zenith Construction Co. | B160: - | C160: - | D160: - | E160: - | F160: - | G160: 828548 | H160: - | I160: - | J160: - | K160: - | L160: - | M160: - | N160: =AVERAGE(B160:M160) -> 828548
A161: Divine Creations | B161: - | C161: - | D161: - | E161: - | F161: - | G161: - | H161: - | I161: - | J161: - | K161: - | L161: 3443532 | M161: - | N161: =AVERAGE(B161:M161) -> 3443532
A162: Metro Tech Solutions | B162: - | C162: - | D162: 3577658 | E162: - | F162: - | G162: - | H162: - | I162: - | J162: - | K162: - | L162: - | M162: - | N162: =AVERAGE(B162:M162) -> 3577658
A163: True Path Logistics | B163: - | C163: - | D163: - | E163: - | F163: - | G163: - | H163: 1276242 | I163: - | J163: - | K163: - | L163: - | M163: - | N163: =AVERAGE(B163:M163) -> 1276242
A164: Visionary Holdings | B164: - | C164: - | D164: - | E164: - | F164: - | G164: - | H164: - | I164: - | J164: - | K164: 4510462 | L164: - | M164: - | N164: =AVERAGE(B164:M164) -> 4510462
A165: Stellar Design Studio | B165: - | C165: - | D165: - | E165: 5389631 | F165: - | G165: - | H165: - | I165: - | J165: - | K165: - | L165: - | M165: - | N165: =AVERAGE(B165:M165) -> 5389631
A166: Crystal Clear Solutions | B166: - | C166: - | D166: - | E166: - | F166: - | G166: - | H166: - | I166: 3469540 | J166: - | K166: - | L166: - | M166: - | N166: =AVERAGE(B166:M166) -> 3469540
A167: Modern Trends Fashion | B167: - | C167: - | D167: - | E167: - | F167: - | G167: - | H167: - | I167: - | J167: - | K167: - | L167: 1809280 | M167: - | N167: =AVERAGE(B167:M167) -> 1809280
A168: Future Insights Analytics | B168: 6042924.8 | C168: - | D168: 8821338 | E168: 3128664.3 | F168: 6083964 | G168: 5381324.5 | H168: 4605916 | I168: 5019516.2 | J168: 2589399 | K168: 3006453 | L168: 3845365.3 | M168: - | N168: =AVERAGE(B168:M168) -> 4852486.5
A169: Golden Era Realty | B169: - | C169: - | D169: - | E169: - | F169: 3735570 | G169: - | H169: - | I169: - | J169: - | K169: - | L169: - | M169: - | N169: =AVERAGE(B169:M169) -> 3735570
A170: Urban Edge Consulting | B170: - | C170: - | D170: - | E170: - | F170: - | G170: - | H170: - | I170: - | J170: 3619671 | K170: - | L170: - | M170: - | N170: =AVERAGE(B170:M170) -> 3619671
A171: Radiance Spa | B171: - | C171: - | D171: - | E171: - | F171: - | G171: - | H171: - | I171: - | J171: - | K171: - | L171: 1189524 | M171: - | N171: =AVERAGE(B171:M171) -> 1189524
A172: Verve Fitness Studio | B172: - | C172: - | D172: - | E172: 4936932 | F172: - | G172: - | H172: - | I172: - | J172: - | K172: - | L172: - | M172: - | N172: =AVERAGE(B172:M172) -> 4936932
A173: Dynamic Events Management | B173: - | C173: 6858152 | D173: - | E173: - | F173: - | G173: - | H173: - | I173: - | J173: - | K173: - | L173: - | M173: - | N173: =AVERAGE(B173:M173) -> 6858152
A174: Classic Heritage Crafts | B174: - | C174: - | D174: - | E174: - | F174: - | G174: - | H174: - | I174: - | J174: - | K174: 4431556 | L174: - | M174: - | N174: =AVERAGE(B174:M174) -> 4431556
A175: Noble Nutraceuticals | B175: - | C175: - | D175: - | E175: - | F175: - | G175: - | H175: - | I175: - | J175: - | K175: - | L175: 5987340 | M175: - | N175: =AVERAGE(B175:M175) -> 5987340
A176: Supreme Travel Agency | B176: - | C176: - | D176: 3440310 | E176: - | F176: - | G176: - | H176: - | I176: - | J176: - | K176: - | L176: - | M176: - | N176: =AVERAGE(B176:M176) -> 3440310
A177: Future Vision Tech | B177: - | C177: - | D177: - | E177: - | F177: 3300091 | G177: - | H177: - | I177: - | J177: - | K177: - | L177: - | M177: - | N177: =AVERAGE(B177:M177) -> 3300091
A178: Pinnacle Health Products | B178: - | C178: - | D178: - | E178: - | F178: - | G178: - | H178: - | I178: 1852065 | J178: - | K178: - | L178: - | M178: - | N178: =AVERAGE(B178:M178) -> 1852065
A179: Apex Auto Care | B179: - | C179: - | D179: - | E179: - | F179: - | G179: 7541264 | H179: - | I179: - | J179: - | K179: - | L179: - | M179: - | N179: =AVERAGE(B179:M179) -> 7541264
A180: Royal Glow Cosmetics | B180: - | C180: - | D180: - | E180: - | F180: 3584988 | G180: - | H180: - | I180: - | J180: - | K180: - | L180: - | M180: - | N180: =AVERAGE(B180:M180) -> 3584988
A181: Zenith Culinary Arts | B181: - | C181: - | D181: - | E181: - | F181: - | G181: - | H181: 3786588 | I181: - | J181: - | K181: - | L181: - | M181: - | N181: =AVERAGE(B181:M181) -> 3786588
A182: Visionary Tours | B182: 3102610 | C182: - | D182: - | E182: - | F182: - | G182: - | H182: - | I182: - | J182: - | K182: - | L182: - | M182: - | N182: =AVERAGE(B182:M182) -> 3102610
A183: Horizon Wellness | B183: - | C183: - | D183: - | E183: 1091128 | F183: - | G183: - | H183: - | I183: - | J183: - | K183: - | L183: - | M183: - | N183: =AVERAGE(B183:M183) -> 1091128
A184: True Value Electronics | B184: - | C184: - | D184: - | E184: - | F184: - | G184: - | H184: - | I184: - | J184: 3751820 | K184: - | L184: - | M184: - | N184: =AVERAGE(B184:M184) -> 3751820
A185: Stellar Advertising | B185: - | C185: - | D185: - | E185: - | F185: - | G185: - | H185: - | I185: - | J185: - | K185: 4207275 | L185: - | M185: - | N185: =AVERAGE(B185:M185) -> 4207275
A186: Radiant Enterprise Solutions | B186: - | C186: 7123368 | D186: - | E186: - | F186: - | G186: - | H186: - | I186: - | J186: - | K186: - | L186: - | M186: - | N186: =AVERAGE(B186:M186) -> 7123368
A187: Modern Trends Retail | B187: - | C187: - | D187: 3196629 | E187: - | F187: - | G187: - | H187: - | I187: - | J187: - | K187: - | L187: - | M187: - | N187: =AVERAGE(B187:M187) -> 3196629
A188: Global Spectrum Consulting | B188: - | C188: - | D188: - | E188: - | F188: 2857995 | G188: - | H188: - | I188: - | J188: - | K188: - | L188: - | M188: - | N188: =AVERAGE(B188:M188) -> 2857995
A189: Elite Essence Products | B189: - | C189: - | D189: - | E189: - | F189: - | G189: - | H189: - | I189: - | J189: 1134440 | K189: - | L189: - | M189: - | N189: =AVERAGE(B189:M189) -> 1134440
A190: Infinite Solutions | B190: - | C190: - | D190: - | E190: 4839324 | F190: - | G190: - | H190: - | I190: - | J190: - | K190: - | L190: - | M190: - | N190: =AVERAGE(B190:M190) -> 4839324
A191: Apex Construction | B191: - | C191: - | D191: - | E191: - | F191: - | G191: - | H191: - | I191: - | J191: - | K191: - | L191: 1404660 | M191: - | N191: =AVERAGE(B191:M191) -> 1404660
A192: Legacy Innovations | B192: - | C192: - | D192: - | E192: - | F192: - | G192: - | H192: - | I192: - | J192: - | K192: 5215104 | L192: - | M192: - | N192: =AVERAGE(B192:M192) -> 5215104
A193: Pure Harmony Foods | B193: - | C193: - | D193: - | E193: - | F193: - | G193: - | H193: 5941091 | I193: - | J193: - | K193: - | L193: - | M193: - | N193: =AVERAGE(B193:M193) -> 5941091
A194: Zenith Security Systems | B194: - | C194: - | D194: - | E194: - | F194: - | G194: - | H194: - | I194: - | J194: - | K194: 1377948 | L194: - | M194: - | N194: =AVERAGE(B194:M194) -> 1377948
A195: Crystal Clear Beverages | B195: - | C195: - | D195: - | E195: - | F195: - | G195: - | H195: 5832320 | I195: - | J195: - | K195: - | L195: - | M195: - | N195: =AVERAGE(B195:M195) -> 5832320
A196: Metro Line Tech | B196: - | C196: - | D196: - | E196: - | F196: - | G196: - | H196: - | I196: 6943300 | J196: - | K196: - | L196: - | M196: - | N196: =AVERAGE(B196:M196) -> 6943300
A197: Urban Pulse Consulting | B197: - | C197: - | D197: - | E197: - | F197: 6392812 | G197: - | H197: - | I197: - | J197: - | K197: - | L197: - | M197: - | N197: =AVERAGE(B197:M197) -> 6392812
A198: Noble Travel Services | B198: - | C198: - | D198: - | E198: - | F198: - | G198: - | H198: - | I198: - | J198: 1866900 | K198: - | L198: - | M198: - | N198: =AVERAGE(B198:M198) -> 1866900
A199: Bright Future Academy | B199: - | C199: 6708205 | D199: - | E199: - | F199: - | G199: - | H199: - | I199: - | J199: - | K199: - | L199: - | M199: - | N199: =AVERAGE(B199:M199) -> 6708205
A200: Apex Retailers | B200: - | C200: - | D200: - | E200: - | F200: - | G200: - | H200: - | I200: 1356885 | J200: - | K200: - | L200: - | M200: - | N200: =AVERAGE(B200:M200) -> 1356885
A201: Prestige Property Developers | B201: - | C201: 3370182 | D201: - | E201: - | F201: - | G201: - | H201: - | I201: - | J201: - | K201: - | L201: - | M201: - | N201: =AVERAGE(B201:M201) -> 3370182
A202: Harmony Ventures | B202: 9033531 | C202: - | D202: - | E202: - | F202: - | G202: - | H202: - | I202: - | J202: - | K202: - | L202: - | M202: - | N202: =AVERAGE(B202:M202) -> 9033531
A203: Future Path Technologies | B203: - | C203: - | D203: - | E203: - | F203: - | G203: 1528735 | H203: - | I203: - | J203: - | K203: - | L203: - | M203: - | N203: =AVERAGE(B203:M203) -> 1528735
A204: Radiance Health and Wellness | B204: 3304596 | C204: - | D204: - | E204: - | F204: - | G204: - | H204: - | I204: - | J204: - | K204: - | L204: - | M204: - | N204: =AVERAGE(B204:M204) -> 3304596
A205: Legacy Auto Works | B205: - | C205: - | D205: - | E205: - | F205: - | G205: - | H205: - | I205: - | J205: - | K205: - | L205: 2671306 | M205: - | N205: =AVERAGE(B205:M205) -> 2671306
A206: Prime Essence Creations | B206: 4275084 | C206: - | D206: - | E206: - | F206: - | G206: - | H206: - | I206: - | J206: - | K206: - | L206: - | M206: - | N206: =AVERAGE(B206:M206) -> 4275084
A207: Quantum Ventures | B207: - | C207: - | D207: 4313937 | E207: - | F207: - | G207: - | H207: - | I207: - | J207: - | K207: - | L207: - | M207: - | N207: =AVERAGE(B207:M207) -> 4313937
A208: Horizon Tech Solutions | B208: - | C208: - | D208: - | E208: - | F208: - | G208: - | H208: - | I208: - | J208: 4796908 | K208: - | L208: - | M208: - | N208: =AVERAGE(B208:M208) -> 4796908
A209: Urban Legends Apparel | B209: - | C209: - | D209: - | E209: - | F209: - | G209: - | H209: - | I209: - | J209: 6594820 | K209: - | L209: - | M209: - | N209: =AVERAGE(B209:M209) -> 6594820
A210: Pure Bliss Beverages | B210: 5324221 | C210: - | D210: - | E210: - | F210: - | G210: - | H210: - | I210: 3599318 | J210: - | K210: 4437695 | L210: - | M210: - | N210: =AVERAGE(B210:M210) -> 4453744.7
A211: Apex Travel Ventures | B211: - | C211: 1240575 | D211: - | E211: - | F211: - | G211: - | H211: - | I211: - | J211: - | K211: 6192618 | L211: - | M211: - | N211: =AVERAGE(B211:M211) -> 3716596.5
A212: Legacy Design Group | B212: - | C212: - | D212: - | E212: - | F212: - | G212: - | H212: 5255244 | I212: - | J212: - | K212: - | L212: - | M212: - | N212: =AVERAGE(B212:M212) -> 5255244
A213: Supreme Wellness | B213: - | C213: - | D213: - | E213: - | F213: - | G213: 6438095 | H213: - | I213: - | J213: - | K213: - | L213: - | M213: - | N213: =AVERAGE(B213:M213) -> 6438095
A214: Harmony Tech Innovations | B214: - | C214: - | D214: - | E214: - | F214: - | G214: - | H214: - | I214: - | J214: 2672000 | K214: - | L214: - | M214: - | N214: =AVERAGE(B214:M214) -> 2672000
A215: Stellar Education Services | B215: - | C215: - | D215: - | E215: - | F215: - | G215: - | H215: - | I215: 6800576 | J215: - | K215: - | L215: - | M215: - | N215: =AVERAGE(B215:M215) -> 6800576
A216: Crystal Innovations | B216: - | C216: - | D216: - | E216: - | F216: - | G216: - | H216: - | I216: - | J216: 1902560 | K216: - | L216: - | M216: - | N216: =AVERAGE(B216:M216) -> 1902560
A217: Future Trends Retail | B217: - | C217: - | D217: - | E217: - | F217: - | G217: - | H217: - | I217: - | J217: - | K217: 4872609 | L217: - | M217: - | N217: =AVERAGE(B217:M217) -> 4872609
A218: Radiant Horizon Ventures | B218: - | C218: 6242976 | D218: 3540726 | E218: 3946464 | F218: - | G218: - | H218: - | I218: - | J218: - | K218: - | L218: - | M218: - | N218: =AVERAGE(B218:M218) -> 4576722
A219: Elite Spectrum Consulting | B219: 4635288 | C219: - | D219: - | E219: - | F219: - | G219: - | H219: - | I219: - | J219: - | K219: - | L219: - | M219: - | N219: =AVERAGE(B219:M219) -> 4635288
A220: Dynamic Design Studio | B220: - | C220: - | D220: - | E220: - | F220: 5225856 | G220: - | H220: - | I220: - | J220: - | K220: - | L220: - | M220: - | N220: =AVERAGE(B220:M220) -> 5225856
A221: Royal Crest Foods | B221: - | C221: - | D221: 3621286 | E221: - | F221: 5477964 | G221: - | H221: - | I221: 2446290 | J221: 5795784 | K221: - | L221: - | M221: - | N221: =AVERAGE(B221:M221) -> 4335331
A222: Legacy Apparel | B222: - | C222: - | D222: - | E222: - | F222: - | G222: - | H222: - | I222: - | J222: - | K222: - | L222: 4704803 | M222: - | N222: =AVERAGE(B222:M222) -> 4704803
A223: Pinnacle Education Group | B223: - | C223: - | D223: - | E223: - | F223: - | G223: - | H223: - | I223: 1351636 | J223: - | K223: - | L223: - | M223: - | N223: =AVERAGE(B223:M223) -> 1351636
A224: Urban Pulse Media | B224: - | C224: - | D224: - | E224: - | F224: - | G224: - | H224: - | I224: - | J224: - | K224: 4274517 | L224: - | M224: - | N224: =AVERAGE(B224:M224) -> 4274517
A225: Crystal Clear Realty | B225: 6147545 | C225: 3302221.8 | D225: 3832284.7 | E225: 4134837 | F225: 2862026.2 | G225: 2385175 | H225: - | I225: 5371219.5 | J225: 2809252 | K225: 6386463 | L225: 3035136 | M225: - | N225: =AVERAGE(B225:M225) -> 4026616
A226: Apex Enterprise Solutions | B226: - | C226: - | D226: - | E226: - | F226: - | G226: - | H226: - | I226: - | J226: - | K226: - | L226: 1996896 | M226: - | N226: =AVERAGE(B226:M226) -> 1996896
A227: Radiant Vision Realty | B227: - | C227: - | D227: - | E227: - | F227: - | G227: - | H227: - | I227: 1577225 | J227: - | K227: - | L227: - | M227: - | N227: =AVERAGE(B227:M227) -> 1577225
A228: Stellar Health Services | B228: - | C228: - | D228: - | E228: - | F228: - | G228: - | H228: - | I228: - | J228: - | K228: 3223200 | L228: - | M228: - | N228: =AVERAGE(B228:M228) -> 3223200
A229: Prestige Solutions | B229: - | C229: - | D229: - | E229: - | F229: - | G229: - | H229: 4638410 | I229: - | J229: - | K229: - | L229: 4296810 | M229: - | N229: =AVERAGE(B229:M229) -> 4467610
A230: Radiant Travel Services | B230: - | C230: - | D230: - | E230: - | F230: - | G230: 6097110 | H230: - | I230: - | J230: - | K230: - | L230: - | M230: - | N230: =AVERAGE(B230:M230) -> 6097110
A231: Modern Trends Consulting | B231: - | C231: - | D231: - | E231: 2895288 | F231: - | G231: - | H231: - | I231: - | J231: - | K231: - | L231: - | M231: - | N231: =AVERAGE(B231:M231) -> 2895288
A232: Global Horizon Ventures | B232: - | C232: - | D232: - | E232: - | F232: - | G232: - | H232: - | I232: - | J232: 8314173 | K232: - | L232: - | M232: - | N232: =AVERAGE(B232:M232) -> 8314173
A233: Radiance Apparel | B233: - | C233: - | D233: - | E233: - | F233: 5331045 | G233: - | H233: - | I233: - | J233: - | K233: - | L233: - | M233: - | N233: =AVERAGE(B233:M233) -> 5331045
A234: Zenith Design Group | B234: - | C234: - | D234: - | E234: - | F234: - | G234: - | H234: - | I234: 7530354 | J234: - | K234: - | L234: - | M234: - | N234: =AVERAGE(B234:M234) -> 7530354
A235: Legacy Travel Agency | B235: - | C235: - | D235: - | E235: 2810830 | F235: - | G235: - | H235: - | I235: - | J235: - | K235: - | L235: - | M235: - | N235: =AVERAGE(B235:M235) -> 2810830
A236: Pure Essence Solutions | B236: - | C236: - | D236: - | E236: - | F236: - | G236: 7446900 | H236: - | I236: - | J236: - | K236: - | L236: - | M236: - | N236: =AVERAGE(B236:M236) -> 7446900
A237: Pinnacle Finance | B237: - | C237: - | D237: - | E237: - | F237: - | G237: 5250229 | H237: - | I237: - | J237: - | K237: - | L237: - | M237: - | N237: =AVERAGE(B237:M237) -> 5250229
A238: Horizon Tech Ventures | B238: - | C238: - | D238: 3667648 | E238: - | F238: - | G238: - | H238: - | I238: - | J238: - | K238: - | L238: - | M238: - | N238: =AVERAGE(B238:M238) -> 3667648
A239: Crystal Health Solutions | B239: - | C239: - | D239: - | E239: - | F239: 5275072 | G239: - | H239: - | I239: - | J239: - | K239: - | L239: - | M239: - | N239: =AVERAGE(B239:M239) -> 5275072
A240: Urban Focus Products | B240: - | C240: 1082720 | D240: - | E240: - | F240: - | G240: - | H240: - | I240: - | J240: - | K240: - | L240: - | M240: - | N240: =AVERAGE(B240:M240) -> 1082720
...

Sheet Lookup & Refrence
A1: Employee_ID | B1: Employee_Name | C1: Department | D1: Salary | F1: Employee_ID | G1: Salary | H1: Salary
A2: 101 | B2: Amit Sharma | C2: Accounts | D2: 35000 | F2: 101 | G2: =VLOOKUP(F2,A2:D11,4,FALSE) -> 35000
A3: 102 | B3: Neha Verma | C3: HR | D3: 30000
A4: 103 | B4: Rohit Gupta | C4: Sales | D4: 40000
A5: 104 | B5: Pooja Singh | C5: IT | D5: 45000
A6: 105 | B6: Ankit Jain | C6: Marketing | D6: 38000
A7: 106 | B7: Amit Sharma | C7: Accounts | D7: 35000
A8: 107 | B8: Neha Verma | C8: HR | D8: 30000
A9: 108 | B9: Rohit Gupta | C9: Sales | D9: 40000
A10: 109 | B10: Pooja Singh | C10: IT | D10: 45000
A11: 110 | B11: Ankit Jain | C11: Marketing | D11: 38000
A18: Employee_ID | B18: Employee_Name | C18: Department | D18: Salary | F18: Employee_ID | G18: Salary | H18: Salary
A19: 101 | B19: Amit Sharma | C19: Accounts | D19: 35000 | F19: 103 | G19: =VLOOKUP($F19,$A$19:$D$28,4,FALSE) -> 40000
A20: 102 | B20: Neha Verma | C20: HR | D20: 30000 | F20: 108 | G20: =VLOOKUP($F20,$A$19:$D$28,4,FALSE) -> 40000
A21: 103 | B21: Rohit Gupta | C21: Sales | D21: 40000 | F21: 109 | G21: =VLOOKUP($F21,$A$19:$D$28,4,FALSE) -> 45000
A22: 104 | B22: Pooja Singh | C22: IT | D22: 45000 | F22: 110 | G22: =VLOOKUP($F22,$A$19:$D$28,4,FALSE) -> 38000
A23: 105 | B23: Ankit Jain | C23: Marketing | D23: 38000
A24: 106 | B24: Amit Sharma | C24: Accounts | D24: 35000
A25: 107 | B25: Neha Verma | C25: HR | D25: 30000
A26: 108 | B26: Rohit Gupta | C26: Sales | D26: 40000
A27: 109 | B27: Pooja Singh | C27: IT | D27: 45000
A28: 110 | B28: Ankit Jain | C28: Marketing | D28: 38000
A33: S no | B33: Employee_ID | C33: Employee_Name | D33: Department | E33: Salary | G33: Employee_ID | H33: Salary | I33: Salary
A34: 1 | B34: 101 | C34: Amit Sharma | D34: Accounts | E34: 35000 | G34: 103 | H34: =VLOOKUP(G34,$A$34:$E$43,5,FALSE) -> #N/A
A35: 2 | B35: 102 | C35: Neha Verma | D35: HR | E35: 30000 | G35: 106 | H35: =VLOOKUP(G35,$A$34:$E$43,5,FALSE) -> #N/A
A36: 3 | B36: 103 | C36: Rohit Gupta | D36: Sales | E36: 40000 | G36: 109 | H36: =VLOOKUP(G36,$A$34:$E$43,5,FALSE) -> #N/A
A37: 4 | B37: 104 | C37: Pooja Singh | D37: IT | E37: 45000 | G37: 110 | H37: =VLOOKUP(G37,$A$34:$E$43,5,FALSE) -> #N/A
A38: 5 | B38: 105 | C38: Ankit Jain | D38: Marketing | E38: 38000
A39: 6 | B39: 106 | C39: Amit Sharma | D39: Accounts | E39: 35000
A40: 7 | B40: 107 | C40: Neha Verma | D40: HR | E40: 30000
A41: 8 | B41: 108 | C41: Rohit Gupta | D41: Sales | E41: 40000
A42: 9 | B42: 109 | C42: Pooja Singh | D42: IT | E42: 45000
A43: 10 | B43: 110 | C43: Ankit Jain | D43: Marketing | E43: 38000
A51: Employee_ID | B51: Employee_Name | C51: Department | D51: Salary | F51: Employee_ID | G51: Salary
A52: 101 | B52: Amit Sharma | C52: Accounts | D52: 35000 | F52: 103 | G52: =VLOOKUP(F52,A52:D61,4,FALSE) -> 40000
A53: 102 | B53: Neha Verma | C53: HR | D53: 30000
A54: 103 | B54: Rohit Gupta | C54: Sales | D54: 40000 | F54: I m asking for pooja singh's salary instead of Rohit Gupta
A55: 104 | B55: Pooja Singh | C55: IT | D55: 45000
A56: 105 | B56: Ankit Jain | C56: Marketing | D56: 38000
A57: 101 | B57: Amit Sharma | C57: Accounts | D57: 35000
A58: 107 | B58: Neha Verma | C58: HR | D58: 30000
A59: 102 | B59: Rohit Gupta | C59: Sales | D59: 40000
A60: 103 | B60: Pooja Singh | C60: IT | D60: 45000
A61: 104 | B61: Ankit Jain | C61: Marketing | D61: 38000
A73: Employee_ID | B73: Employee_Name | C73: Department | D73: Salary | F73: Employee_ID | G73: Salary
A74: 101 | B74: Amit Sharma | C74: Accounts | D74: 35000 | F74: 103 | G74: =VLOOKUP(F74,A74:D83,4,FALSE) -> #N/A
A75: 102 | B75: Neha Verma | C75: HR | D75: 30000
A76: 111 | B76: Rohit Gupta | C76: Sales | D76: 40000
A77: 104 | B77: Pooja Singh | C77: IT | D77: 45000
A78: 105 | B78: Ankit Jain | C78: Marketing | D78: 38000
A79: 101 | B79: Amit Sharma | C79: Accounts | D79: 35000
A80: 107 | B80: Neha Verma | C80: HR | D80: 30000
A81: 102 | B81: Rohit Gupta | C81: Sales | D81: 40000
A82: 112 | B82: Pooja Singh | C82: IT | D82: 45000
A83: 104 | B83: Ankit Jain | C83: Marketing | D83: 38000
A88: Employee_ID | B88: Employee_Name | C88: Department | D88: Salary | F88: Employee_ID | G88: Department | H88: Salary
A89: 101 | B89: Amit Sharma | C89: Accounts | D89: 35000 | F89: 103 | G89: {=VLOOKUP($F89,$A$89:$D$98,{3,4},FALSE)} -> Sales | H89: 40000
A90: 102 | B90: Neha Verma | C90: HR | D90: 30000 | F90: 108 | G90: {=VLOOKUP($F90,$A$89:$D$98,{3,4},FALSE)} -> Sales | H90: 40000
A91: 103 | B91: Rohit Gupta | C91: Sales | D91: 40000 | F91: 109 | G91: {=VLOOKUP($F91,$A$89:$D$98,{3,4},FALSE)} -> IT | H91: 45000
A92: 104 | B92: Pooja Singh | C92: IT | D92: 45000 | F92: 110 | G92: {=VLOOKUP($F92,$A$89:$D$98,{3,4},FALSE)} -> Marketing | H92: 38000
A93: 105 | B93: Ankit Jain | C93: Marketing | D93: 38000
A94: 106 | B94: Amit Sharma | C94: Accounts | D94: 35000
A95: 107 | B95: Neha Verma | C95: HR | D95: 30000 | F95: Employee_ID | G95: Department | H95: Salary
A96: 108 | B96: Rohit Gupta | C96: Sales | D96: 40000 | F96: 103
A97: 109 | B97: Pooja Singh | C97: IT | D97: 45000 | F97: 108
A98: 110 | B98: Ankit Jain | C98: Marketing | D98: 38000 | F98: 109
F99: 110
A110: Employee_Name | B110: Department | C110: Salary | D110: Employee_ID | F110: Employee_ID | G110: Department | H110: Salary
A111: Amit Sharma | B111: Accounts | C111: 35000 | D111: 101 | F111: 103 | G111: {=VLOOKUP($F111,CHOOSE({1,2,3,4},$D$111:$D$120,$A$111:$A$120,$B$111:$B$120,$C$111:$C$120),{3,4},FALSE)} -> Sales | H111: 40000
A112: Neha Verma | B112: HR | C112: 30000 | D112: 102 | F112: 108 | G112: {=VLOOKUP($F112,CHOOSE({1,2,3,4},$D$111:$D$120,$A$111:$A$120,$B$111:$B$120,$C$111:$C$120),{3,4},FALSE)} -> Sales | H112: 40000
A113: Rohit Gupta | B113: Sales | C113: 40000 | D113: 103 | F113: 109 | G113: {=VLOOKUP($F113,CHOOSE({1,2,3,4},$D$111:$D$120,$A$111:$A$120,$B$111:$B$120,$C$111:$C$120),{3,4},FALSE)} -> IT | H113: 45000
A114: Pooja Singh | B114: IT | C114: 45000 | D114: 104 | F114: 110 | G114: {=VLOOKUP($F114,CHOOSE({1,2,3,4},$D$111:$D$120,$A$111:$A$120,$B$111:$B$120,$C$111:$C$120),{3,4},FALSE)} -> Marketing | H114: 38000
A115: Ankit Jain | B115: Marketing | C115: 38000 | D115: 105
A116: Amit Sharma | B116: Accounts | C116: 35000 | D116: 106
A117: Neha Verma | B117: HR | C117: 30000 | D117: 107 | F117: Employee_ID | G117: Department | H117: Salary
A118: Rohit Gupta | B118: Sales | C118: 40000 | D118: 108 | F118: 103
A119: Pooja Singh | B119: IT | C119: 45000 | D119: 109 | F119: 108
A120: Ankit Jain | B120: Marketing | C120: 38000 | D120: 110 | F120: 109
F121: 110
B125: {=CHOOSE({1,2,3,4},D111:D120,A111:A120,B111:B120,C111:C120)} -> 101 | C125: Amit Sharma | D125: Accounts | E125: 35000
B126: 102 | C126: Neha Verma | D126: HR | E126: 30000
B127: 103 | C127: Rohit Gupta | D127: Sales | E127: 40000
B128: 104 | C128: Pooja Singh | D128: IT | E128: 45000
B129: 105 | C129: Ankit Jain | D129: Marketing | E129: 38000
B130: 106 | C130: Amit Sharma | D130: Accounts | E130: 35000
B131: 107 | C131: Neha Verma | D131: HR | E131: 30000
B132: 108 | C132: Rohit Gupta | D132: Sales | E132: 40000
B133: 109 | C133: Pooja Singh | D133: IT | E133: 45000
B134: 110 | C134: Ankit Jain | D134: Marketing | E134: 38000
A151: Students Name | B151: Hindi | C151: English | D151: Math | E151: Science | F151: Total | G151: % | H151: Grade
A152: Aarav Mehta | B152: 100 | C152: 100 | D152: 90 | E152: 90 | F152: =SUM(B152:E152) -> 380 | G152: =F152/400 -> 0.95 | H152: =VLOOKUP(G152,$K$152:$L$156,2,TRUE) -> A+ | J152: 0%-30% | K152: 0 | L152: D
A153: Priya Sharma | B153: 95 | C153: 85 | D153: 96 | E153: 95 | F153: =SUM(B153:E153) -> 371 | G153: =F153/400 -> 0.9275 | H153: =VLOOKUP(G153,$K$152:$L$156,2,TRUE) -> A+ | J153: 30%-50% | K153: 0.3 | L153: C
A154: Ishaan Verma | B154: 85 | C154: 87 | D154: 58 | E154: 62 | F154: =SUM(B154:E154) -> 292 | G154: =F154/400 -> 0.73 | H154: =VLOOKUP(G154,$K$152:$L$156,2,TRUE) -> B | J154: 50%-75% | K154: 0.5 | L154: B
A155: Sneha Iyer | B155: 61 | C155: 52 | D155: 77 | E155: 67 | F155: =SUM(B155:E155) -> 257 | G155: =F155/400 -> 0.6425 | H155: =VLOOKUP(G155,$K$152:$L$156,2,TRUE) -> B | J155: 75%-90% | K155: 0.75 | L155: A
A156: Rohan Das | B156: 26 | C156: 91 | D156: 75 | E156: 38 | F156: =SUM(B156:E156) -> 230 | G156: =F156/400 -> 0.575 | H156: =VLOOKUP(G156,$K$152:$L$156,2,TRUE) -> B | J156: 90%-100% | K156: 0.9 | L156: A+
A157: Kritika Nair | B157: 49 | C157: 55 | D157: 63 | E157: 73 | F157: =SUM(B157:E157) -> 240 | G157: =F157/400 -> 0.6 | H157: =VLOOKUP(G157,$K$152:$L$156,2,TRUE) -> B
A158: Yash Patel | B158: 44 | C158: 56 | D158: 92 | E158: 77 | F158: =SUM(B158:E158) -> 269 | G158: =F158/400 -> 0.6725 | H158: =VLOOKUP(G158,$K$152:$L$156,2,TRUE) -> B
A159: Ananya Reddy | B159: 95 | C159: 80 | D159: 62 | E159: 85 | F159: =SUM(B159:E159) -> 322 | G159: =F159/400 -> 0.805 | H159: =VLOOKUP(G159,$K$152:$L$156,2,TRUE) -> A
A160: Aditya Choudhary | B160: 64 | C160: 59 | D160: 85 | E160: 58 | F160: =SUM(B160:E160) -> 266 | G160: =F160/400 -> 0.665 | H160: =VLOOKUP(G160,$K$152:$L$156,2,TRUE) -> B
A161: Tanvi Joshi | B161: 32 | C161: 42 | D161: 30 | E161: 63 | F161: =SUM(B161:E161) -> 167 | G161: =F161/400 -> 0.4175 | H161: =VLOOKUP(G161,$K$152:$L$156,2,TRUE) -> C
...

Sheet Sheet7
A1: Employee_ID | B1: Employee_Name | C1: Department | D1: Salary | F1: Employee_ID | G1: Salary
A2: 101 | B2: Amit Sharma | C2: Accounts | D2: 35000 | F2: 101 | G2: =VLOOKUP(F2,Table1[],4,FALSE) -> 35000
A3: 102 | B3: Neha Verma | C3: HR | D3: 30000
A4: 103 | B4: Rohit Gupta | C4: Sales | D4: 40000
A5: 104 | B5: Pooja Singh | C5: IT | D5: 45000
A6: 105 | B6: Ankit Jain | C6: Marketing | D6: 38000
A7: 106 | B7: Amit Sharma | C7: Accounts | D7: 35000
A8: 107 | B8: Neha Verma | C8: HR | D8: 30000
A9: 108 | B9: Rohit Gupta | C9: Sales | D9: 40000
A10: 109 | B10: Pooja Singh | C10: IT | D10: 45000
A11: 110 | B11: Ankit Jain | C11: Marketing | D11: 38000
A21: Employee_Name | B21: Department | C21: Salary | E21: Employee_ID | F21: Salary
A22: Amit Sharma | B22: Accounts | C22: 35000 | E22: 103 | F22: =VLOOKUP(E22,Table1[],4,FALSE) -> 40000
A23: Neha Verma | B23: HR | C23: 30000 | E23: 108 | F23: =VLOOKUP(E23,Table1[],4,FALSE) -> 40000
A24: Rohit Gupta | B24: Sales | C24: 40000 | E24: 109 | F24: =VLOOKUP(E24,Table1[],4,FALSE) -> 45000
A25: Pooja Singh | B25: IT | C25: 45000 | E25: 110 | F25: =VLOOKUP(E25,Table1[],4,FALSE) -> 38000
A26: Ankit Jain | B26: Marketing | C26: 38000
A27: Amit Sharma | B27: Accounts | C27: 35000
A28: Neha Verma | B28: HR | C28: 30000
A29: Rohit Gupta | B29: Sales | C29: 40000
A30: Pooja Singh | B30: IT | C30: 45000
A31: Ankit Jain | B31: Marketing | C31: 38000

Sheet Filter Formula
B1: Employee_ID | C1: Employee_Name | D1: Department | E1: Salary
B2: 101 | C2: Amit Sharma | D2: Accounts | E2: 40000 | G2: 104
B3: 102 | C3: Neha Verma | D3: HR | E3: 30000
B4: 101 | C4: Amit Sharma | D4: Accounts | E4: 20000 | G4: Employee_ID | H4: Employee_Name | I4: Department | J4: Salary
B5: 104 | C5: Pooja Singh | D5: IT | E5: 45000 | G5: {=_xlfn._xlws.FILTER(B2:E11,B2:B11=G2)} -> 104 | H5: Pooja Singh | I5: IT | J5: 45000
B6: 102 | C6: Neha Verma | D6: HR | E6: 30000 | G6: 104 | H6: Pooja Singh | I6: IT | J6: 50000
B7: 101 | C7: Amit Sharma | D7: Accounts | E7: 35000 | G7: 104 | H7: Pooja Singh | I7: IT | J7: 45000
B8: 104 | C8: Pooja Singh | D8: IT | E8: 50000
B9: 102 | C9: Neha Verma | D9: HR | E9: 30000
B10: 101 | C10: Amit Sharma | D10: Accounts | E10: 35000
B11: 104 | C11: Pooja Singh | D11: IT | E11: 45000
B16: Employee_ID | C16: Employee_Name | D16: Department | E16: Salary
B17: 101 | C17: Amit Sharma | D17: Accounts | E17: 40000 | G17: Amit Sharma
B18: 102 | C18: Neha Verma | D18: HR | E18: 30000
B19: 101 | C19: Amit Sharma | D19: Accounts | E19: 20000 | G19: Employee_ID | H19: Employee_Name | I19: Department | J19: Salary
B20: 104 | C20: Pooja Singh | D20: IT | E20: 45000 | G20: {=_xlfn._xlws.FILTER(B17:E26,C17:C26=G17)} -> 101 | H20: Amit Sharma | I20: Accounts | J20: 40000
B21: 102 | C21: Neha Verma | D21: HR | E21: 30000 | G21: 101 | H21: Amit Sharma | I21: Accounts | J21: 20000
B22: 101 | C22: Amit Sharma | D22: Accounts | E22: 35000 | G22: 101 | H22: Amit Sharma | I22: Accounts | J22: 35000
B23: 104 | C23: Pooja Singh | D23: IT | E23: 50000 | G23: 101 | H23: Amit Sharma | I23: Accounts | J23: 35000
B24: 102 | C24: Neha Verma | D24: HR | E24: 30000
B25: 101 | C25: Amit Sharma | D25: Accounts | E25: 35000
B26: 104 | C26: Pooja Singh | D26: IT | E26: 45000
B32: Employee_ID | C32: Employee_Name | D32: Department | E32: Salary
B33: 101 | C33: Amit Sharma | D33: Accounts | E33: 40000 | G33: 40000
B34: 102 | C34: Neha Verma | D34: HR | E34: 30000
B35: 101 | C35: Amit Sharma | D35: Accounts | E35: 20000 | G35: Employee_ID | H35: Employee_Name | I35: Department | J35: Salary
B36: 104 | C36: Pooja Singh | D36: IT | E36: 45000 | G36: {=_xlfn._xlws.FILTER(B33:E42,E33:E42>G33)} -> 104 | H36: Pooja Singh | I36: IT | J36: 45000
B37: 102 | C37: Neha Verma | D37: HR | E37: 30000 | G37: 104 | H37: Pooja Singh | I37: IT | J37: 50000
B38: 101 | C38: Amit Sharma | D38: Accounts | E38: 35000 | G38: 104 | H38: Pooja Singh | I38: IT | J38: 45000
B39: 104 | C39: Pooja Singh | D39: IT | E39: 50000
B40: 102 | C40: Neha Verma | D40: HR | E40: 30000
B41: 101 | C41: Amit Sharma | D41: Accounts | E41: 35000
B42: 104 | C42: Pooja Singh | D42: IT | E42: 45000
B57: Employee_ID | C57: Employee_Name | D57: Department | E57: Salary | G57: Department
B58: 101 | C58: Amit Sharma | D58: Accounts | E58: 40000 | G58: Accounts
B59: 102 | C59: Neha Verma | D59: HR | E59: 30000
B60: 101 | C60: Amit Sharma | D60: Accounts | E60: 20000 | G60: Employee_ID | H60: Employee_Name | I60: Department | J60: Salary
B61: 104 | C61: Pooja Singh | D61: Accounts | E61: 45000 | G61: 101 | H61: Amit Sharma | I61: Accounts | J61: 40000
B62: 102 | C62: Neha Verma | D62: HR | E62: 30000 | G62: 101 | H62: Amit Sharma | I62: Accounts | J62: 20000
B63: 101 | C63: Amit Sharma | D63: HR | E63: 35000 | G63: 104 | H63: Pooja Singh | I63: Accounts | J63: 45000
B64: 104 | C64: Pooja Singh | D64: IT | E64: 50000 | G64: 101 | H64: Amit Sharma | I64: Accounts | J64: 35000
B65: 102 | C65: Neha Verma | D65: HR | E65: 30000
B66: 101 | C66: Amit Sharma | D66: Accounts | E66: 35000
B67: 104 | C67: Pooja Singh | D67: IT | E67: 45000

Sheet Financial Formulas
C2: Principle Amount | D2: 110000
C3: Down Payment | D3: 10000
C4: Remaining amount | D4: =D2-D3 -> 100000
C5: Interest (in years) | D5: 0.12
C6: Interest (in months) | D6: =D5/12 -> 0.01
C7: Time (in years) | D7: 1
C8: Time (in months) | D8: =D7*12 -> 12
C9: Emi (Pmt) | D9: =PMT(D6,D8,D4) -> -8884.8789
C10: Interest Paid (ipmt) | D10: =IPMT(D6,D7,D8,D4) -> -1000
C11: Principle paid (ppmt) | D11: =PPMT(D6,D7,D8,D4) -> -7884.8789
C14: Emi = IPMT + PPMT

Sheet Formula 365
A1: Employee_ID | B1: Employee_Name | C1: Department | D1: Salary | F1: Employee_ID | G1: Employee_Name | H1: Department | I1: Salary | K1: Employee_ID | L1: Employee_Name | M1: Department | N1: Salary
A2: 101 | B2: Amit Sharma | C2: Accounts | D2: 35000 | F2: 105 | G2: Ankit Jain | H2: Marketing | I2: 38000 | K2: 108 | L2: Rohit Gupta | M2: Sales | N2: 40000
A3: 102 | B3: Neha Verma | C3: HR | D3: 30000 | F3: 106 | G3: Amit Sharma | H3: Accounts | I3: 35000 | K3: 109 | L3: Pooja Singh | M3: IT | N3: 45000
A4: 103 | B4: Neha Verma | C4: Sales | D4: 40000 | F4: 107 | G4: Neha Verma | H4: HR | I4: 30000 | K4: 110 | L4: Ankit Jain | M4: Marketing | N4: 38000
A5: 104 | B5: Pooja Singh | C5: IT | D5: 45000
B9: {=_xlfn.UNIQUE(B2:B5)} -> Amit Sharma | E9: {=_xlfn.VSTACK(A1:D5,F2:I4,K2:N4)} -> Employee_ID | F9: Employee_Name | G9: Department | H9: Salary
B10: Neha Verma | E10: 101 | F10: Amit Sharma | G10: Accounts | H10: 35000
B11: Pooja Singh | E11: 102 | F11: Neha Verma | G11: HR | H11: 30000
E12: 103 | F12: Neha Verma | G12: Sales | H12: 40000
E13: 104 | F13: Pooja Singh | G13: IT | H13: 45000
E14: 105 | F14: Ankit Jain | G14: Marketing | H14: 38000
E15: 106 | F15: Amit Sharma | G15: Accounts | H15: 35000
E16: 107 | F16: Neha Verma | G16: HR | H16: 30000
E17: 108 | F17: Rohit Gupta | G17: Sales | H17: 40000
E18: 109 | F18: Pooja Singh | G18: IT | H18: 45000
E19: 110 | F19: Ankit Jain | G19: Marketing | H19: 38000
C30: {=_xlfn.SEQUENCE(5,4,1,1)} -> 1 | D30: 2 | E30: 3 | F30: 4
C31: 5 | D31: 6 | E31: 7 | F31: 8
C32: 9 | D32: 10 | E32: 11 | F32: 12
C33: 13 | D33: 14 | E33: 15 | F33: 16
C34: 17 | D34: 18 | E34: 19 | F34: 20
C39: 1 | D39: 5 | E39: 9 | F39: 13 | G39: 17
C40: 2 | D40: 6 | E40: 10 | F40: 14 | G40: 18
C41: 3 | D41: 7 | E41: 11 | F41: 15 | G41: 19
C42: 4 | D42: 8 | E42: 12 | F42: 16 | G42: 20

Sheet QR Code

Sheet Partywise Monthly Sale
A1: Partywise & Monthwise Sale Summary
A3: Party Name | B3: Jan | C3: Feb | D3: Mar | E3: Apr | F3: May | G3: Jun | H3: Jul | I3: Aug | J3: Sep | K3: Oct | L3: Nov | M3: Dec | N3: Grand Total
A4: Apex Auto Care | B4: =SUMIFS('Master data'!$M$2:$M$296,'Master data'!$D$2:$D$296,$A4,'Master data'!$C$2:$C$296,B$3) -> 0 | C4: =SUMIFS('Master data'!$M$2:$M$296,'Master data'!$D$2:$D$296,$A4,'Master data'!$C$2:$C$296,C$3) -> 0 | D4: =SUMIFS('Master data'!$M$2:$M$296,'Master data'!$D$2:$D$296,$A4,'Master data'!$C$2:$C$296,D$3) -> 0 | E4: =SUMIFS('Master data'!$M$2:$M$296,'Master data'!$D$2:$D$296,$A4,'Master data'!$C$2:$C$296,E$3) -> 0 | F4: =SUMIFS('Master data'!$M$2:$M$296,'Master data'!$D$2:$D$296,$A4,'Master data'!$C$2:$C$296,F$3) -> 0 | G4: =SUMIFS('Master data'!$M$2:$M$296,'Master data'!$D$2:$D$296,$A4,'Master data'!$C$2:$C$296,G$3) -> 0 | H4: =SUMIFS('Master data'!$M$2:$M$296,'Master data'!$D$2:$D$296,$A4,'Master data'!$C$2:$C$296,H$3) -> 0 | I4: =SUMIFS('Master data'!$M$2:$M$296,'Master data'!$D$2:$D$296,$A4,'Master data'!$C$2:$C$296,I$3) -> 0 | ... M4: =SUMIFS('Master data'!$M$2:$M$296,'Master data'!$D$2:$D$296,$A4,'Master data'!$C$2:$C$296,M$3) -> 0 | N4: =SUM(B4:M4) -> 7541264
A5: Apex Construction | B5: =SUMIFS('Master data'!$M$2:$M$296,'Master data'!$D$2:$D$296,$A5,'Master data'!$C$2:$C$296,B$3) -> 0 | C5: =SUMIFS('Master data'!$M$2:$M$296,'Master data'!$D$2:$D$296,$A5,'Master data'!$C$2:$C$296,C$3) -> 1404660 | D5: =SUMIFS('Master data'!$M$2:$M$296,'Master data'!$D$2:$D$296,$A5,'Master data'!$C$2:$C$296,D$3) -> 0 | E5: =SUMIFS('Master data'!$M$2:$M$296,'Master data'!$D$2:$D$296,$A5,'Master data'!$C$2:$C$296,E$3) -> 0 | F5: =SUMIFS('Master data'!$M$2:$M$296,'Master data'!$D$2:$D$296,$A5,'Master data'!$C$2:$C$296,F$3) -> 0 | G5: =SUMIFS('Master data'!$M$2:$M$296,'Master data'!$D$2:$D$296,$A5,'Master data'!$C$2:$C$296,G$3) -> 0 | H5: =SUMIFS('Master data'!$M$2:$M$296,'Master data'!$D$2:$D$296,$A5,'Master data'!$C$2:$C$296,H$3) -> 0 | I5: =SUMIFS('Master data'!$M$2:$M$296,'Master data'!$D$2:$D$296,$A5,'Master data'!$C$2:$C$296,I$3) -> 0 | ... M5: =SUMIFS('Master data'!$M$2:$M$296,'Master data'!$D$2:$D$296,$A5,'Master data'!$C$2:$C$296,M$3) -> 0 | N5: =SUM(B5:M5) -> 1404660
A6: Apex Creative Solutions | B6: =SUMIFS('Master data'!$M$2:$M$296,'Master data'!$D$2:$D$296,$A6,'Master data'!$C$2:$C$296,B$3) -> 0 | C6: =SUMIFS('Master data'!$M$2:$M$296,'Master data'!$D$2:$D$296,$A6,'Master data'!$C$2:$C$296,C$3) -> 0 | D6: =SUMIFS('Master data'!$M$2:$M$296,'Master data'!$D$2:$D$296,$A6,'Master data'!$C$2:$C$296,D$3) -> 0 | E6: =SUMIFS('Master data'!$M$2:$M$296,'Master data'!$D$2:$D$296,$A6,'Master data'!$C$2:$C$296,E$3) -> 0 | F6: =SUMIFS('Master data'!$M$2:$M$296,'Master data'!$D$2:$D$296,$A6,'Master data'!$C$2:$C$296,F$3) -> 0 | G6: =SUMIFS('Master data'!$M$2:$M$296,'Master data'!$D$2:$D$296,$A6,'Master data'!$C$2:$C$296,G$3) -> 0 | H6: =SUMIFS('Master data'!$M$2:$M$296,'Master data'!$D$2:$D$296,$A6,'Master data'!$C$2:$C$296,H$3) -> 0 | I6: =SUMIFS('Master data'!$M$2:$M$296,'Master data'!$D$2:$D$296,$A6,'Master data'!$C$2:$C$296,I$3) -> 3206472 | ... M6: =SUMIFS('Master data'!$M$2:$M$296,'Master data'!$D$2:$D$296,$A6,'Master data'!$C$2:$C$296,M$3) -> 0 | N6: =SUM(B6:M6) -> 3206472
A7: Apex Educational Group | B7: =SUMIFS('Master data'!$M$2:$M$296,'Master data'!$D$2:$D$296,$A7,'Master data'!$C$2:$C$296,B$3) -> 0 | C7: =SUMIFS('Master data'!$M$2:$M$296,'Master data'!$D$2:$D$296,$A7,'Master data'!$C$2:$C$296,C$3) -> 1283040 | D7: =SUMIFS('Master data'!$M$2:$M$296,'Master data'!$D$2:$D$296,$A7,'Master data'!$C$2:$C$296,D$3) -> 0 | E7: =SUMIFS('Master data'!$M$2:$M$296,'Master data'!$D$2:$D$296,$A7,'Master data'!$C$2:$C$296,E$3) -> 0 | F7: =SUMIFS('Master data'!$M$2:$M$296,'Master data'!$D$2:$D$296,$A7,'Master data'!$C$2:$C$296,F$3) -> 8036326 | G7: =SUMIFS('Master data'!$M$2:$M$296,'Master data'!$D$2:$D$296,$A7,'Master data'!$C$2:$C$296,G$3) -> 0 | H7: =SUMIFS('Master data'!$M$2:$M$296,'Master data'!$D$2:$D$296,$A7,'Master data'!$C$2:$C$296,H$3) -> 0 | I7: =SUMIFS('Master data'!$M$2:$M$296,'Master data'!$D$2:$D$296,$A7,'Master data'!$C$2:$C$296,I$3) -> 0 | ... M7: =SUMIFS('Master data'!$M$2:$M$296,'Master data'!$D$2:$D$296,$A7,'Master data'!$C$2:$C$296,M$3) -> 0 | N7: =SUM(B7:M7) -> 14543556
A8: Apex Enterprise Solutions | B8: =SUMIFS('Master data'!$M$2:$M$296,'Master data'!$D$2:$D$296,$A8,'Master data'!$C$2:$C$296,B$3) -> 0 | C8: =SUMIFS('Master data'!$M$2:$M$296,'Master data'!$D$2:$D$296,$A8,'Master data'!$C$2:$C$296,C$3) -> 1996896 | D8: =SUMIFS('Master data'!$M$2:$M$296,'Master data'!$D$2:$D$296,$A8,'Master data'!$C$2:$C$296,D$3) -> 0 | E8: =SUMIFS('Master data'!$M$2:$M$296,'Master data'!$D$2:$D$296,$A8,'Master data'!$C$2:$C$296,E$3) -> 0 | F8: =SUMIFS('Master data'!$M$2:$M$296,'Master data'!$D$2:$D$296,$A8,'Master data'!$C$2:$C$296,F$3) -> 0 | G8: =SUMIFS('Master data'!$M$2:$M$296,'Master data'!$D$2:$D$296,$A8,'Master data'!$C$2:$C$296,G$3) -> 0 | H8: =SUMIFS('Master data'!$M$2:$M$296,'Master data'!$D$2:$D$296,$A8,'Master data'!$C$2:$C$296,H$3) -> 0 | I8: =SUMIFS('Master data'!$M$2:$M$296,'Master data'!$D$2:$D$296,$A8,'Master data'!$C$2:$C$296,I$3) -> 0 | ... M8: =SUMIFS('Master data'!$M$2:$M$296,'Master data'!$D$2:$D$296,$A8,'Master data'!$C$2:$C$296,M$3) -> 0 | N8: =SUM(B8:M8) -> 1996896
A9: Apex Finance Group | B9: =SUMIFS('Master data'!$M$2:$M$296,'Master data'!$D$2:$D$296,$A9,'Master data'!$C$2:$C$296,B$3) -> 0 | C9: =SUMIFS('Master data'!$M$2:$M$296,'Master data'!$D$2:$D$296,$A9,'Master data'!$C$2:$C$296,C$3) -> 0 | D9: =SUMIFS('Master data'!$M$2:$M$296,'Master data'!$D$2:$D$296,$A9,'Master data'!$C$2:$C$296,D$3) -> 0 | E9: =SUMIFS('Master data'!$M$2:$M$296,'Master data'!$D$2:$D$296,$A9,'Master data'!$C$2:$C$296,E$3) -> 0 | F9: =SUMIFS('Master data'!$M$2:$M$296,'Master data'!$D$2:$D$296,$A9,'Master data'!$C$2:$C$296,F$3) -> 0 | G9: =SUMIFS('Master data'!$M$2:$M$296,'Master data'!$D$2:$D$296,$A9,'Master data'!$C$2:$C$296,G$3) -> 0 | H9: =SUMIFS('Master data'!$M$2:$M$296,'Master data'!$D$2:$D$296,$A9,'Master data'!$C$2:$C$296,H$3) -> 0 | I9: =SUMIFS('Master data'!$M$2:$M$296,'Master data'!$D$2:$D$296,$A9,'Master data'!$C$2:$C$296,I$3) -> 0 | ... M9: =SUMIFS('Master data'!$M$2:$M$296,'Master data'!$D$2:$D$296,$A9,'Master data'!$C$2:$C$296,M$3) -> 0 | N9: =SUM(B9:M9) -> 6053400
A10: Apex Health Services | B10: =SUMIFS('Master data'!$M$2:$M$296,'Master data'!$D$2:$D$296,$A10,'Master data'!$C$2:$C$296,B$3) -> 0 | C10: =SUMIFS('Master data'!$M$2:$M$296,'Master data'!$D$2:$D$296,$A10,'Master data'!$C$2:$C$296,C$3) -> 0 | D10: =SUMIFS('Master data'!$M$2:$M$296,'Master data'!$D$2:$D$296,$A10,'Master data'!$C$2:$C$296,D$3) -> 0 | E10: =SUMIFS('Master data'!$M$2:$M$296,'Master data'!$D$2:$D$296,$A10,'Master data'!$C$2:$C$296,E$3) -> 1998444 | F10: =SUMIFS('Master data'!$M$2:$M$296,'Master data'!$D$2:$D$296,$A10,'Master data'!$C$2:$C$296,F$3) -> 0 | G10: =SUMIFS('Master data'!$M$2:$M$296,'Master data'!$D$2:$D$296,$A10,'Master data'!$C$2:$C$296,G$3) -> 0 | H10: =SUMIFS('Master data'!$M$2:$M$296,'Master data'!$D$2:$D$296,$A10,'Master data'!$C$2:$C$296,H$3) -> 0 | I10: =SUMIFS('Master data'!$M$2:$M$296,'Master data'!$D$2:$D$296,$A10,'Master data'!$C$2:$C$296,I$3) -> 0 | ... M10: =SUMIFS('Master data'!$M$2:$M$296,'Master data'!$D$2:$D$296,$A10,'Master data'!$C$2:$C$296,M$3) -> 0 | N10: =SUM(B10:M10) -> 1998444
A11: Apex Media Co. | B11: =SUMIFS('Master data'!$M$2:$M$296,'Master data'!$D$2:$D$296,$A11,'Master data'!$C$2:$C$296,B$3) -> 0 | C11: =SUMIFS('Master data'!$M$2:$M$296,'Master data'!$D$2:$D$296,$A11,'Master data'!$C$2:$C$296,C$3) -> 0 | D11: =SUMIFS('Master data'!$M$2:$M$296,'Master data'!$D$2:$D$296,$A11,'Master data'!$C$2:$C$296,D$3) -> 0 | E11: =SUMIFS('Master data'!$M$2:$M$296,'Master data'!$D$2:$D$296,$A11,'Master data'!$C$2:$C$296,E$3) -> 0 | F11: =SUMIFS('Master data'!$M$2:$M$296,'Master data'!$D$2:$D$296,$A11,'Master data'!$C$2:$C$296,F$3) -> 0 | G11: =SUMIFS('Master data'!$M$2:$M$296,'Master data'!$D$2:$D$296,$A11,'Master data'!$C$2:$C$296,G$3) -> 0 | H11: =SUMIFS('Master data'!$M$2:$M$296,'Master data'!$D$2:$D$296,$A11,'Master data'!$C$2:$C$296,H$3) -> 0 | I11: =SUMIFS('Master data'!$M$2:$M$296,'Master data'!$D$2:$D$296,$A11,'Master data'!$C$2:$C$296,I$3) -> 4601856 | ... M11: =SUMIFS('Master data'!$M$2:$M$296,'Master data'!$D$2:$D$296,$A11,'Master data'!$C$2:$C$296,M$3) -> 0 | N11: =SUM(B11:M11) -> 4601856
A12: Apex Retailers | B12: =SUMIFS('Master data'!$M$2:$M$296,'Master data'!$D$2:$D$296,$A12,'Master data'!$C$2:$C$296,B$3) -> 0 | C12: =SUMIFS('Master data'!$M$2:$M$296,'Master data'!$D$2:$D$296,$A12,'Master data'!$C$2:$C$296,C$3) -> 0 | D12: =SUMIFS('Master data'!$M$2:$M$296,'Master data'!$D$2:$D$296,$A12,'Master data'!$C$2:$C$296,D$3) -> 0 | E12: =SUMIFS('Master data'!$M$2:$M$296,'Master data'!$D$2:$D$296,$A12,'Master data'!$C$2:$C$296,E$3) -> 0 | F12: =SUMIFS('Master data'!$M$2:$M$296,'Master data'!$D$2:$D$296,$A12,'Master data'!$C$2:$C$296,F$3) -> 0 | G12: =SUMIFS('Master data'!$M$2:$M$296,'Master data'!$D$2:$D$296,$A12,'Master data'!$C$2:$C$296,G$3) -> 0 | H12: =SUMIFS('Master data'!$M$2:$M$296,'Master data'!$D$2:$D$296,$A12,'Master data'!$C$2:$C$296,H$3) -> 0 | I12: =SUMIFS('Master data'!$M$2:$M$296,'Master data'!$D$2:$D$296,$A12,'Master data'!$C$2:$C$296,I$3) -> 0 | ... M12: =SUMIFS('Master data'!$M$2:$M$296,'Master data'!$D$2:$D$296,$A12,'Master data'!$C$2:$C$296,M$3) -> 0 | N12: =SUM(B12:M12) -> 1356885
A13: Apex Travel Ventures | B13: =SUMIFS('Master data'!$M$2:$M$296,'Master data'!$D$2:$D$296,$A13,'Master data'!$C$2:$C$296,B$3) -> 6192618 | C13: =SUMIFS('Master data'!$M$2:$M$296,'Master data'!$D$2:$D$296,$A13,'Master data'!$C$2:$C$296,C$3) -> 0 | D13: =SUMIFS('Master data'!$M$2:$M$296,'Master data'!$D$2:$D$296,$A13,'Master data'!$C$2:$C$296,D$3) -> 0 | E13: =SUMIFS('Master data'!$M$2:$M$296,'Master data'!$D$2:$D$296,$A13,'Master data'!$C$2:$C$296,E$3) -> 0 | F13: =SUMIFS('Master data'!$M$2:$M$296,'Master data'!$D$2:$D$296,$A13,'Master data'!$C$2:$C$296,F$3) -> 1240575 | G13: =SUMIFS('Master data'!$M$2:$M$296,'Master data'!$D$2:$D$296,$A13,'Master data'!$C$2:$C$296,G$3) -> 0 | H13: =SUMIFS('Master data'!$M$2:$M$296,'Master data'!$D$2:$D$296,$A13,'Master data'!$C$2:$C$296,H$3) -> 0 | I13: =SUMIFS('Master data'!$M$2:$M$296,'Master data'!$D$2:$D$296,$A13,'Master data'!$C$2:$C$296,I$3) -> 0 | ... M13: =SUMIFS('Master data'!$M$2:$M$296,'Master data'!$D$2:$D$296,$A13,'Master data'!$C$2:$C$296,M$3) -> 0 | N13: =SUM(B13:M13) -> 7433193
A14: Bharat Innovations | B14: =SUMIFS('Master data'!$M$2:$M$296,'Master data'!$D$2:$D$296,$A14,'Master data'!$C$2:$C$296,B$3) -> 0 | C14: =SUMIFS('Master data'!$M$2:$M$296,'Master data'!$D$2:$D$296,$A14,'Master data'!$C$2:$C$296,C$3) -> 3360636 | D14: =SUMIFS('Master data'!$M$2:$M$296,'Master data'!$D$2:$D$296,$A14,'Master data'!$C$2:$C$296,D$3) -> 0 | E14: =SUMIFS('Master data'!$M$2:$M$296,'Master data'!$D$2:$D$296,$A14,'Master data'!$C$2:$C$296,E$3) -> 0 | F14: =SUMIFS('Master data'!$M$2:$M$296,'Master data'!$D$2:$D$296,$A14,'Master data'!$C$2:$C$296,F$3) -> 0 | G14: =SUMIFS('Master data'!$M$2:$M$296,'Master data'!$D$2:$D$296,$A14,'Master data'!$C$2:$C$296,G$3) -> 0 | H14: =SUMIFS('Master data'!$M$2:$M$296,'Master data'!$D$2:$D$296,$A14,'Master data'!$C$2:$C$296,H$3) -> 0 | I14: =SUMIFS('Master data'!$M$2:$M$296,'Master data'!$D$2:$D$296,$A14,'Master data'!$C$2:$C$296,I$3) -> 0 | ... M14: =SUMIFS('Master data'!$M$2:$M$296,'Master data'!$D$2:$D$296,$A14,'Master data'!$C$2:$C$296,M$3) -> 0 | N14: =SUM(B14:M14) -> 3360636
A15: Bright Future Academy | B15: =SUMIFS('Master data'!$M$2:$M$296,'Master data'!$D$2:$D$296,$A15,'Master data'!$C$2:$C$296,B$3) -> 0 | C15: =SUMIFS('Master data'!$M$2:$M$296,'Master data'!$D$2:$D$296,$A15,'Master data'!$C$2:$C$296,C$3) -> 0 | D15: =SUMIFS('Master data'!$M$2:$M$296,'Master data'!$D$2:$D$296,$A15,'Master data'!$C$2:$C$296,D$3) -> 0 | E15: =SUMIFS('Master data'!$M$2:$M$296,'Master data'!$D$2:$D$296,$A15,'Master data'!$C$2:$C$296,E$3) -> 0 | F15: =SUMIFS('Master data'!$M$2:$M$296,'Master data'!$D$2:$D$296,$A15,'Master data'!$C$2:$C$296,F$3) -> 13416410 | G15: =SUMIFS('Master data'!$M$2:$M$296,'Master data'!$D$2:$D$296,$A15,'Master data'!$C$2:$C$296,G$3) -> 0 | H15: =SUMIFS('Master data'!$M$2:$M$296,'Master data'!$D$2:$D$296,$A15,'Master data'!$C$2:$C$296,H$3) -> 0 | I15: =SUMIFS('Master data'!$M$2:$M$296,'Master data'!$D$2:$D$296,$A15,'Master data'!$C$2:$C$296,I$3) -> 0 | ... M15: =SUMIFS('Master data'!$M$2:$M$296,'Master data'!$D$2:$D$296,$A15,'Master data'!$C$2:$C$296,M$3) -> 0 | N15: =SUM(B15:M15) -> 13416410
... A150: Zenith Tech Solutions | B150: =SUMIFS('Master data'!$M$2:$M$296,'Master data'!$D$2:$D$296,$A150,'Master data'!$C$2:$C$296,B$3) -> 0 | C150: =SUMIFS('Master data'!$M$2:$M$296,'Master data'!$D$2:$D$296,$A150,'Master data'!$C$2:$C$296,C$3) -> 0 | D150: =SUMIFS('Master data'!$M$2:$M$296,'Master data'!$D$2:$D$296,$A150,'Master data'!$C$2:$C$296,D$3) -> 0 | E150: =SUMIFS('Master data'!$M$2:$M$296,'Master data'!$D$2:$D$296,$A150,'Master data'!$C$2:$C$296,E$3) -> 0 | F150: =SUMIFS('Master data'!$M$2:$M$296,'Master data'!$D$2:$D$296,$A150,'Master data'!$C$2:$C$296,F$3) -> 0 | G150: =SUMIFS('Master data'!$M$2:$M$296,'Master data'!$D$2:$D$296,$A150,'Master data'!$C$2:$C$296,G$3) -> 5145410 | H150: =SUMIFS('Master data'!$M$2:$M$296,'Master data'!$D$2:$D$296,$A150,'Master data'!$C$2:$C$296,H$3) -> 0 | I150: =SUMIFS('Master data'!$M$2:$M$296,'Master data'!$D$2:$D$296,$A150,'Master data'!$C$2:$C$296,I$3) -> 0 | ... M150: =SUMIFS('Master data'!$M$2:$M$296,'Master data'!$D$2:$D$296,$A150,'Master data'!$C$2:$C$296,M$3) -> 0 | N150: =SUM(B150:M150) -> 5145410
A151: Grand Total | B151: =SUM(B4:B150) -> 133167828 | C151: =SUM(C4:C150) -> 109768919 | D151: =SUM(D4:D150) -> 0 | E151: =SUM(E4:E150) -> 129993665 | F151: =SUM(F4:F150) -> 107590190 | G151: =SUM(G4:G150) -> 125417871 | H151: =SUM(H4:H150) -> 106105554 | I151: =SUM(I4:I150) -> 119639104 | ... N151: =SUM(N4:N150) -> 1242096365
